Workbook
Name ___xlnm.Print_Area: 'Cash Flow'!$A$1:$BA$39
Name __xlnm.Print_Area: 'Cash Flow'!$A$1:$BA$39
Name ___xlnm.Print_Area: '4B. Tel. Expense Assumptions'!$B$1:$R$68
Name ___xlnm.Print_Titles: '4B. Tel. Expense Assumptions'!$D:$D
Name __xlnm.Print_Area: '4B. Tel. Expense Assumptions'!$B$1:$R$68
Name __xlnm.Print_Titles: '4B. Tel. Expense Assumptions'!$D:$D
Name ___xlnm.Print_Area: '6B. Pre-Launch Exps. - Detail'!$A$1:$Q$132
Name ___xlnm.Print_Titles: '6B. Pre-Launch Exps. - Detail'!$C:$C
Name __xlnm.Print_Area: '6B. Pre-Launch Exps. - Detail'!$A$1:$Q$132
Name __xlnm.Print_Titles: '6B. Pre-Launch Exps. - Detail'!$C:$C
Name ___xlnm.Print_Area: 'Headcount & Salaries - 2'!$A$1:$BG$84
Name __xlnm.Print_Area: 'Headcount & Salaries - 2'!$A$1:$BG$84
Name ___xlnm.Print_Area: 'Income Statement'!$A$1:$BB$41
Name __xlnm.Print_Area: 'Income Statement'!$A$1:$BB$41
Name ___xlnm.Print_Area: 'Balance Sheet'!$A$1:$BB$45
Name __xlnm.Print_Area: 'Balance Sheet'!$A$1:$BB$45
Name ___xlnm.Print_Area: 'Depreciation & Amortization '!$A$1:$AA$74
Name __xlnm.Print_Area: 'Depreciation & Amortization '!$A$1:$AA$74
Name ___xlnm.Print_Area: Valuation!$A$1:$BB$7
Name __xlnm.Print_Area: Valuation!$A$1:$BB$7
Name ___xlnm.Print_Area: Summary!$A$1:$I$43
Name __xlnm.Print_Area: Summary!$A$1:$I$43

Sheet 1A. Consolidated - FY P&L
B2: PURE TECHNOLOGY INC.
B4: TELEPHONE - HARDWARE & MARKET RESEARCH SERVICES
B6: PROJECTED INCOME STATEMENT
B8: PRE-LAUNCH (MONTHS -12 to -1) AND POST-LAUNCH (YEARS 1 - 5)
B10: AT August 25th, 2025
G11: Consolidated Financials - PT (Core Model), PI, CPG, Camera Commerce, etc
I15: Pre-Launch | J15: Post-Launch
I18: Year 0 | J18: Year 1 | K18: Year 2 | L18: Year 3 | M18: Year 4 | N18: Year 5
I19: Months -12 to -1 | J19: Months 1 - 12 | K19: Months 13 - 24 | L19: Months 25 - 36 | M19: Months 37 - 48 | N19: Months 49 - 60
B23: MOBILE TELEPHONES DEPLOYED
B26: ● | C26: Full-Year Average | I26: - - | J26: ='3C. Tel. - Revenue Drivers - 1 '!V79 | K26: ='3C. Tel. - Revenue Drivers - 1 '!V97 | L26: ='3C. Tel. - Revenue Drivers - 1 '!V115 | M26: ='3C. Tel. - Revenue Drivers - 1 '!V133 | N26: ='3C. Tel. - Revenue Drivers - 1 '!V151
B27: ● | C27: End of Year | I27: - - | J27: ='3C. Tel. - Revenue Drivers - 1 '!V75 | K27: ='3C. Tel. - Revenue Drivers - 1 '!V93 | L27: ='3C. Tel. - Revenue Drivers - 1 '!V111 | M27: ='3C. Tel. - Revenue Drivers - 1 '!V129 | N27: ='3C. Tel. - Revenue Drivers - 1 '!V147
B29: REVENUE
B31: ● | C31: Hardware Subsidies* | I31: ='2A. Cash Forecast'!V25+'2A. Cash Forecast'!S29 | J31: ='3B. Tel. - Rev. Detail x Month'!W55 | K31: ='3B. Tel. - Rev. Detail x Month'!W93 | L31: ='3B. Tel. - Rev. Detail x Month'!W131 | M31: ='3B. Tel. - Rev. Detail x Month'!W169 | N31: ='3B. Tel. - Rev. Detail x Month'!W207
B32: ● | C32: Total Revenue, Market Research Services / Core Model | I32: 0 | J32: ='3B. Tel. - Rev. Detail x Month'!W296 | K32: ='3B. Tel. - Rev. Detail x Month'!W328 | L32: ='3B. Tel. - Rev. Detail x Month'!W360 | M32: ='3B. Tel. - Rev. Detail x Month'!W392 | N32: ='3B. Tel. - Rev. Detail x Month'!W424
B33: ● | C33: Total Revenue, Pure Influence | I33: ='2A. Cash Forecast'!V27 | J33: ='2A. Cash Forecast'!AK27 | K33: ='2A. Cash Forecast'!AZ27 | L33: ='2A. Cash Forecast'!BO27 | M33: ='2A. Cash Forecast'!CD27 | N33: ='2A. Cash Forecast'!CS27
B34: ● | C34: Total Revenue, CPG Model | I34: ='2A. Cash Forecast'!V30 | J34: ='2A. Cash Forecast'!AK30 | K34: ='2A. Cash Forecast'!AZ30 | L34: ='2A. Cash Forecast'!BO30 | M34: ='2A. Cash Forecast'!CD30 | N34: ='2A. Cash Forecast'!CS30
B35: ● | C35: Total Revenue, Camera Commerce | I35: ='2A. Cash Forecast'!V31 | J35: ='2A. Cash Forecast'!AK31 | K35: ='2A. Cash Forecast'!AZ31 | L35: ='2A. Cash Forecast'!BO31 | M35: ='2A. Cash Forecast'!CD31 | N35: ='2A. Cash Forecast'!CS31
B36: ● | C36: Total Revenue, Pure Research | I36: ='2A. Cash Forecast'!V28 | J36: ='8. Pure Research - 1 of 2'!N36 | K36: ='8. Pure Research - 1 of 2'!S36 | L36: ='8. Pure Research - 1 of 2'!X36 | M36: ='8. Pure Research - 1 of 2'!AC36 | N36: ='8. Pure Research - 1 of 2'!AH36
B37: ● | C37: Total Revenue, PureBrain | I37: =+'11. PureBrain'!I22 | J37: =+'11. PureBrain'!J22 | K37: =+'11. PureBrain'!K22 | L37: =+'11. PureBrain'!L22 | M37: =+'11. PureBrain'!M22 | N37: =+'11. PureBrain'!N22
D40: TOTAL REVENUE | I40: =SUM(I31:I37) | J40: =SUM(J31:J37) | K40: =SUM(K31:K37) | L40: =SUM(L31:L37) | M40: =SUM(M31:M37) | N40: =SUM(N31:N37)
B42: COST OF GOODS SOLD
B43: ● | C43: Hardware COGS | I43: ='6A. Pre-Launch Exps. - Roll-Up'!X41+'2A. Cash Forecast'!T49 | J43: ='3B. Tel. - Rev. Detail x Month'!W62+'3B. Tel. - Rev. Detail x Month'!W75 | K43: ='3B. Tel. - Rev. Detail x Month'!W100+'3B. Tel. - Rev. Detail x Month'!W109+'3B. Tel. - Rev. Detail x Month'!W113 | L43: ='3B. Tel. - Rev. Detail x Month'!W138+'3B. Tel. - Rev. Detail x Month'!W147+'3B. Tel. - Rev. Detail x Month'!W151 | M43: ='3B. Tel. - Rev. Detail x Month'!W176+'3B. Tel. - Rev. Detail x Month'!W185+'3B. Tel. - Rev. Detail x Month'!W189 | N43: ='3B. Tel. - Rev. Detail x Month'!W214+'3B. Tel. - Rev. Detail x Month'!W223+'3B. Tel. - Rev. Detail x Month'!W227
B44: ● | C44: PureBrain COGS | I44: =+'11. PureBrain'!I27 | J44: =+'11. PureBrain'!J27 | K44: =+'11. PureBrain'!K27 | L44: =+'11. PureBrain'!L27 | M44: =+'11. PureBrain'!M27 | N44: =+'11. PureBrain'!N27
C45: COGS | I45: =I43+I44 | J45: =J43+J44 | K45: =K43+K44 | L45: =L43+L44 | M45: =M43+M44 | N45: =N43+N44
B47: NET OPERATING MARGIN | I47: =I39-I43 | J47: =J39-J43 | K47: =K39-K43 | L47: =L39-L43 | M47: =M39-M43 | N47: =N39-N43
B49: OPERATING EXPENSES | P49: % of Total Revenue
B52: ● | C52: People Cost (Salaries, ER Taxes, Benefits) | I52: ='6A. Pre-Launch Exps. - Roll-Up'!X35 | J52: ='4A. Tel. - Exps. & OI x Month'!AA41 | K52: ='4A. Tel. - Exps. & OI x Month'!Y133 | L52: ='4A. Tel. - Exps. & OI x Month'!Y225 | M52: ='4A. Tel. - Exps. & OI x Month'!Y317 | N52: ='4A. Tel. - Exps. & OI x Month'!Y409 | P52: =J52/J40 | Q52: =K52/K40 | R52: =L52/L40 | S52: =M52/M40 | T52: =N52/N40
B53: ● | C53: Research and Development | I53: ='6A. Pre-Launch Exps. - Roll-Up'!X39 | J53: ='4A. Tel. - Exps. & OI x Month'!Y45 | K53: ='4A. Tel. - Exps. & OI x Month'!Y137 | L53: ='4A. Tel. - Exps. & OI x Month'!Y229 | M53: ='4A. Tel. - Exps. & OI x Month'!Y321 | N53: ='4A. Tel. - Exps. & OI x Month'!Y413 | P53: =J53/J$40 | Q53: =K53/K$40 | R53: =L53/L$40 | S53: =M53/M$40 | T53: =N53/N$40
B54: ● | C54: Sales and Marketing | I54: ='6A. Pre-Launch Exps. - Roll-Up'!X53 | J54: ='4A. Tel. - Exps. & OI x Month'!Y54 | K54: ='4A. Tel. - Exps. & OI x Month'!Y146 | L54: ='4A. Tel. - Exps. & OI x Month'!Y238 | M54: ='4A. Tel. - Exps. & OI x Month'!Y330 | N54: ='4A. Tel. - Exps. & OI x Month'!Y422 | P54: =J54/J$40 | Q54: =K54/K$40 | R54: =L54/L$40 | S54: =M54/M$40 | T54: =N54/N$40
B55: ● | C55: Occupancy | I55: ='6A. Pre-Launch Exps. - Roll-Up'!X62 | J55: ='4A. Tel. - Exps. & OI x Month'!Y63 | K55: ='4A. Tel. - Exps. & OI x Month'!Y155 | L55: ='4A. Tel. - Exps. & OI x Month'!Y247 | M55: ='4A. Tel. - Exps. & OI x Month'!Y339 | N55: ='4A. Tel. - Exps. & OI x Month'!Y431 | P55: =J55/J$40 | Q55: =K55/K$40 | R55: =L55/L$40 | S55: =M55/M$40 | T55: =N55/N$40
B56: ● | C56: General and Administrative | I56: ='6A. Pre-Launch Exps. - Roll-Up'!X87 | J56: ='4A. Tel. - Exps. & OI x Month'!Y84 | K56: ='4A. Tel. - Exps. & OI x Month'!Y176 | L56: ='4A. Tel. - Exps. & OI x Month'!Y268 | M56: ='4A. Tel. - Exps. & OI x Month'!Y360 | N56: ='4A. Tel. - Exps. & OI x Month'!Y452 | P56: =J56/J$40 | Q56: =K56/K$40 | R56: =L56/L$40 | S56: =M56/M$40 | T56: =N56/N$40
B57: ● | C57: Customer Rewards | I57: ='2A. Cash Forecast'!V53 | J57: ='2A. Cash Forecast'!AK53 | K57: ='2A. Cash Forecast'!AZ53 | L57: ='2A. Cash Forecast'!BO53 | M57: ='2A. Cash Forecast'!CD53 | N57: ='2A. Cash Forecast'!CS53 | P57: =J57/J$40 | Q57: =K57/K$40 | R57: =L57/L$40 | S57: =M57/M$40 | T57: =N57/N$40
B58: ● | C58: Pure Influence Expenses | I58: ='2A. Cash Forecast'!V56 | J58: ='2A. Cash Forecast'!AK56 | K58: ='2A. Cash Forecast'!AZ56 | L58: ='2A. Cash Forecast'!BO56 | M58: ='2A. Cash Forecast'!CD56 | N58: ='2A. Cash Forecast'!CS56 | P58: =J58/J$40 | Q58: =K58/K$40 | R58: =L58/L$40 | S58: =M58/M$40 | T58: =N58/N$40
B59: ● | C59: CPG Model - Expenses | I59: ='2A. Cash Forecast'!V57 | J59: ='2A. Cash Forecast'!AK57 | K59: ='2A. Cash Forecast'!AZ57 | L59: ='2A. Cash Forecast'!BO57 | M59: ='2A. Cash Forecast'!CD57 | N59: ='2A. Cash Forecast'!CS57 | P59: =J59/J$40 | Q59: =K59/K$40 | R59: =L59/L$40 | S59: =M59/M$40 | T59: =N59/N$40
B60: ● | C60: Camera Commerce - Expenses | I60: ='2A. Cash Forecast'!V58 | J60: ='2A. Cash Forecast'!AK58 | K60: ='2A. Cash Forecast'!AZ58 | L60: ='2A. Cash Forecast'!BO58 | M60: ='2A. Cash Forecast'!CD58 | N60: ='2A. Cash Forecast'!CS58 | P60: =J60/J$40 | Q60: =K60/K$40 | R60: =L60/L$40 | S60: =M60/M$40 | T60: =N60/N$40
B61: ● | C61: Capital Expenditures | I61: ='2A. Cash Forecast'!V55 | J61: ='2A. Cash Forecast'!AK55 | K61: ='2A. Cash Forecast'!AZ55 | L61: ='2A. Cash Forecast'!BO55 | M61: ='2A. Cash Forecast'!CD55 | N61: ='2A. Cash Forecast'!CS55 | P61: =J61/J$40 | Q61: =K61/K$40 | R61: =L61/L$40 | S61: =M61/M$40 | T61: =N61/N$40
B62: ● | C62: One Time Legacy Expenses + Strategic Investments | I62: ='2A. Cash Forecast'!V44+'2A. Cash Forecast'!V45+'2A. Cash Forecast'!V54+'2A. Cash Forecast'!V46 | J62: ='2A. Cash Forecast'!AK46 | K62: ='2A. Cash Forecast'!AZ46+'2A. Cash Forecast'!AZ59 | L62: ='2A. Cash Forecast'!BO46 | M62: ='2A. Cash Forecast'!CD46 | N62: ='2A. Cash Forecast'!CS46 | P62: =J62/J$40 | Q62: =K62/K$40 | R62: =L62/L$40 | S62: =M62/M$40 | T62: =N62/N$40
B63: ● | C63: PureBrain Operating Expenses | I63: =+'11. PureBrain'!I38 | J63: =+'11. PureBrain'!J38 | K63: =+'11. PureBrain'!K38 | L63: =+'11. PureBrain'!L38 | M63: =+'11. PureBrain'!M38 | N63: =+'11. PureBrain'!N38 | P63: =J63/J$40 | Q63: =K63/K$40 | R63: =L63/L$40 | S63: =M63/M$40 | T63: =N63/N$40
D66: TOTAL OPERATING EXPENSES | I66: =SUM(I50:I60)+I63 | J66: =SUM(J50:J60)+J63 | K66: =SUM(K50:K60)+K63 | L66: =SUM(L50:L60)+L63 | M66: =SUM(M50:M60)+M63 | N66: =SUM(N50:N60)+N63 | P66: =J63/J$39 | Q66: =K63/K$39 | R66: =L63/L$39 | S66: =M63/M$39 | T66: =N63/N$39
P71: =SUM(P50:P60) | Q71: =SUM(Q50:Q60) | R71: =SUM(R50:R60) | S71: =SUM(S50:S60) | T71: =SUM(T50:T60) | U71: Checked
E72: EBITDA/OPERATING INCOME / (LOSS), $ | I72: =((I45)-(I63)) | J72: =((J45)-(J63)) | K72: =((K45)-(K63)) | L72: =((L45)-(L63)) | M72: =((M45)-(M63)) | N72: =((N45)-(N63))
E73: EBIDA/OPERATING MARGIN, % | I73: =((I72)/(I40)) | J73: =((J72)/(J40)) | K73: =((K72)/(K40)) | L73: =((L72)/(L40)) | M73: =((M72)/(M40)) | N73: =((N72)/(N40))
G75: Expense per phone | J75: =(J43+J52+J53+J54+J55+J56+J61)/J27 | K75: =(K43+K52+K53+K54+K55+K56+K61)/K27 | L75: =(L43+L52+L53+L54+L55+L56+L61)/L27 | M75: =(M43+M52+M53+M54+M55+M56+M61)/M27 | N75: =(N43+N52+N53+N54+N55+N56+N61)/N27 | U75: Use of Funds
G76: Revenue per phone | J76: =(J31+J32+J36)/J27 | K76: =(K31+K32+K36)/K27 | L76: =(L31+L32+L36)/L27 | M76: =(M31+M32+M36)/M27 | N76: =(N31+N32+N36)/N27 | U76: People Cost (Salaries, ER Taxes, Benefits) | W76: =I50/25000000
G77: Profit per phone | J77: =J76-J75 | K77: =K76-K75 | L77: =L76-L75 | M77: =M76-M75 | N77: =N76-N75 | U77: Research and Development | W77: =I51/25000000
U78: Sales and Marketing | W78: =I52/25000000
D79: Total Expenses Check | I79: ='6A. Pre-Launch Exps. - Roll-Up'!X94+'2A. Cash Forecast'!V44+'2A. Cash Forecast'!V45+'2A. Cash Forecast'!V46+'2A. Cash Forecast'!V49+'2A. Cash Forecast'!V54+'2A. Cash Forecast'!V55+'2A. Cash Forecast'!V56+'2A. Cash Forecast'!V57+'2A. Cash Forecast'!V58+'2A. Cash Forecast'!V59+'2A. Cash Forecast'!V60 | J79: ='4A. Tel. - Exps. & OI x Month'!Y91+'2A. Cash Forecast'!AK44+'2A. Cash Forecast'!AK45+'2A. Cash Forecast'!AK46++'2A. Cash Forecast'!AK49+'2A. Cash Forecast'!AK54+'2A. Cash Forecast'!AK55+'2A. Cash Forecast'!AK56+'2A. Cash Forecast'!AK57+'2A. Cash Forecast'!AK58+'2A. Cash Forecast'!AK59+'2A. Cash Forecast'!AK60+'2A. Cash Forecast'!AK53 | K79: ='4A. Tel. - Exps. & OI x Month'!Y183+'2A. Cash Forecast'!AZ44+'2A. Cash Forecast'!AZ45+'2A. Cash Forecast'!AZ46++'2A. Cash Forecast'!AZ49+'2A. Cash Forecast'!AZ54+'2A. Cash Forecast'!AZ55+'2A. Cash Forecast'!AZ56+'2A. Cash Forecast'!AZ57+'2A. Cash Forecast'!AZ58+'2A. Cash Forecast'!AZ59+'2A. Cash Forecast'!AZ60+'2A. Cash Forecast'!AZ53 | L79: ='4A. Tel. - Exps. & OI x Month'!Y275+'2A. Cash Forecast'!BO44+'2A. Cash Forecast'!BO45+'2A. Cash Forecast'!BO46+'2A. Cash Forecast'!BO49+'2A. Cash Forecast'!BO54+'2A. Cash Forecast'!BO55+'2A. Cash Forecast'!BO56+'2A. Cash Forecast'!BO57+'2A. Cash Forecast'!BO58+'2A. Cash Forecast'!BO59+'2A. Cash Forecast'!BO60+'2A. Cash Forecast'!BO53 | M79: ='4A. Tel. - Exps. & OI x Month'!Y367+'2A. Cash Forecast'!CD44+'2A. Cash Forecast'!CD45+'2A. Cash Forecast'!CD46+'2A. Cash Forecast'!CD49+'2A. Cash Forecast'!CD53+'2A. Cash Forecast'!CD54+'2A. Cash Forecast'!CD55+'2A. Cash Forecast'!CD56+'2A. Cash Forecast'!CD57+'2A. Cash Forecast'!CD58+'2A. Cash Forecast'!CD59+'2A. Cash Forecast'!CD60 | N79: ='4A. Tel. - Exps. & OI x Month'!Y459+'2A. Cash Forecast'!CS44+'2A. Cash Forecast'!CS45+'2A. Cash Forecast'!CS46+'2A. Cash Forecast'!CS49+'2A. Cash Forecast'!CS53+'2A. Cash Forecast'!CS55+'2A. Cash Forecast'!CS56+'2A. Cash Forecast'!CS57+'2A. Cash Forecast'!CS58 | U79: Occupancy | W79: =I53/25000000
J80: =J63+'2A. Cash Forecast'!AK49 | K80: =K63+'2A. Cash Forecast'!AZ49 | L80: =L63+'2A. Cash Forecast'!BO49+'2A. Cash Forecast'!BO59 | M80: =M63+'2A. Cash Forecast'!CD49+'2A. Cash Forecast'!CD59 | N80: =N63+'2A. Cash Forecast'!CS49+'2A. Cash Forecast'!CS59 | U80: General and Administrative | W80: =I54/25000000
J81: ='2A. Cash Forecast'!AK69 | K81: ='2A. Cash Forecast'!AZ69 | L81: ='2A. Cash Forecast'!BO69 | M81: ='2A. Cash Forecast'!CD69 | N81: ='2A. Cash Forecast'!CS69 | U81: Customer Rewards | W81: =I55/25000000
D82: Total Expenses double checked against forecast | I82: =I43+I63 | J82: =J43+J63 | K82: =K43+K63 | L82: =L43+L63 | M82: =M43+M63 | N82: =N43+N63 | U82: Capital Expenditures | W82: =I56/25000000
D83: Total Ops Income/(Loss) checked against forecast | I83: ='2A. Cash Forecast'!V72 | J83: ='2A. Cash Forecast'!AK72 | K83: ='2A. Cash Forecast'!AZ72 | L83: ='2A. Cash Forecast'!BO72 | M83: ='2A. Cash Forecast'!CD72 | N83: ='2A. Cash Forecast'!CS72 | U83: Strategic Investments | W83: ='2A. Cash Forecast'!#REF!/25000000
J84: =K81 | U84: One Time Legacy Expenses + Strategic Investments | W84: =('2A. Cash Forecast'!#REF!+'2A. Cash Forecast'!#REF!+'2A. Cash Forecast'!#REF!)/25000000
B85: * | D85: In Years 1 and 2, it is expected that distribution of proprietary Pure Technology mobile telephones ('Hardware') will be fully funded by early-adopter brands and/or our go to market strategy and that this funding will exceed the Hardware COGS. | W85: =SUM(W73:W81)
E86: From Year 3 onward, legacy users of PT Hardware are provided a new mobile telephone handset at no cost so hardware subsidies become less than hardware COGS from that point onward. | U86: working capital | W86: =100%-W82
E87: New subscribers to our system will still receive phones either subsidized via go-to-market (deployment strategy), or other means.
E88: Only legacy users will receive free hardware without subsidization aside from what the previous device generated.
J90: Net Hardware Revenue or (Cost)
J91: Year 1 | K91: Year 2 | L91: Year 3 | M91: Year 4 | N91: Year 5
J92: =J31-J42 | K92: =K31-K42 | L92: =L31-L42 | M92: =M31-M42 | N92: =N31-N42
G95: Operations Minus People Costs | I95: =I63-I50 | J95: =J63-J50 | K95: =K63-K50 | L95: =L63-L50 | M95: =M63-M50 | N95: =N63-N50 | P95: <-- other costs minus salary
G102: Original Numbers - projects on 7.5 hours per year
G103: Revenue Per phone | J103: =J73 | K103: =J100*1.15 | L103: =K100*1.15 | M103: =L100*1.15 | N103: =M100*1.15
G104: Internal Expense per phone | J104: =J72 | K104: =K72 | L104: =L72 | M104: =M72 | N104: =N72
G105: Revenue share per phone - 10% | J105: =J100*0.1 | K105: =K100*0.1 | L105: =L100*0.1 | M105: =M100*0.1 | N105: =N100*0.1
G106: PT's remaining Profit margin per phone | J106: =J100-(J101+J102) | K106: =K100-(K101+K102) | L106: =L100-(L101+L102) | M106: =M100-(M101+M102) | N106: =N100-(N101+N102)
G107: Operating Margin | J107: =J103/J100 | K107: =K103/K100 | L107: =L103/L100 | M107: =M103/M100 | N107: =N103/N100
G109: 2025 Ed's Numbers - projects on 7.5 hours per year
G110: Revenue Per phone | J110: 2656.42 | K110: =J107*1.15 | L110: =K107*1.15 | M110: =L107*1.15 | N110: =M107*1.15
G111: Internal Expense per phone | J111: =J72 | K111: =K72 | L111: =L72 | M111: =M72 | N111: =N72
G112: Revenue share per phone - 10% | J112: =J107*0.1 | K112: =K107*0.1 | L112: =L107*0.1 | M112: =M107*0.1 | N112: =N107*0.1
G113: PT's remaining Profit margin per phone | J113: =J107-(J108+J109) | K113: =K107-(K108+K109) | L113: =L107-(L108+L109) | M113: =M107-(M108+M109) | N113: =N107-(N108+N109)
G114: Operating Margin | J114: =J110/J107 | K114: =K110/K107 | L114: =L110/L107 | M114: =M110/M107 | N114: =N110/N107
G124: PURE TECH + VSBLTY
I128: Pre-Launch | J128: Post-Launch
I131: Year 0 | J131: Year 1 | K131: Year 2 | L131: Year 3 | M131: Year 4 | N131: Year 5
I132: Months -12 to -1 | J132: Months 1 - 12 | K132: Months 13 - 24 | L132: Months 25 - 36 | M132: Months 37 - 48 | N132: Months 49 - 60
B136: MOBILE TELEPHONES DEPLOYED
B139: ● | C139: Full-Year Average | I139: =I26 | J139: =J26 | K139: =K26 | L139: =L26 | M139: =M26 | N139: =N26
B140: ● | C140: End of Year | I140: =I27 | J140: =J27 | K140: =K27 | L140: =L27 | M140: =M27 | N140: =N27
B142: REVENUE
B144: ● | C144: Hardware Subsidies* | I144: =I31 | J144: =J31 | K144: =K31 | L144: =L31 | M144: =M31 | N144: =N31
B145: ● | C145: Total Gross Revenue, Market Research Services | I145: =I32 | J145: =J32 | K145: =K32 | L145: =L32 | M145: =M32 | N145: =N32
B146: ● | C146: Total Gross Revenue, Pure Influence | I146: =I33 | J146: =J33 | K146: =K33 | L146: =L33 | M146: =M33 | N146: =N33
B147: ● | C147: Total Gross Revenue, Pure Research | I147: =I36 | J147: =J36 | K147: =K36 | L147: =L36 | M147: =M36 | N147: =N36
B148: ● | C148: Total Gross Revenue, VSBLTY / Pure Vision | I148: ='[1]P&L Projection Quarterly'!$K$51 | J148: ='[1]P&L Projection Quarterly'!$P$51 | K148: =J145*1.25 | L148: =K145*1.25 | M148: =L145*1.25 | N148: =M145*1.25
D150: TOTAL NET REVENUE | I150: =SUM(I141:I146) | J150: =SUM(J141:J146) | K150: =SUM(K141:K146) | L150: =SUM(L141:L146) | M150: =SUM(M141:M146) | N150: =SUM(N141:N146)
B152: COST OF GOODS SOLD
B153: ● | C153: Hardware COGS | I153: =I42 | J153: =J42 | K153: =K42 | L153: =L42 | M153: =M42 | N153: =N42
B154: ● | C154: Pure Influence COGS | I154: =I56 | J154: =J56 | K154: =K56 | L154: =L56 | M154: =M56 | N154: =N56
B155: ● | C155: VSBLTY / Pure Vision COGS | I155: ='[1]P&L Projection Quarterly'!$K$57 | J155: ='[1]P&L Projection Quarterly'!$P$57 | K155: =J152*1.25 | L155: =K152*1.25 | M155: =L152*1.25 | N155: =M152*1.25
C156: COGS | I156: =I150+I151+(-I152) | J156: =J150+J151+(-J152) | K156: =K150+K151+(-K152) | L156: =L150+L151+(-L152) | M156: =M150+M151+(-M152) | N156: =N150+N151+(-N152)
B157: NET OPERATING MARGIN | I157: =I147-I153 | J157: =J147-J153 | K157: =K147-K153 | L157: =L147-L153 | M157: =M147-M153 | N157: =N147-N153
B159: OPERATING EXPENSES
B162: ● | C162: People Cost (Salaries, ER Taxes, Benefits) | I162: =I50 | J162: =J50 | K162: =K50 | L162: =L50 | M162: =M50 | N162: =N50
B163: ● | C163: Research and Development | I163: =I51 | J163: =J51 | K163: =K51 | L163: =L51 | M163: =M51 | N163: =N51
B164: ● | C164: Sales and Marketing | I164: =I52 | J164: =J52 | K164: =K52 | L164: =L52 | M164: =M52 | N164: =N52
B165: ● | C165: Occupancy | I165: =I53 | J165: =J53 | K165: =K53 | L165: =L53 | M165: =M53 | N165: =N53
B166: ● | C166: General and Administrative | I166: =I60 | J166: =J60 | K166: =K60 | L166: =L60 | M166: =M60 | N166: =N60
B167: ● | C167: VSBLTY / Pure Vision Operating Expenses | I167: 5928357 | J167: 6243213 | K167: =J164*1.15 | L167: =K164*1.15 | M167: =L164*1.15 | N167: =M164*1.15
...

Sheet 2A. Cash Forecast
B2: PURE TECHNOLOGY INC.
B4: CASH FORECAST
B6: BY MONTH, MONTHS -12 THROUGH -1 AND MONTHS 1 - 60
B8: AT August 25th, 2025
I13: Pre-Launch (Twelve Months) | X13: Post-Launch | AM13: Post-Launch | BB13: Post-Launch | BQ13: Post-Launch | CF13: Post-Launch
I16: Month | J16: Month | K16: Month | L16: Month | M16: Month | N16: Month | O16: Month | P16: Month | Q16: Month | R16: Month | S16: Month | T16: Month | V16: Total | X16: Month | Y16: Month | Z16: Month | AA16: Month | AB16: Month | AC16: Month | AD16: Month | AE16: Month | AF16: Month | AG16: Month | AH16: Month | AI16: Month | AK16: Total | AM16: Month | AN16: Month | AO16: Month | AP16: Month | AQ16: Month | AR16: Month | AS16: Month | AT16: Month | AU16: Month | AV16: Month | AW16: Month | AX16: Month | AZ16: Total | BB16: Month | BC16: Month | BD16: Month | BE16: Month | BF16: Month | BG16: Month | BH16: Month | BI16: Month | BJ16: Month | BK16: Month | BL16: Month | BM16: Month | BO16: Total | BQ16: Month | BR16: Month | BS16: Month | BT16: Month | BU16: Month | BV16: Month | BW16: Month | BX16: Month | BY16: Month | BZ16: Month | CA16: Month | CB16: Month | CD16: Total | CF16: Month | CG16: Month | CH16: Month | CI16: Month | CJ16: Month | CK16: Month | CL16: Month | CM16: Month | CN16: Month | CO16: Month | CP16: Month | CQ16: Month | CS16: Total
I17: -12 | J17: -11 | K17: -10 | L17: -9 | M17: =((L17)+(1)) | N17: =((M17)+(1)) | O17: =((N17)+(1)) | P17: =((O17)+(1)) | Q17: =((P17)+(1)) | R17: =((Q17)+(1)) | S17: =((R17)+(1)) | T17: =((S17)+(1)) | V17: Months -12 to -1 | X17: 1 | Y17: =((X17)+(1)) | Z17: =((Y17)+(1)) | AA17: =((Z17)+(1)) | AB17: =((AA17)+(1)) | AC17: =((AB17)+(1)) | AD17: =((AC17)+(1)) | AE17: =((AD17)+(1)) | AF17: =((AE17)+(1)) | ... AI17: =((AH17)+(1)) | AK17: Months 1 - 12 | AM17: 13 | AN17: =((AM17)+(1)) | AO17: =((AN17)+(1)) | AP17: =((AO17)+(1)) | AQ17: =((AP17)+(1)) | AR17: =((AQ17)+(1)) | AS17: =((AR17)+(1)) | AT17: =((AS17)+(1)) | AU17: =((AT17)+(1)) | ... AX17: =((AW17)+(1)) | AZ17: Months 13 - 24 | BB17: 25 | BC17: =((BB17)+(1)) | BD17: =((BC17)+(1)) | BE17: =((BD17)+(1)) | BF17: =((BE17)+(1)) | BG17: =((BF17)+(1)) | BH17: =((BG17)+(1)) | BI17: =((BH17)+(1)) | BJ17: =((BI17)+(1)) | ... BM17: =((BL17)+(1)) | BO17: Months 25 - 36 | BQ17: 37 | BR17: =((BQ17)+(1)) | BS17: =((BR17)+(1)) | BT17: =((BS17)+(1)) | BU17: =((BT17)+(1)) | BV17: =((BU17)+(1)) | BW17: =((BV17)+(1)) | BX17: =((BW17)+(1)) | BY17: =((BX17)+(1)) | ... CB17: =((CA17)+(1)) | CD17: Months 37 - 48 | CF17: 49 | CG17: =((CF17)+(1)) | CH17: =((CG17)+(1)) | CI17: =((CH17)+(1)) | CJ17: =((CI17)+(1)) | CK17: =((CJ17)+(1)) | CL17: =((CK17)+(1)) | CM17: =((CL17)+(1)) | CN17: =((CM17)+(1)) | ... CQ17: =((CP17)+(1)) | CS17: Months 49 - 60
B21: Beginning Balance | I21: =20000000+1000 | J21: =(I73) | K21: =(J73) | L21: =(K73) | M21: =(L73) | N21: =(M73) | O21: =(N73) | P21: =(O73) | Q21: =(P73) | ... T21: =(S73) | V21: =(I21) | X21: =(T73) | Y21: =(X73) | Z21: =(Y73) | AA21: =(Z73) | AB21: =(AA73) | AC21: =(AB73) | AD21: =(AC73) | AE21: =(AD73) | AF21: =(AE73) | ... AI21: =(AH73) | AK21: =(X21) | AM21: =(AI73) | AN21: =(AM73) | AO21: =(AN73) | AP21: =(AO73) | AQ21: =(AP73) | AR21: =(AQ73) | AS21: =(AR73) | AT21: =(AS73) | AU21: =(AT73) | ... AX21: =(AW73) | AZ21: =(AM21) | BB21: =(AX73) | BC21: =(BB73) | BD21: =(BC73) | BE21: =(BD73) | BF21: =(BE73) | BG21: =(BF73) | BH21: =(BG73) | BI21: =(BH73) | BJ21: =(BI73) | ... BM21: =(BL73) | BO21: =(BB21) | BQ21: =(BM73) | BR21: =(BQ73) | BS21: =(BR73) | BT21: =(BS73) | BU21: =(BT73) | BV21: =(BU73) | BW21: =(BV73) | BX21: =(BW73) | BY21: =(BX73) | ... CB21: =(CA73) | CD21: =(BQ21) | CF21: =(CB73) | CG21: =(CF73) | CH21: =(CG73) | CI21: =(CH73) | CJ21: =(CI73) | CK21: =(CJ73) | CL21: =(CK73) | CM21: =(CL73) | CN21: =(CM73) | ... CQ21: =(CP73) | CS21: =(CF21)
B24: Cash Receipts
B25: ● | C25: Telephone Sales | I25: ='2B. Cash Collections'!I20 | J25: ='2B. Cash Collections'!J20 | K25: ='2B. Cash Collections'!K20 | L25: ='2B. Cash Collections'!L20 | M25: ='2B. Cash Collections'!M20 | N25: ='2B. Cash Collections'!N20 | O25: ='2B. Cash Collections'!O20 | P25: ='2B. Cash Collections'!P20 | ... T25: ='2B. Cash Collections'!T20 | V25: =SUM(I25:T25) | X25: ='2B. Cash Collections'!X20 | Y25: ='2B. Cash Collections'!Y20 | Z25: ='2B. Cash Collections'!Z20 | AA25: ='2B. Cash Collections'!AA20 | AB25: ='2B. Cash Collections'!AB20 | AC25: ='2B. Cash Collections'!AC20 | AD25: ='2B. Cash Collections'!AD20 | AE25: ='2B. Cash Collections'!AE20 | ... AI25: ='2B. Cash Collections'!AI20 | AK25: =SUM(X25:AI25) | AM25: ='2B. Cash Collections'!AM20 | AN25: ='2B. Cash Collections'!AN20 | AO25: ='2B. Cash Collections'!AO20 | AP25: ='2B. Cash Collections'!AP20 | AQ25: ='2B. Cash Collections'!AQ20 | AR25: ='2B. Cash Collections'!AR20 | AS25: ='2B. Cash Collections'!AS20 | AT25: ='2B. Cash Collections'!AT20 | ... AX25: ='2B. Cash Collections'!AX20 | AZ25: =SUM(AM25:AX25) | BB25: ='2B. Cash Collections'!BB20 | BC25: ='2B. Cash Collections'!BC20 | BD25: ='2B. Cash Collections'!BD20 | BE25: ='2B. Cash Collections'!BE20 | BF25: ='2B. Cash Collections'!BF20 | BG25: ='2B. Cash Collections'!BG20 | BH25: ='2B. Cash Collections'!BH20 | BI25: ='2B. Cash Collections'!BI20 | ... BM25: ='2B. Cash Collections'!BM20 | BO25: =SUM(BB25:BM25) | BQ25: ='2B. Cash Collections'!BQ20 | BR25: ='2B. Cash Collections'!BR20 | BS25: ='2B. Cash Collections'!BS20 | BT25: ='2B. Cash Collections'!BT20 | BU25: ='2B. Cash Collections'!BU20 | BV25: ='2B. Cash Collections'!BV20 | BW25: ='2B. Cash Collections'!BW20 | BX25: ='2B. Cash Collections'!BX20 | ... CB25: ='2B. Cash Collections'!CB20 | CD25: =SUM(BQ25:CB25) | CF25: ='2B. Cash Collections'!CF20 | CG25: ='2B. Cash Collections'!CG20 | CH25: ='2B. Cash Collections'!CH20 | CI25: ='2B. Cash Collections'!CI20 | CJ25: ='2B. Cash Collections'!CJ20 | CK25: ='2B. Cash Collections'!CK20 | CL25: ='2B. Cash Collections'!CL20 | CM25: ='2B. Cash Collections'!CM20 | ... CQ25: ='2B. Cash Collections'!CQ20 | CS25: =SUM(CF25:CQ25)
B26: ● | C26: Market Research Services / Core Model | I26: 0 | J26: 0 | K26: 0 | L26: 0 | M26: 0 | N26: 0 | O26: 0 | P26: 0 | Q26: 0 | R26: 0 | S26: 0 | T26: 0 | V26: =SUM(I26:T26) | X26: ='2B. Cash Collections'!X31 | Y26: ='2B. Cash Collections'!Y31 | Z26: ='2B. Cash Collections'!Z31 | AA26: ='2B. Cash Collections'!AA31 | AB26: ='2B. Cash Collections'!AB31 | AC26: ='2B. Cash Collections'!AC31 | AD26: ='2B. Cash Collections'!AD31 | AE26: ='2B. Cash Collections'!AE31 | ... AI26: ='2B. Cash Collections'!AI31 | AK26: =SUM(X26:AI26) | AM26: ='2B. Cash Collections'!AM31 | AN26: ='2B. Cash Collections'!AN31 | AO26: ='2B. Cash Collections'!AO31 | AP26: ='2B. Cash Collections'!AP31 | AQ26: ='2B. Cash Collections'!AQ31 | AR26: ='2B. Cash Collections'!AR31 | AS26: ='2B. Cash Collections'!AS31 | AT26: ='2B. Cash Collections'!AT31 | ... AX26: ='2B. Cash Collections'!AX31 | AZ26: =SUM(AM26:AX26) | BB26: ='2B. Cash Collections'!BB31 | BC26: ='2B. Cash Collections'!BC31 | BD26: ='2B. Cash Collections'!BD31 | BE26: ='2B. Cash Collections'!BE31 | BF26: ='2B. Cash Collections'!BF31 | BG26: ='2B. Cash Collections'!BG31 | BH26: ='2B. Cash Collections'!BH31 | BI26: ='2B. Cash Collections'!BI31 | ... BM26: ='2B. Cash Collections'!BM31 | BO26: =SUM(BB26:BM26) | BQ26: ='2B. Cash Collections'!BQ31 | BR26: ='2B. Cash Collections'!BR31 | BS26: ='2B. Cash Collections'!BS31 | BT26: ='2B. Cash Collections'!BT31 | BU26: ='2B. Cash Collections'!BU31 | BV26: ='2B. Cash Collections'!BV31 | BW26: ='2B. Cash Collections'!BW31 | BX26: ='2B. Cash Collections'!BX31 | ... CB26: ='2B. Cash Collections'!CB31 | CD26: =SUM(BQ26:CB26) | CF26: ='2B. Cash Collections'!CF31 | CG26: ='2B. Cash Collections'!CG31 | CH26: ='2B. Cash Collections'!CH31 | CI26: ='2B. Cash Collections'!CI31 | CJ26: ='2B. Cash Collections'!CJ31 | CK26: ='2B. Cash Collections'!CK31 | CL26: ='2B. Cash Collections'!CL31 | CM26: ='2B. Cash Collections'!CM31 | ... CQ26: ='2B. Cash Collections'!CQ31 | CS26: =SUM(CF26:CQ26)
B27: ● | C27: Pure Influence | I27: 0 | J27: 0 | K27: 0 | L27: 0 | M27: 0 | N27: 0 | O27: 0 | P27: 0 | Q27: ='7. Pure Influence'!G16 | R27: ='7. Pure Influence'!H16 | S27: ='7. Pure Influence'!I16 | T27: ='7. Pure Influence'!J16 | V27: =SUM(I27:T27) | X27: ='7. Pure Influence'!K16 | Y27: ='7. Pure Influence'!L16 | Z27: ='7. Pure Influence'!M16 | AA27: ='7. Pure Influence'!N16 | AB27: =('7. Pure Influence'!O16) | AC27: =('7. Pure Influence'!P16) | AD27: =('7. Pure Influence'!Q16) | AE27: =('7. Pure Influence'!R16) | AF27: ='7. Pure Influence'!G33 | AG27: ='7. Pure Influence'!H33 | AH27: ='7. Pure Influence'!I33 | AI27: ='7. Pure Influence'!J33 | AK27: =SUM(X27:AI27) | AM27: ='7. Pure Influence'!K33 | AN27: ='7. Pure Influence'!L33 | AO27: ='7. Pure Influence'!M33 | AP27: ='7. Pure Influence'!N33 | AQ27: ='7. Pure Influence'!O33 | AR27: ='7. Pure Influence'!P33 | AS27: ='7. Pure Influence'!Q33 | AT27: ='7. Pure Influence'!R33 | AU27: ='7. Pure Influence'!G50 | AV27: ='7. Pure Influence'!H50 | AW27: ='7. Pure Influence'!I50 | AX27: ='7. Pure Influence'!J50 | AZ27: =SUM(AM27:AX27) | BB27: ='7. Pure Influence'!K50 | BC27: ='7. Pure Influence'!L50 | BD27: ='7. Pure Influence'!M50 | BE27: ='7. Pure Influence'!N50 | BF27: ='7. Pure Influence'!O50 | BG27: ='7. Pure Influence'!P50 | BH27: ='7. Pure Influence'!Q50 | BI27: ='7. Pure Influence'!R50 | BJ27: ='7. Pure Influence'!G67 | BK27: ='7. Pure Influence'!H67 | BL27: ='7. Pure Influence'!I67 | BM27: ='7. Pure Influence'!J67 | BO27: =SUM(BB27:BM27) | BQ27: ='7. Pure Influence'!K67 | BR27: ='7. Pure Influence'!L67 | BS27: ='7. Pure Influence'!M67 | BT27: ='7. Pure Influence'!N67 | BU27: ='7. Pure Influence'!O67 | BV27: ='7. Pure Influence'!P67 | BW27: ='7. Pure Influence'!Q67 | BX27: ='7. Pure Influence'!R67 | BY27: ='7. Pure Influence'!G84 | BZ27: ='7. Pure Influence'!H84 | CA27: ='7. Pure Influence'!I84 | CB27: ='7. Pure Influence'!J84 | CD27: =SUM(BQ27:CB27) | CF27: ='7. Pure Influence'!K84 | CG27: ='7. Pure Influence'!L84 | CH27: ='7. Pure Influence'!M84 | CI27: ='7. Pure Influence'!N84 | CJ27: ='7. Pure Influence'!O84 | CK27: ='7. Pure Influence'!P84 | CL27: ='7. Pure Influence'!Q84 | CM27: ='7. Pure Influence'!R84 | CN27: ='7. Pure Influence'!G101 | CO27: ='7. Pure Influence'!H101 | CP27: ='7. Pure Influence'!I101 | CQ27: ='7. Pure Influence'!J101 | CS27: =SUM(CF27:CQ27) | CU27: ='7. Pure Influence'!K101 | CV27: ='7. Pure Influence'!L101 | CW27: ='7. Pure Influence'!M101 | CX27: ='7. Pure Influence'!N101 | CY27: ='7. Pure Influence'!O101 | CZ27: ='7. Pure Influence'!P101 | DA27: ='7. Pure Influence'!Q101 | DB27: ='7. Pure Influence'!R101
B28: ● | C28: Pure Research - this is part of lead gen to distribute phones | I28: 0 | J28: 0 | K28: 0 | L28: 0 | M28: 0 | N28: 0 | O28: =('8. Pure Research - 1 of 2'!$I$40) | P28: =('8. Pure Research - 1 of 2'!$I$40) | Q28: =('8. Pure Research - 1 of 2'!$I$40) | R28: =('8. Pure Research - 1 of 2'!$I$40) | S28: =('8. Pure Research - 1 of 2'!$I$40) | T28: =('8. Pure Research - 1 of 2'!$I$40) | V28: =SUM(I28:T28) | X28: ='8. Pure Research - 1 of 2'!$N$40 | Y28: ='8. Pure Research - 1 of 2'!$N$40 | Z28: ='8. Pure Research - 1 of 2'!$N$40 | AA28: ='8. Pure Research - 1 of 2'!$N$40 | AB28: ='8. Pure Research - 1 of 2'!$N$40 | AC28: ='8. Pure Research - 1 of 2'!$N$40 | AD28: ='8. Pure Research - 1 of 2'!$N$40 | AE28: ='8. Pure Research - 1 of 2'!$N$40 | ... AI28: ='8. Pure Research - 1 of 2'!$N$40 | AK28: =SUM(X28:AI28) | AM28: ='8. Pure Research - 1 of 2'!$S$40 | AN28: ='8. Pure Research - 1 of 2'!$S$40 | AO28: ='8. Pure Research - 1 of 2'!$S$40 | AP28: ='8. Pure Research - 1 of 2'!$S$40 | AQ28: ='8. Pure Research - 1 of 2'!$S$40 | AR28: ='8. Pure Research - 1 of 2'!$S$40 | AS28: ='8. Pure Research - 1 of 2'!$S$40 | AT28: ='8. Pure Research - 1 of 2'!$S$40 | ... AX28: ='8. Pure Research - 1 of 2'!$S$40 | AZ28: =SUM(AM28:AX28) | BB28: ='8. Pure Research - 1 of 2'!$X$40 | BC28: ='8. Pure Research - 1 of 2'!$X$40 | BD28: ='8. Pure Research - 1 of 2'!$X$40 | BE28: ='8. Pure Research - 1 of 2'!$X$40 | BF28: ='8. Pure Research - 1 of 2'!$X$40 | BG28: ='8. Pure Research - 1 of 2'!$X$40 | BH28: ='8. Pure Research - 1 of 2'!$X$40 | BI28: ='8. Pure Research - 1 of 2'!$X$40 | ... BM28: ='8. Pure Research - 1 of 2'!$X$40 | BO28: =SUM(BB28:BM28) | BQ28: ='8. Pure Research - 1 of 2'!$AC$40 | BR28: ='8. Pure Research - 1 of 2'!$AC$40 | BS28: ='8. Pure Research - 1 of 2'!$AC$40 | BT28: ='8. Pure Research - 1 of 2'!$AC$40 | BU28: ='8. Pure Research - 1 of 2'!$AC$40 | BV28: ='8. Pure Research - 1 of 2'!$AC$40 | BW28: ='8. Pure Research - 1 of 2'!$AC$40 | BX28: ='8. Pure Research - 1 of 2'!$AC$40 | ... CB28: ='8. Pure Research - 1 of 2'!$AC$40 | CD28: =SUM(BQ28:CB28) | CF28: ='8. Pure Research - 1 of 2'!$AH$40 | CG28: ='8. Pure Research - 1 of 2'!$AH$40 | CH28: ='8. Pure Research - 1 of 2'!$AH$40 | CI28: ='8. Pure Research - 1 of 2'!$AH$40 | CJ28: ='8. Pure Research - 1 of 2'!$AH$40 | CK28: ='8. Pure Research - 1 of 2'!$AH$40 | CL28: ='8. Pure Research - 1 of 2'!$AH$40 | CM28: ='8. Pure Research - 1 of 2'!$AH$40 | ... CQ28: ='8. Pure Research - 1 of 2'!$AH$40 | CS28: =SUM(CF28:CQ28)
B29: ● | C29: Crowd Funding / Pre Sales / Program Opt Ins | I29: 0 | J29: 0 | K29: 0 | L29: 0 | M29: 0 | N29: 0 | O29: 0 | P29: 0 | Q29: 0 | R29: 0 | S29: ='2D. Crowd Funding'!G13 | T29: 0 | V29: =SUM(I29:T29) | X29: 0 | Y29: 0 | Z29: 0 | AA29: 0 | AB29: 0 | AC29: 0 | AD29: 0 | AE29: 0 | AF29: 0 | AG29: 0 | AH29: 0 | AI29: 0 | AK29: =SUM(X29:AI29) | AM29: 0 | AN29: 0 | AO29: 0 | AP29: 0 | AQ29: 0 | AR29: 0 | AS29: 0 | AT29: 0 | AU29: 0 | AV29: 0 | AW29: 0 | AX29: 0 | AZ29: =SUM(AM29:AX29) | BB29: 0 | BC29: 0 | BD29: 0 | BE29: 0 | BF29: 0 | BG29: 0 | BH29: 0 | BI29: 0 | BJ29: 0 | BK29: 0 | BL29: 0 | BM29: 0 | BO29: =SUM(BB29:BM29) | BQ29: 0 | BR29: 0 | BS29: 0 | BT29: 0 | BU29: 0 | BV29: 0 | BW29: 0 | BX29: 0 | BY29: 0 | BZ29: 0 | CA29: 0 | CB29: 0 | CD29: =SUM(BQ29:CB29) | CF29: 0 | CG29: 0 | CH29: 0 | CI29: 0 | CJ29: 0 | CK29: 0 | CL29: 0 | CM29: 0 | CN29: 0 | CO29: 0 | CP29: 0 | CQ29: 0 | CS29: =SUM(CF29:CQ29)
B30: ● | C30: CPG Model - Revenue | I30: 0 | J30: 0 | K30: 0 | L30: 0 | M30: 0 | N30: 0 | O30: 0 | P30: 0 | Q30: 0 | R30: 0 | S30: =Table13[[#Totals],[Month 1]] | T30: =Table13[[#Totals],[Month 2]] | V30: =SUM(I30:T30) | X30: =Table13[[#Totals],[Month 3]] | Y30: =Table13[[#Totals],[Month 4]] | Z30: =Table13[[#Totals],[Month 5]] | AA30: =Table13[[#Totals],[Month 6]] | AB30: =Table13[[#Totals],[Month 7]] | AC30: =Table13[[#Totals],[Month 8]] | AD30: =Table13[[#Totals],[Month 9]] | AE30: =Table13[[#Totals],[Month 10]] | AF30: =Table13[[#Totals],[Month 11]] | AG30: =Table13[[#Totals],[Month 12]] | AH30: =Table13[[#Totals],[Month 13]] | AI30: =Table13[[#Totals],[Month 14]] | AK30: =SUM(X30:AI30) | AM30: =Table13[[#Totals],[Month 15]] | AN30: =Table13[[#Totals],[Month 16]] | AO30: =Table13[[#Totals],[Month 17]] | AP30: =Table13[[#Totals],[Month 18]] | AQ30: =Table13[[#Totals],[Month 19]] | AR30: =Table13[[#Totals],[Month 20]] | AS30: =Table13[[#Totals],[Month 21]] | AT30: =Table13[[#Totals],[Month 22]] | AU30: =Table13[[#Totals],[Month 23]] | AV30: =Table13[[#Totals],[Month 24]] | AW30: =Table13[[#Totals],[Month 25]] | AX30: =Table13[[#Totals],[Month 26]] | AZ30: =SUM(AM30:AX30) | BB30: =Table13[[#Totals],[Month 27]] | BC30: =Table13[[#Totals],[Month 28]] | BD30: =Table13[[#Totals],[Month 29]] | BE30: =Table13[[#Totals],[Month 30]] | BF30: =Table13[[#Totals],[Month 31]] | BG30: =Table13[[#Totals],[Month 32]] | BH30: =Table13[[#Totals],[Month 33]] | BI30: =Table13[[#Totals],[Month 34]] | BJ30: =Table13[[#Totals],[Month 35]] | BK30: =Table13[[#Totals],[Month 36]] | BL30: =Table13[[#Totals],[Month 37]] | BM30: =Table13[[#Totals],[Month 38]] | BO30: =SUM(BB30:BM30) | BQ30: =Table13[[#Totals],[Month 39]] | BR30: =Table13[[#Totals],[Month 40]] | BS30: =Table13[[#Totals],[Month 41]] | BT30: =Table13[[#Totals],[Month 42]] | BU30: =Table13[[#Totals],[Month 43]] | BV30: =Table13[[#Totals],[Month 44]] | BW30: =Table13[[#Totals],[Month 45]] | BX30: =Table13[[#Totals],[Month 46]] | BY30: =Table13[[#Totals],[Month 47]] | BZ30: =Table13[[#Totals],[Month 48]] | CA30: =Table13[[#Totals],[Month 49]] | CB30: =Table13[[#Totals],[Month 50]] | CD30: =SUM(BQ30:CB30) | CF30: =Table13[[#Totals],[Month 51]] | CG30: =Table13[[#Totals],[Month 52]] | CH30: =Table13[[#Totals],[Month 53]] | CI30: =Table13[[#Totals],[Month 54]] | CJ30: =Table13[[#Totals],[Month 55]] | CK30: =Table13[[#Totals],[Month 56]] | CL30: =Table13[[#Totals],[Month 57]] | CM30: =Table13[[#Totals],[Month 58]] | CN30: =Table13[[#Totals],[Month 59]] | CO30: =Table13[[#Totals],[Month 60]] | CP30: 0 | CQ30: 0 | CS30: =SUM(CF30:CQ30)
B31: ● | C31: Camera Commerce | I31: 0 | J31: 0 | K31: 0 | L31: 0 | M31: 0 | N31: ='9. Camera Commerce'!B6 | O31: ='9. Camera Commerce'!C6 | P31: ='9. Camera Commerce'!D6 | Q31: ='9. Camera Commerce'!E6 | R31: ='9. Camera Commerce'!F6 | S31: ='9. Camera Commerce'!G6 | T31: ='9. Camera Commerce'!H6 | V31: =SUM(I31:T31) | X31: ='9. Camera Commerce'!I6 | Y31: ='9. Camera Commerce'!J6 | Z31: ='9. Camera Commerce'!K6 | AA31: ='9. Camera Commerce'!L6 | AB31: ='9. Camera Commerce'!M6 | AC31: ='9. Camera Commerce'!O6 | AD31: ='9. Camera Commerce'!P6 | AE31: ='9. Camera Commerce'!Q6 | AF31: ='9. Camera Commerce'!R6 | AG31: ='9. Camera Commerce'!S6 | AH31: ='9. Camera Commerce'!T6 | AI31: ='9. Camera Commerce'!U6 | AK31: =SUM(X31:AI31) | AM31: ='9. Camera Commerce'!V6 | AN31: ='9. Camera Commerce'!W6 | AO31: ='9. Camera Commerce'!X6 | AP31: ='9. Camera Commerce'!Y6 | AQ31: ='9. Camera Commerce'!Z6 | AR31: ='9. Camera Commerce'!AB6 | AS31: ='9. Camera Commerce'!AC6 | AT31: ='9. Camera Commerce'!AD6 | AU31: ='9. Camera Commerce'!AE6 | AV31: ='9. Camera Commerce'!AF6 | AW31: ='9. Camera Commerce'!AG6 | AX31: ='9. Camera Commerce'!AH6 | AZ31: =SUM(AM31:AX31) | BB31: ='9. Camera Commerce'!AI6 | BC31: ='9. Camera Commerce'!AJ6 | BD31: ='9. Camera Commerce'!AK6 | BE31: ='9. Camera Commerce'!AL6 | BF31: ='9. Camera Commerce'!AM6 | BG31: ='9. Camera Commerce'!AO6 | BH31: ='9. Camera Commerce'!AP6 | BI31: ='9. Camera Commerce'!AQ6 | BJ31: ='9. Camera Commerce'!AR6 | BK31: ='9. Camera Commerce'!AS6 | BL31: ='9. Camera Commerce'!AT6 | BM31: ='9. Camera Commerce'!AU6 | BO31: =SUM(BB31:BM31) | BQ31: ='9. Camera Commerce'!AV6 | BR31: ='9. Camera Commerce'!AW6 | BS31: ='9. Camera Commerce'!AX6 | BT31: ='9. Camera Commerce'!AY6 | BU31: ='9. Camera Commerce'!AZ6 | BV31: ='9. Camera Commerce'!BB6 | BW31: ='9. Camera Commerce'!BC6 | BX31: ='9. Camera Commerce'!BD6 | BY31: ='9. Camera Commerce'!BE6 | BZ31: ='9. Camera Commerce'!BF6 | CA31: ='9. Camera Commerce'!BG6 | CB31: ='9. Camera Commerce'!BH6 | CD31: =SUM(BQ31:CB31) | CF31: ='9. Camera Commerce'!BI6 | CG31: ='9. Camera Commerce'!BJ6 | CH31: ='9. Camera Commerce'!BK6 | CI31: ='9. Camera Commerce'!BL6 | CJ31: ='9. Camera Commerce'!BM6 | CS31: =SUM(CF31:CQ31)
B32: ● | C32: Capital Raise | I32: 0 | J32: 0 | K32: 0 | L32: 0 | M32: 0 | N32: 5000000 | O32: 0 | P32: 0 | Q32: 0 | R32: 0 | S32: 0 | T32: 0 | V32: =SUM(I32:T32) | X32: 0 | Y32: 43000000 | Z32: 0 | AA32: 0 | AB32: 0 | AC32: 0 | AD32: 0 | AE32: 0 | AF32: 0 | AG32: 0 | AH32: 0 | AI32: 0 | AK32: =SUM(X32:AI32) | AM32: 0 | AN32: 100000000 | AO32: 0 | AP32: 0 | AQ32: 0 | AR32: 0 | AS32: 0 | AT32: 0 | AU32: 0 | AV32: 0 | AW32: 0 | AX32: 0 | AZ32: =SUM(AM32:AX32) | BB32: 0 | BC32: 500000000 | BD32: 0 | BE32: 0 | BF32: 0 | BG32: 0 | BH32: 0 | BI32: 0 | BJ32: 0 | BK32: 0 | BL32: 0 | BM32: 0 | BO32: =SUM(BB32:BM32) | BQ32: 0 | BR32: 0 | BS32: 0 | BT32: 0 | BU32: 0 | BV32: 0 | BW32: 0 | BX32: 0 | BY32: 0 | BZ32: 0 | CA32: 0 | CB32: 0 | CD32: =SUM(BQ32:CB32) | CF32: 0 | CG32: 0 | CH32: 0 | CI32: 0 | CJ32: 0 | CK32: 0 | CL32: 0 | CM32: 0 | CN32: 0 | CO32: 0 | CP32: 0 | CQ32: 0 | CS32: =SUM(CF32:CQ32)
V33: =SUM(I33:T33) | AD33: 0 | AK33: =SUM(X33:AI33) | AM33: 0 | AN33: 0 | AO33: 0 | AP33: 0 | AQ33: 0 | AR33: 0 | AS33: 0 | AT33: 0 | AU33: 0 | AV33: 0 | AW33: 0 | AX33: 0 | AZ33: =SUM(AM33:AX33) | BB33: 0 | BC33: 0 | BD33: 0 | BE33: 0 | BF33: 0 | BG33: 0 | BH33: 0 | BI33: 0 | BJ33: 0 | BK33: 0 | BL33: 0 | BM33: 0 | BO33: =SUM(BB33:BM33) | BQ33: 0 | BR33: 0 | BS33: 0 | BT33: 0 | BU33: 0 | BV33: 0 | BW33: 0 | BX33: 0 | BY33: 0 | BZ33: 0 | CA33: 0 | CB33: 0 | CD33: =SUM(BQ33:CB33) | CF33: 0 | CG33: 0 | CH33: 0 | CI33: 0 | CJ33: 0 | CK33: 0 | CL33: 0 | CM33: 0 | CN33: 0 | CO33: 0 | CP33: 0 | CQ33: 0 | CS33: =SUM(CF33:CQ33)
B34: ● | C34: Working Capital Financing - Borrowings | I34: 0 | J34: 0 | K34: 0 | L34: 0 | M34: 0 | N34: 0 | O34: 0 | P34: 0 | Q34: 0 | R34: 0 | S34: 0 | T34: 0 | V34: =SUM(I34:T34) | X34: 0 | Y34: 0 | Z34: 0 | AA34: 0 | AB34: 0 | AC34: 0 | AD34: 0 | AE34: 0 | AF34: 0 | AG34: 0 | AH34: 0 | AI34: 0 | AK34: =SUM(X34:AI34) | AM34: 0 | AN34: 0 | AO34: 0 | AP34: 0 | AQ34: 0 | AR34: 0 | AS34: 0 | AT34: 0 | AU34: 0 | AV34: 0 | AW34: 0 | AX34: 0 | AZ34: =SUM(AM34:AX34) | BB34: 0 | BC34: 0 | BD34: 0 | BE34: 0 | BF34: 0 | BG34: 0 | BH34: 0 | BI34: 0 | BJ34: 0 | BK34: 0 | BL34: 0 | BM34: 0 | BO34: =SUM(BB34:BM34) | BQ34: 0 | BR34: 0 | BS34: 0 | BT34: 0 | BU34: 0 | BV34: 0 | BW34: 0 | BX34: 0 | BY34: 0 | BZ34: 0 | CA34: 0 | CB34: 0 | CD34: =SUM(BQ34:CB34) | CF34: 0 | CG34: 0 | CH34: 0 | CI34: 0 | CJ34: 0 | CK34: 0 | CL34: 0 | CM34: 0 | CN34: 0 | CO34: 0 | CP34: 0 | CQ34: 0 | CS34: =SUM(CF34:CQ34)
V35: =SUM(I35:T35) | AK35: =SUM(X35:AI35) | AZ35: =SUM(AM35:AX35) | BO35: =SUM(BB35:BM35) | CD35: =SUM(BQ35:CB35) | CS35: =SUM(CF35:CQ35)
V36: =SUM(I36:T36) | AK36: =SUM(X36:AI36) | AZ36: =SUM(AM36:AX36) | BO36: =SUM(BB36:BM36) | CD36: =SUM(BQ36:CB36) | CS36: =SUM(CF36:CQ36)
D37: Total Cash Disbursements | I37: =SUM(I25:I34) | J37: =SUM(J25:J34) | K37: =SUM(K25:K34) | L37: =SUM(L25:L34) | M37: =SUM(M25:M34) | N37: =SUM(N25:N34) | O37: =SUM(O25:O34) | P37: =SUM(P25:P34) | ... T37: =SUM(T25:T34) | V37: =SUM(V25:V34) | X37: =SUM(X25:X34) | Y37: =SUM(Y25:Y34) | Z37: =SUM(Z25:Z34) | AA37: =SUM(AA25:AA34) | AB37: =SUM(AB25:AB34) | AC37: =SUM(AC25:AC34) | AD37: =SUM(AD25:AD34) | AE37: =SUM(AE25:AE34) | ... AI37: =SUM(AI25:AI34) | AK37: =SUM(AK25:AK34) | AM37: =SUM(AM25:AM34) | AN37: =SUM(AN25:AN34) | AO37: =SUM(AO25:AO34) | AP37: =SUM(AP25:AP34) | AQ37: =SUM(AQ25:AQ34) | AR37: =SUM(AR25:AR34) | AS37: =SUM(AS25:AS34) | AT37: =SUM(AT25:AT34) | ... AX37: =SUM(AX25:AX34) | AZ37: =SUM(AZ25:AZ34) | BB37: =SUM(BB25:BB34) | BC37: =SUM(BC25:BC34) | BD37: =SUM(BD25:BD34) | BE37: =SUM(BE25:BE34) | BF37: =SUM(BF25:BF34) | BG37: =SUM(BG25:BG34) | BH37: =SUM(BH25:BH34) | BI37: =SUM(BI25:BI34) | ... BM37: =SUM(BM25:BM34) | BO37: =SUM(BO25:BO34) | BQ37: =SUM(BQ25:BQ34) | BR37: =SUM(BR25:BR34) | BS37: =SUM(BS25:BS34) | BT37: =SUM(BT25:BT34) | BU37: =SUM(BU25:BU34) | BV37: =SUM(BV25:BV34) | BW37: =SUM(BW25:BW34) | BX37: =SUM(BX25:BX34) | ... CB37: =SUM(CB25:CB34) | CD37: =SUM(CD25:CD34) | CF37: =SUM(CF25:CF34) | CG37: =SUM(CG25:CG34) | CH37: =SUM(CH25:CH34) | CI37: =SUM(CI25:CI34) | CJ37: =SUM(CJ25:CJ34) | CK37: =SUM(CK25:CK34) | CL37: =SUM(CL25:CL34) | CM37: =SUM(CM25:CM34) | ... CQ37: =SUM(CQ25:CQ34) | CS37: =SUM(CS25:CS34)
V40: =V37-5000000 | AK40: =AK37-(Y32)+'2D. Crowd Funding'!G40 | AZ40: =AZ37-AN32 | BO40: =BO37-BC32 | CD40: =CD37-BR32 | CS40: =CS37-CG32
T41: Core Model | V41: =V25+V29+V26+V28 | AI41: Core Model | AK41: =AK25+AK29+AK26+AK28+'2D. Crowd Funding'!G40 | AX41: Core Model | AZ41: =AZ25+AZ29+AZ26+AZ28 | BM41: Core Model | BO41: =BO25+BO29+BO26+BO28 | CB41: Core Model | CD41: =CD25+CD29+CD26+CD28 | CQ41: Core Model | CS41: =CS25+CS29+CS26+CS28
B42: Cash Disbursements
B43: ● | C43: People Cost: Salaries, ER Payroll Taxes and EE Benefits | I43: ='6A. Pre-Launch Exps. - Roll-Up'!K35 | J43: ='6A. Pre-Launch Exps. - Roll-Up'!L35 | K43: ='6A. Pre-Launch Exps. - Roll-Up'!M35 | L43: ='6A. Pre-Launch Exps. - Roll-Up'!N35 | M43: ='6A. Pre-Launch Exps. - Roll-Up'!O35 | N43: ='6A. Pre-Launch Exps. - Roll-Up'!P35 | O43: ='6A. Pre-Launch Exps. - Roll-Up'!Q35 | P43: ='6A. Pre-Launch Exps. - Roll-Up'!R35 | ... T43: ='6A. Pre-Launch Exps. - Roll-Up'!V35 | V43: =SUM(I43:T43) | X43: ='4A. Tel. - Exps. & OI x Month'!$L41 | Y43: ='4A. Tel. - Exps. & OI x Month'!$M41 | Z43: ='4A. Tel. - Exps. & OI x Month'!$N41 | AA43: ='4A. Tel. - Exps. & OI x Month'!$O41 | AB43: ='4A. Tel. - Exps. & OI x Month'!$P41 | AC43: ='4A. Tel. - Exps. & OI x Month'!$Q41 | AD43: ='4A. Tel. - Exps. & OI x Month'!$R41 | AE43: ='4A. Tel. - Exps. & OI x Month'!$S41 | AF43: ='4A. Tel. - Exps. & OI x Month'!$T41 | AG43: ='4A. Tel. - Exps. & OI x Month'!$U41 | AH43: ='4A. Tel. - Exps. & OI x Month'!$V41 | AI43: ='4A. Tel. - Exps. & OI x Month'!$W41 | AK43: =SUM(X43:AI43) | AM43: ='4A. Tel. - Exps. & OI x Month'!$L133 | AN43: ='4A. Tel. - Exps. & OI x Month'!$M133 | AO43: ='4A. Tel. - Exps. & OI x Month'!$N133 | AP43: ='4A. Tel. - Exps. & OI x Month'!$O133 | AQ43: ='4A. Tel. - Exps. & OI x Month'!$P133 | AR43: ='4A. Tel. - Exps. & OI x Month'!$Q133 | AS43: ='4A. Tel. - Exps. & OI x Month'!$R133 | AT43: ='4A. Tel. - Exps. & OI x Month'!$S133 | AU43: ='4A. Tel. - Exps. & OI x Month'!$T133 | AV43: ='4A. Tel. - Exps. & OI x Month'!$U133 | AW43: ='4A. Tel. - Exps. & OI x Month'!$V133 | AX43: ='4A. Tel. - Exps. & OI x Month'!$W133 | AZ43: =SUM(AM43:AX43) | BB43: ='4A. Tel. - Exps. & OI x Month'!$L225 | BC43: ='4A. Tel. - Exps. & OI x Month'!$M225 | BD43: ='4A. Tel. - Exps. & OI x Month'!$N225 | BE43: ='4A. Tel. - Exps. & OI x Month'!$O225 | BF43: ='4A. Tel. - Exps. & OI x Month'!$P225 | BG43: ='4A. Tel. - Exps. & OI x Month'!$Q225 | BH43: ='4A. Tel. - Exps. & OI x Month'!$R225 | BI43: ='4A. Tel. - Exps. & OI x Month'!$S225 | BJ43: ='4A. Tel. - Exps. & OI x Month'!$T225 | BK43: ='4A. Tel. - Exps. & OI x Month'!$U225 | BL43: ='4A. Tel. - Exps. & OI x Month'!$V225 | BM43: ='4A. Tel. - Exps. & OI x Month'!$W225 | BO43: =SUM(BB43:BM43) | BQ43: ='4A. Tel. - Exps. & OI x Month'!L317 | BR43: ='4A. Tel. - Exps. & OI x Month'!M317 | BS43: ='4A. Tel. - Exps. & OI x Month'!N317 | BT43: ='4A. Tel. - Exps. & OI x Month'!O317 | BU43: ='4A. Tel. - Exps. & OI x Month'!P317 | BV43: ='4A. Tel. - Exps. & OI x Month'!Q317 | BW43: ='4A. Tel. - Exps. & OI x Month'!R317 | BX43: ='4A. Tel. - Exps. & OI x Month'!S317 | ... CB43: ='4A. Tel. - Exps. & OI x Month'!W317 | CD43: =SUM(BQ43:CB43) | CF43: ='4A. Tel. - Exps. & OI x Month'!L409 | CG43: ='4A. Tel. - Exps. & OI x Month'!M409 | CH43: ='4A. Tel. - Exps. & OI x Month'!N409 | CI43: ='4A. Tel. - Exps. & OI x Month'!O409 | CJ43: ='4A. Tel. - Exps. & OI x Month'!P409 | CK43: ='4A. Tel. - Exps. & OI x Month'!Q409 | CL43: ='4A. Tel. - Exps. & OI x Month'!R409 | CM43: ='4A. Tel. - Exps. & OI x Month'!S409 | ... CQ43: ='4A. Tel. - Exps. & OI x Month'!W409 | CS43: =SUM(CF43:CQ43) | CU43: <--
B44: ● | C44: Legacy Accrued Payroll | I44: ='[3]$25M Investment'!$M$82 | J44: ='[3]$25M Investment'!$M$149 | K44: 0 | L44: 0 | M44: 0 | N44: 0 | O44: 0 | P44: ='[4]$25M Investment'!$M$551 | Q44: 0 | R44: 0 | S44: 0 | T44: 0 | V44: =SUM(I44:T44) | X44: 0 | Y44: 0 | Z44: 0 | AA44: 0 | AB44: 0 | AC44: 0 | AD44: 0 | AE44: 0 | AF44: 0 | AG44: 0 | AH44: 0 | AI44: 0 | AK44: =SUM(X44:AI44) | AM44: 0 | AN44: 0 | AO44: 0 | AP44: 0 | AQ44: 0 | AR44: 0 | AS44: 0 | AT44: 0 | AU44: 0 | AV44: 0 | AW44: 0 | AX44: 0 | AZ44: =SUM(AM44:AX44) | BB44: 0 | BC44: 0 | BD44: 0 | BE44: 0 | BF44: 0 | BG44: 0 | BH44: 0 | BI44: 0 | BJ44: 0 | BK44: 0 | BL44: 0 | BM44: 0 | BO44: =SUM(BB44:BM44) | BQ44: 0 | BR44: 0 | BS44: 0 | BT44: 0 | BU44: 0 | BV44: 0 | BW44: 0 | BX44: 0 | BY44: 0 | BZ44: 0 | CA44: 0 | CB44: 0 | CD44: =SUM(BQ44:CB44) | CF44: 0 | CG44: 0 | CH44: 0 | CI44: 0 | CJ44: 0 | CK44: 0 | CL44: 0 | CM44: 0 | CN44: 0 | CO44: 0 | CP44: 0 | CQ44: 0 | CS44: =SUM(CF44:CQ44)
B45: ● | C45: Other Legacy/Pre-Funding Liabilities, Estimate | I45: ='[3]$25M Investment'!$M$80 | J45: ='[3]$25M Investment'!$M$147 | K45: ='[4]$25M Investment'!$M$214 | L45: ='[4]$25M Investment'!$M$281 | M45: ='[4]$25M Investment'!$M$348 | N45: ='[4]$25M Investment'!$M$415 | O45: ='[4]$25M Investment'!$M$482 | P45: 0 | Q45: 0 | R45: 0 | S45: 0 | T45: 0 | V45: =SUM(I45:T45) | X45: 0 | Y45: 0 | Z45: 0 | AA45: 0 | AB45: 0 | AC45: 0 | AD45: 0 | AE45: 0 | AF45: 0 | AG45: 0 | AH45: 0 | AI45: 0 | AK45: =SUM(X45:AI45) | AM45: 0 | AN45: 0 | AO45: 0 | AP45: 0 | AQ45: 0 | AR45: 0 | AS45: 0 | AT45: 0 | AU45: 0 | AV45: 0 | AW45: 0 | AX45: 0 | AZ45: =SUM(AM45:AX45) | BB45: 0 | BC45: 0 | BD45: 0 | BE45: 0 | BF45: 0 | BG45: 0 | BH45: 0 | BI45: 0 | BJ45: 0 | BK45: 0 | BL45: 0 | BM45: 0 | BO45: =SUM(BB45:BM45) | BQ45: 0 | BR45: 0 | BS45: 0 | BT45: 0 | BU45: 0 | BV45: 0 | BW45: 0 | BX45: 0 | BY45: 0 | BZ45: 0 | CA45: 0 | CB45: 0 | CD45: =SUM(BQ45:CB45) | CF45: 0 | CG45: 0 | CH45: 0 | CI45: 0 | CJ45: 0 | CK45: 0 | CL45: 0 | CM45: 0 | CN45: 0 | CO45: 0 | CP45: 0 | CQ45: 0 | CS45: =SUM(CF45:CQ45)
B46: ● | C46: Strategic Investments | I46: 0 | J46: ='[4]$25M Investment'!$M$150 | K46: ='[4]$25M Investment'!$M$217 | L46: ='[4]$25M Investment'!$M$284 | M46: ='[4]$25M Investment'!$M$351 | N46: ='[4]$25M Investment'!$M$418 | O46: ='[4]$25M Investment'!$M$485 | P46: ='[4]$25M Investment'!$M$552 | Q46: ='[4]$25M Investment'!$M$619 | R46: ='[4]$25M Investment'!$M$686 | S46: ='[4]$25M Investment'!$M$753 | T46: ='[4]$25M Investment'!$M$820 | V46: =SUM(I46:T46) | X46: ='[4]$25M Investment'!$M$820 | Y46: ='[4]$25M Investment'!$M$820 | Z46: ='[4]$25M Investment'!$M$820 | AA46: ='[4]$25M Investment'!$M$820 | AB46: ='[4]$25M Investment'!$M$820 | AC46: ='[4]$25M Investment'!$M$820 | AD46: ='[4]$25M Investment'!$M$820 | AE46: ='[4]$25M Investment'!$M$820 | ... AI46: ='[4]$25M Investment'!$M$820 | AK46: =SUM(X46:AI46) | AM46: ='[4]$25M Investment'!$M$820 | AN46: ='[4]$25M Investment'!$M$820 | AO46: ='[4]$25M Investment'!$M$820 | AP46: ='[4]$25M Investment'!$M$820 | AQ46: ='[4]$25M Investment'!$M$820 | AR46: ='[4]$25M Investment'!$M$820 | AS46: ='[4]$25M Investment'!$M$820 | AT46: ='[4]$25M Investment'!$M$820+10000 | AU46: ='[4]$25M Investment'!$M$820+10000 | AV46: ='[4]$25M Investment'!$M$820+10000 | AW46: ='[4]$25M Investment'!$M$820+10000 | AX46: ='[4]$25M Investment'!$M$820+10000 | AZ46: =SUM(AM46:AX46) | BB46: ='[4]$25M Investment'!$M$820+10000 | BC46: ='[4]$25M Investment'!$M$820+10000 | BD46: ='[4]$25M Investment'!$M$820+10000 | BE46: ='[4]$25M Investment'!$M$820+10000 | BF46: ='[4]$25M Investment'!$M$820+10000 | BG46: ='[4]$25M Investment'!$M$820+10000 | BH46: ='[4]$25M Investment'!$M$820+10000 | BI46: ='[4]$25M Investment'!$M$820+10000 | ... BM46: ='[4]$25M Investment'!$M$820+10000 | BO46: =SUM(BB46:BM46) | BQ46: ='[4]$25M Investment'!$M$820+10000 | BR46: ='[4]$25M Investment'!$M$820+10000 | BS46: ='[4]$25M Investment'!$M$820+10000 | BT46: ='[4]$25M Investment'!$M$820+10000 | BU46: ='[4]$25M Investment'!$M$820+10000 | BV46: ='[4]$25M Investment'!$M$820+10000 | BW46: ='[4]$25M Investment'!$M$820+10000 | BX46: 0 | BY46: 0 | BZ46: 0 | CA46: 0 | CB46: 0 | CD46: =SUM(BQ46:CB46) | CF46: 0 | CG46: 0 | CH46: 0 | CI46: 0 | CJ46: 0 | CK46: 0 | CL46: 0 | CM46: 0 | CN46: 0 | CO46: 0 | CP46: 0 | CQ46: 0 | CS46: =SUM(CF46:CQ46)
B47: ● | C47: Research and Development | I47: ='6A. Pre-Launch Exps. - Roll-Up'!K39 | J47: ='6A. Pre-Launch Exps. - Roll-Up'!L39 | K47: ='6A. Pre-Launch Exps. - Roll-Up'!M39 | L47: ='6A. Pre-Launch Exps. - Roll-Up'!N39 | M47: ='6A. Pre-Launch Exps. - Roll-Up'!O39 | N47: ='6A. Pre-Launch Exps. - Roll-Up'!P39 | O47: ='6A. Pre-Launch Exps. - Roll-Up'!Q39 | P47: ='6A. Pre-Launch Exps. - Roll-Up'!R39 | ... T47: ='6A. Pre-Launch Exps. - Roll-Up'!V39 | V47: =SUM(I47:T47) | X47: ='4A. Tel. - Exps. & OI x Month'!$L45 | Y47: ='4A. Tel. - Exps. & OI x Month'!$M45 | Z47: ='4A. Tel. - Exps. & OI x Month'!$N45 | AA47: ='4A. Tel. - Exps. & OI x Month'!$O45 | AB47: ='4A. Tel. - Exps. & OI x Month'!$P45 | AC47: ='4A. Tel. - Exps. & OI x Month'!$Q45 | AD47: ='4A. Tel. - Exps. & OI x Month'!$R45 | AE47: ='4A. Tel. - Exps. & OI x Month'!$S45 | AF47: ='4A. Tel. - Exps. & OI x Month'!T45 | AG47: ='4A. Tel. - Exps. & OI x Month'!$U45 | AH47: ='4A. Tel. - Exps. & OI x Month'!$V45 | AI47: ='4A. Tel. - Exps. & OI x Month'!$W45 | AK47: =SUM(X47:AI47) | AM47: ='4A. Tel. - Exps. & OI x Month'!L137 | AN47: ='4A. Tel. - Exps. & OI x Month'!M137 | AO47: ='4A. Tel. - Exps. & OI x Month'!N137 | AP47: ='4A. Tel. - Exps. & OI x Month'!O137 | AQ47: ='4A. Tel. - Exps. & OI x Month'!P137 | AR47: ='4A. Tel. - Exps. & OI x Month'!Q137 | AS47: ='4A. Tel. - Exps. & OI x Month'!R137 | AT47: ='4A. Tel. - Exps. & OI x Month'!S137 | ... AX47: ='4A. Tel. - Exps. & OI x Month'!W137 | AZ47: =SUM(AM47:AX47) | BB47: ='4A. Tel. - Exps. & OI x Month'!L229 | BC47: ='4A. Tel. - Exps. & OI x Month'!M229 | BD47: ='4A. Tel. - Exps. & OI x Month'!N229 | BE47: ='4A. Tel. - Exps. & OI x Month'!O229 | BF47: ='4A. Tel. - Exps. & OI x Month'!P229 | BG47: ='4A. Tel. - Exps. & OI x Month'!Q229 | BH47: ='4A. Tel. - Exps. & OI x Month'!R229 | BI47: ='4A. Tel. - Exps. & OI x Month'!S229 | ... BM47: ='4A. Tel. - Exps. & OI x Month'!W229 | BO47: =SUM(BB47:BM47) | BQ47: ='4A. Tel. - Exps. & OI x Month'!L321 | BR47: ='4A. Tel. - Exps. & OI x Month'!M321 | BS47: ='4A. Tel. - Exps. & OI x Month'!N321 | BT47: ='4A. Tel. - Exps. & OI x Month'!O321 | BU47: ='4A. Tel. - Exps. & OI x Month'!P321 | BV47: ='4A. Tel. - Exps. & OI x Month'!Q321 | BW47: ='4A. Tel. - Exps. & OI x Month'!R321 | BX47: ='4A. Tel. - Exps. & OI x Month'!S321 | ... CB47: ='4A. Tel. - Exps. & OI x Month'!W321 | CD47: =SUM(BQ47:CB47) | CF47: ='4A. Tel. - Exps. & OI x Month'!L413 | CG47: ='4A. Tel. - Exps. & OI x Month'!M413 | CH47: ='4A. Tel. - Exps. & OI x Month'!N413 | CI47: ='4A. Tel. - Exps. & OI x Month'!O413 | CJ47: ='4A. Tel. - Exps. & OI x Month'!P413 | CK47: ='4A. Tel. - Exps. & OI x Month'!Q413 | CL47: ='4A. Tel. - Exps. & OI x Month'!R413 | CM47: ='4A. Tel. - Exps. & OI x Month'!S413 | ... CQ47: ='4A. Tel. - Exps. & OI x Month'!W413 | CS47: =SUM(CF47:CQ47)
B48: ● | C48: Pre-Launch Telephone Inventory Investment | I48: ='6A. Pre-Launch Exps. - Roll-Up'!K41 | J48: ='6A. Pre-Launch Exps. - Roll-Up'!L41 | K48: ='6A. Pre-Launch Exps. - Roll-Up'!M41 | L48: ='6A. Pre-Launch Exps. - Roll-Up'!N41 | M48: ='6A. Pre-Launch Exps. - Roll-Up'!O41 | N48: ='6A. Pre-Launch Exps. - Roll-Up'!P41 | O48: ='6A. Pre-Launch Exps. - Roll-Up'!Q41 | P48: ='6A. Pre-Launch Exps. - Roll-Up'!R41 | ... T48: ='6A. Pre-Launch Exps. - Roll-Up'!V41 | V48: =SUM(I48:T48) | X48: 0 | Y48: 0 | Z48: 0 | AA48: 0 | AB48: 0 | AC48: 0 | AD48: 0 | AE48: 0 | AF48: 0 | AG48: 0 | AH48: 0 | AI48: 0 | AK48: =SUM(X48:AI48) | AM48: 0 | AN48: 0 | AO48: 0 | AP48: 0 | AQ48: 0 | AR48: 0 | AS48: 0 | AT48: 0 | AU48: 0 | AV48: 0 | AW48: 0 | AX48: 0 | AZ48: =SUM(AM48:AX48) | BB48: 0 | BC48: 0 | BD48: 0 | BE48: 0 | BF48: 0 | BG48: 0 | BH48: 0 | BI48: 0 | BJ48: 0 | BK48: 0 | BL48: 0 | BM48: 0 | BO48: =SUM(BB48:BM48) | BQ48: 0 | BR48: 0 | BS48: 0 | BT48: 0 | BU48: 0 | BV48: 0 | BW48: 0 | BX48: 0 | BY48: 0 | BZ48: 0 | CA48: 0 | CB48: 0 | CD48: =SUM(BQ48:CB48) | CF48: 0 | CG48: 0 | CH48: 0 | CI48: 0 | CJ48: 0 | CK48: 0 | CL48: 0 | CM48: 0 | CN48: 0 | CO48: 0 | CP48: 0 | CQ48: 0 | CS48: =SUM(CF48:CQ48)
B49: ● | C49: Post-Lauch Telephone Inventory Purchases | I49: ='2C. Inventory Cash Disburse.'!G40 | J49: ='2C. Inventory Cash Disburse.'!H40 | K49: ='2C. Inventory Cash Disburse.'!I40 | L49: ='2C. Inventory Cash Disburse.'!M40 | M49: ='2C. Inventory Cash Disburse.'!N40 | N49: ='2C. Inventory Cash Disburse.'!O40 | O49: ='2C. Inventory Cash Disburse.'!P40 | P49: ='2C. Inventory Cash Disburse.'!Q40 | Q49: ='2C. Inventory Cash Disburse.'!R40 | R49: ='2C. Inventory Cash Disburse.'!S40 | S49: ='2C. Inventory Cash Disburse.'!T40 | T49: ='2C. Inventory Cash Disburse.'!U40 | V49: =SUM(I49:T49) | X49: ='2C. Inventory Cash Disburse.'!Y40 | Y49: ='2C. Inventory Cash Disburse.'!Z40 | Z49: ='2C. Inventory Cash Disburse.'!AA40 | AA49: ='2C. Inventory Cash Disburse.'!AB40 | AB49: ='2C. Inventory Cash Disburse.'!AC40 | AC49: ='2C. Inventory Cash Disburse.'!AD40 | AD49: ='2C. Inventory Cash Disburse.'!AE40 | AE49: ='2C. Inventory Cash Disburse.'!AF40 | ... AI49: ='2C. Inventory Cash Disburse.'!AJ40 | AK49: =SUM(X49:AI49) | AM49: ='2C. Inventory Cash Disburse.'!AN40 | AN49: ='2C. Inventory Cash Disburse.'!AO40 | AO49: ='2C. Inventory Cash Disburse.'!AP40 | AP49: ='2C. Inventory Cash Disburse.'!AQ40 | AQ49: ='2C. Inventory Cash Disburse.'!AR40 | AR49: ='2C. Inventory Cash Disburse.'!AS40 | AS49: ='2C. Inventory Cash Disburse.'!AT40 | AT49: ='2C. Inventory Cash Disburse.'!AU40 | ... AX49: ='2C. Inventory Cash Disburse.'!AY40 | AZ49: =SUM(AM49:AX49) | BB49: ='2C. Inventory Cash Disburse.'!BC40 | BC49: ='2C. Inventory Cash Disburse.'!BD40 | BD49: ='2C. Inventory Cash Disburse.'!BE40 | BE49: ='2C. Inventory Cash Disburse.'!BF40 | BF49: ='2C. Inventory Cash Disburse.'!BG40 | BG49: ='2C. Inventory Cash Disburse.'!BH40 | BH49: ='2C. Inventory Cash Disburse.'!BI40 | BI49: ='2C. Inventory Cash Disburse.'!BJ40 | ... BM49: ='2C. Inventory Cash Disburse.'!BN40 | BO49: =SUM(BB49:BM49) | BQ49: ='2C. Inventory Cash Disburse.'!BR40 | BR49: ='2C. Inventory Cash Disburse.'!BS40 | BS49: ='2C. Inventory Cash Disburse.'!BT40 | BT49: ='2C. Inventory Cash Disburse.'!BU40 | BU49: ='2C. Inventory Cash Disburse.'!BV40 | BV49: ='2C. Inventory Cash Disburse.'!BW40 | BW49: ='2C. Inventory Cash Disburse.'!BX40 | BX49: ='2C. Inventory Cash Disburse.'!BY40 | ... CB49: ='2C. Inventory Cash Disburse.'!CC40 | CD49: =SUM(BQ49:CB49) | CF49: ='2C. Inventory Cash Disburse.'!CG40 | CG49: ='2C. Inventory Cash Disburse.'!CH40 | CH49: ='2C. Inventory Cash Disburse.'!CI40 | CI49: ='2C. Inventory Cash Disburse.'!CJ40 | CJ49: ='2C. Inventory Cash Disburse.'!CK40 | CK49: ='2C. Inventory Cash Disburse.'!CL40 | CL49: ='2C. Inventory Cash Disburse.'!CM40 | CM49: ='2C. Inventory Cash Disburse.'!CN40 | ... CQ49: ='2C. Inventory Cash Disburse.'!CR40 | CS49: =SUM(CF49:CQ49)
B50: ● | C50: Sales and Marketing | I50: ='6A. Pre-Launch Exps. - Roll-Up'!K53 | J50: ='6A. Pre-Launch Exps. - Roll-Up'!L53 | K50: ='6A. Pre-Launch Exps. - Roll-Up'!M53 | L50: ='6A. Pre-Launch Exps. - Roll-Up'!N53 | M50: ='6A. Pre-Launch Exps. - Roll-Up'!O53 | N50: ='6A. Pre-Launch Exps. - Roll-Up'!P53 | O50: ='6A. Pre-Launch Exps. - Roll-Up'!Q53 | P50: ='6A. Pre-Launch Exps. - Roll-Up'!R53 | ... T50: ='6A. Pre-Launch Exps. - Roll-Up'!V53 | V50: =SUM(I50:T50) | X50: ='4A. Tel. - Exps. & OI x Month'!$L54 | Y50: ='4A. Tel. - Exps. & OI x Month'!$M54 | Z50: ='4A. Tel. - Exps. & OI x Month'!$N54 | AA50: ='4A. Tel. - Exps. & OI x Month'!$O54 | AB50: ='4A. Tel. - Exps. & OI x Month'!$P54 | AC50: ='4A. Tel. - Exps. & OI x Month'!$Q54 | AD50: ='4A. Tel. - Exps. & OI x Month'!$R54 | AE50: ='4A. Tel. - Exps. & OI x Month'!$S54 | AF50: ='4A. Tel. - Exps. & OI x Month'!$T54 | AG50: ='4A. Tel. - Exps. & OI x Month'!$U54 | AH50: ='4A. Tel. - Exps. & OI x Month'!$V54 | AI50: ='4A. Tel. - Exps. & OI x Month'!$W54 | AK50: =SUM(X50:AI50) | AM50: ='4A. Tel. - Exps. & OI x Month'!L$146 | AN50: ='4A. Tel. - Exps. & OI x Month'!M$146 | AO50: ='4A. Tel. - Exps. & OI x Month'!N$146 | AP50: ='4A. Tel. - Exps. & OI x Month'!O$146 | AQ50: ='4A. Tel. - Exps. & OI x Month'!P$146 | AR50: ='4A. Tel. - Exps. & OI x Month'!Q$146 | AS50: ='4A. Tel. - Exps. & OI x Month'!R$146 | AT50: ='4A. Tel. - Exps. & OI x Month'!S$146 | ... AX50: ='4A. Tel. - Exps. & OI x Month'!W$146 | AZ50: =SUM(AM50:AX50) | BB50: ='4A. Tel. - Exps. & OI x Month'!L238 | BC50: ='4A. Tel. - Exps. & OI x Month'!M238 | BD50: ='4A. Tel. - Exps. & OI x Month'!N238 | BE50: ='4A. Tel. - Exps. & OI x Month'!O238 | BF50: ='4A. Tel. - Exps. & OI x Month'!P238 | BG50: ='4A. Tel. - Exps. & OI x Month'!Q238 | BH50: ='4A. Tel. - Exps. & OI x Month'!R238 | BI50: ='4A. Tel. - Exps. & OI x Month'!S238 | ... BM50: ='4A. Tel. - Exps. & OI x Month'!W238 | BO50: =SUM(BB50:BM50) | BQ50: ='4A. Tel. - Exps. & OI x Month'!L330 | BR50: ='4A. Tel. - Exps. & OI x Month'!M330 | BS50: ='4A. Tel. - Exps. & OI x Month'!N330 | BT50: ='4A. Tel. - Exps. & OI x Month'!O330 | BU50: ='4A. Tel. - Exps. & OI x Month'!P330 | BV50: ='4A. Tel. - Exps. & OI x Month'!Q330 | BW50: ='4A. Tel. - Exps. & OI x Month'!R330 | BX50: ='4A. Tel. - Exps. & OI x Month'!S330 | ... CB50: ='4A. Tel. - Exps. & OI x Month'!W330 | CD50: =SUM(BQ50:CB50) | CF50: ='4A. Tel. - Exps. & OI x Month'!L422 | CG50: ='4A. Tel. - Exps. & OI x Month'!M422 | CH50: ='4A. Tel. - Exps. & OI x Month'!N422 | CI50: ='4A. Tel. - Exps. & OI x Month'!O422 | CJ50: ='4A. Tel. - Exps. & OI x Month'!P422 | CK50: ='4A. Tel. - Exps. & OI x Month'!Q422 | CL50: ='4A. Tel. - Exps. & OI x Month'!R422 | CM50: ='4A. Tel. - Exps. & OI x Month'!S422 | ... CQ50: ='4A. Tel. - Exps. & OI x Month'!W422 | CS50: =SUM(CF50:CQ50)
B51: ● | C51: Occupancy | I51: ='6A. Pre-Launch Exps. - Roll-Up'!K62 | J51: ='6A. Pre-Launch Exps. - Roll-Up'!L62 | K51: ='6A. Pre-Launch Exps. - Roll-Up'!M62 | L51: ='6A. Pre-Launch Exps. - Roll-Up'!N62 | M51: ='6A. Pre-Launch Exps. - Roll-Up'!O62 | N51: ='6A. Pre-Launch Exps. - Roll-Up'!P62 | O51: ='6A. Pre-Launch Exps. - Roll-Up'!Q62 | P51: ='6A. Pre-Launch Exps. - Roll-Up'!R62 | ... T51: ='6A. Pre-Launch Exps. - Roll-Up'!V62 | V51: =SUM(I51:T51) | X51: ='4A. Tel. - Exps. & OI x Month'!$L63 | Y51: ='4A. Tel. - Exps. & OI x Month'!$M63 | Z51: ='4A. Tel. - Exps. & OI x Month'!$N63 | AA51: ='4A. Tel. - Exps. & OI x Month'!$O63 | AB51: ='4A. Tel. - Exps. & OI x Month'!$P63 | AC51: ='4A. Tel. - Exps. & OI x Month'!$Q63 | AD51: ='4A. Tel. - Exps. & OI x Month'!$R63 | AE51: ='4A. Tel. - Exps. & OI x Month'!$S63 | AF51: ='4A. Tel. - Exps. & OI x Month'!$T63 | AG51: ='4A. Tel. - Exps. & OI x Month'!$U63 | AH51: ='4A. Tel. - Exps. & OI x Month'!$V63 | AI51: ='4A. Tel. - Exps. & OI x Month'!$W63 | AK51: =SUM(X51:AI51) | AM51: ='4A. Tel. - Exps. & OI x Month'!L155 | AN51: ='4A. Tel. - Exps. & OI x Month'!M155 | AO51: ='4A. Tel. - Exps. & OI x Month'!N155 | AP51: ='4A. Tel. - Exps. & OI x Month'!O155 | AQ51: ='4A. Tel. - Exps. & OI x Month'!P155 | AR51: ='4A. Tel. - Exps. & OI x Month'!Q155 | AS51: ='4A. Tel. - Exps. & OI x Month'!R155 | AT51: ='4A. Tel. - Exps. & OI x Month'!S155 | ... AX51: ='4A. Tel. - Exps. & OI x Month'!W155 | AZ51: =SUM(AM51:AX51) | BB51: ='4A. Tel. - Exps. & OI x Month'!L247 | BC51: ='4A. Tel. - Exps. & OI x Month'!M247 | BD51: ='4A. Tel. - Exps. & OI x Month'!N247 | BE51: ='4A. Tel. - Exps. & OI x Month'!O247 | BF51: ='4A. Tel. - Exps. & OI x Month'!P247 | BG51: ='4A. Tel. - Exps. & OI x Month'!Q247 | BH51: ='4A. Tel. - Exps. & OI x Month'!R247 | BI51: ='4A. Tel. - Exps. & OI x Month'!S247 | ... BM51: ='4A. Tel. - Exps. & OI x Month'!W247 | BO51: =SUM(BB51:BM51) | BQ51: ='4A. Tel. - Exps. & OI x Month'!L339 | BR51: ='4A. Tel. - Exps. & OI x Month'!M339 | BS51: ='4A. Tel. - Exps. & OI x Month'!N339 | BT51: ='4A. Tel. - Exps. & OI x Month'!O339 | BU51: ='4A. Tel. - Exps. & OI x Month'!P339 | BV51: ='4A. Tel. - Exps. & OI x Month'!Q339 | BW51: ='4A. Tel. - Exps. & OI x Month'!R339 | BX51: ='4A. Tel. - Exps. & OI x Month'!S339 | ... CB51: ='4A. Tel. - Exps. & OI x Month'!W339 | CD51: =SUM(BQ51:CB51) | CF51: ='4A. Tel. - Exps. & OI x Month'!L431 | CG51: ='4A. Tel. - Exps. & OI x Month'!M431 | CH51: ='4A. Tel. - Exps. & OI x Month'!N431 | CI51: ='4A. Tel. - Exps. & OI x Month'!O431 | CJ51: ='4A. Tel. - Exps. & OI x Month'!P431 | CK51: ='4A. Tel. - Exps. & OI x Month'!Q431 | CL51: ='4A. Tel. - Exps. & OI x Month'!R431 | CM51: ='4A. Tel. - Exps. & OI x Month'!S431 | ... CQ51: ='4A. Tel. - Exps. & OI x Month'!W431 | CS51: =SUM(CF51:CQ51)
B52: ● | C52: General and Administrative | I52: ='6A. Pre-Launch Exps. - Roll-Up'!K87 | J52: ='6A. Pre-Launch Exps. - Roll-Up'!L87 | K52: ='6A. Pre-Launch Exps. - Roll-Up'!M87 | L52: ='6A. Pre-Launch Exps. - Roll-Up'!N87 | M52: ='6A. Pre-Launch Exps. - Roll-Up'!O87 | N52: ='6A. Pre-Launch Exps. - Roll-Up'!P87 | O52: ='6A. Pre-Launch Exps. - Roll-Up'!Q87 | P52: ='6A. Pre-Launch Exps. - Roll-Up'!R87 | ... T52: ='6A. Pre-Launch Exps. - Roll-Up'!V87 | V52: =SUM(I52:T52) | X52: ='4A. Tel. - Exps. & OI x Month'!$L84 | Y52: ='4A. Tel. - Exps. & OI x Month'!$M84 | Z52: ='4A. Tel. - Exps. & OI x Month'!$N84 | AA52: ='4A. Tel. - Exps. & OI x Month'!$O84 | AB52: ='4A. Tel. - Exps. & OI x Month'!$P84 | AC52: ='4A. Tel. - Exps. & OI x Month'!$Q84 | AD52: ='4A. Tel. - Exps. & OI x Month'!$R84 | AE52: ='4A. Tel. - Exps. & OI x Month'!$S84 | AF52: ='4A. Tel. - Exps. & OI x Month'!$T84 | AG52: ='4A. Tel. - Exps. & OI x Month'!$U84 | AH52: ='4A. Tel. - Exps. & OI x Month'!$V84 | AI52: ='4A. Tel. - Exps. & OI x Month'!$W84 | AK52: =SUM(X52:AI52) | AM52: ='4A. Tel. - Exps. & OI x Month'!L176 | AN52: ='4A. Tel. - Exps. & OI x Month'!M176 | AO52: ='4A. Tel. - Exps. & OI x Month'!N176 | AP52: ='4A. Tel. - Exps. & OI x Month'!O176 | AQ52: ='4A. Tel. - Exps. & OI x Month'!P176 | AR52: ='4A. Tel. - Exps. & OI x Month'!Q176 | AS52: ='4A. Tel. - Exps. & OI x Month'!R176 | AT52: ='4A. Tel. - Exps. & OI x Month'!S176 | ... AX52: ='4A. Tel. - Exps. & OI x Month'!W176 | AZ52: =SUM(AM52:AX52) | BB52: ='4A. Tel. - Exps. & OI x Month'!L268 | BC52: ='4A. Tel. - Exps. & OI x Month'!M268 | BD52: ='4A. Tel. - Exps. & OI x Month'!N268 | BE52: ='4A. Tel. - Exps. & OI x Month'!O268 | BF52: ='4A. Tel. - Exps. & OI x Month'!P268 | BG52: ='4A. Tel. - Exps. & OI x Month'!Q268 | BH52: ='4A. Tel. - Exps. & OI x Month'!R268 | BI52: ='4A. Tel. - Exps. & OI x Month'!S268 | ... BM52: ='4A. Tel. - Exps. & OI x Month'!W268 | BO52: =SUM(BB52:BM52) | BQ52: ='4A. Tel. - Exps. & OI x Month'!L360 | BR52: ='4A. Tel. - Exps. & OI x Month'!M360 | BS52: ='4A. Tel. - Exps. & OI x Month'!N360 | BT52: ='4A. Tel. - Exps. & OI x Month'!O360 | BU52: ='4A. Tel. - Exps. & OI x Month'!P360 | BV52: ='4A. Tel. - Exps. & OI x Month'!Q360 | BW52: ='4A. Tel. - Exps. & OI x Month'!R360 | BX52: ='4A. Tel. - Exps. & OI x Month'!S360 | ... CB52: ='4A. Tel. - Exps. & OI x Month'!W360 | CD52: =SUM(BQ52:CB52) | CF52: ='4A. Tel. - Exps. & OI x Month'!L452 | CG52: ='4A. Tel. - Exps. & OI x Month'!M452 | CH52: ='4A. Tel. - Exps. & OI x Month'!N452 | CI52: ='4A. Tel. - Exps. & OI x Month'!O452 | CJ52: ='4A. Tel. - Exps. & OI x Month'!P452 | CK52: ='4A. Tel. - Exps. & OI x Month'!Q452 | CL52: ='4A. Tel. - Exps. & OI x Month'!R452 | CM52: ='4A. Tel. - Exps. & OI x Month'!S452 | ... CQ52: ='4A. Tel. - Exps. & OI x Month'!W452 | CS52: =SUM(CF52:CQ52)
B53: ● | C53: Customer Rewards | I53: 0 | J53: 0 | K53: 0 | L53: 0 | M53: 0 | N53: 0 | O53: 0 | P53: 0 | Q53: 0 | R53: 0 | S53: 0 | T53: 0 | V53: =SUM(I53:T53) | X53: ='3B. Tel. - Rev. Detail x Month'!$J300 | Y53: ='3B. Tel. - Rev. Detail x Month'!$K300 | Z53: ='3B. Tel. - Rev. Detail x Month'!$L300 | AA53: ='3B. Tel. - Rev. Detail x Month'!$M300 | AB53: ='3B. Tel. - Rev. Detail x Month'!$N300 | AC53: ='3B. Tel. - Rev. Detail x Month'!$O300 | AD53: ='3B. Tel. - Rev. Detail x Month'!$P300 | AE53: ='3B. Tel. - Rev. Detail x Month'!$Q300 | AF53: ='3B. Tel. - Rev. Detail x Month'!$R300 | AG53: ='3B. Tel. - Rev. Detail x Month'!$S300 | AH53: ='3B. Tel. - Rev. Detail x Month'!$T300 | AI53: ='3B. Tel. - Rev. Detail x Month'!$U300 | AK53: =SUM(X53:AI53) | AM53: ='3B. Tel. - Rev. Detail x Month'!J332 | AN53: ='3B. Tel. - Rev. Detail x Month'!K332 | AO53: ='3B. Tel. - Rev. Detail x Month'!L332 | AP53: ='3B. Tel. - Rev. Detail x Month'!M332 | AQ53: ='3B. Tel. - Rev. Detail x Month'!N332 | AR53: ='3B. Tel. - Rev. Detail x Month'!O332 | AS53: ='3B. Tel. - Rev. Detail x Month'!P332 | AT53: ='3B. Tel. - Rev. Detail x Month'!Q332 | ... AX53: ='3B. Tel. - Rev. Detail x Month'!U332 | AZ53: =SUM(AM53:AX53) | BB53: ='3B. Tel. - Rev. Detail x Month'!J364 | BC53: ='3B. Tel. - Rev. Detail x Month'!K364 | BD53: ='3B. Tel. - Rev. Detail x Month'!L364 | BE53: ='3B. Tel. - Rev. Detail x Month'!M364 | BF53: ='3B. Tel. - Rev. Detail x Month'!N364 | BG53: ='3B. Tel. - Rev. Detail x Month'!O364 | BH53: ='3B. Tel. - Rev. Detail x Month'!P364 | BI53: ='3B. Tel. - Rev. Detail x Month'!Q364 | ... BM53: ='3B. Tel. - Rev. Detail x Month'!U364 | BO53: =SUM(BB53:BM53) | BQ53: ='3B. Tel. - Rev. Detail x Month'!J396 | BR53: ='3B. Tel. - Rev. Detail x Month'!K396 | BS53: ='3B. Tel. - Rev. Detail x Month'!L396 | BT53: ='3B. Tel. - Rev. Detail x Month'!M396 | BU53: ='3B. Tel. - Rev. Detail x Month'!N396 | BV53: ='3B. Tel. - Rev. Detail x Month'!O396 | BW53: ='3B. Tel. - Rev. Detail x Month'!P396 | BX53: ='3B. Tel. - Rev. Detail x Month'!Q396 | ... CB53: ='3B. Tel. - Rev. Detail x Month'!U396 | CD53: =SUM(BQ53:CB53) | CF53: ='3B. Tel. - Rev. Detail x Month'!J428 | CG53: ='3B. Tel. - Rev. Detail x Month'!K428 | CH53: ='3B. Tel. - Rev. Detail x Month'!L428 | CI53: ='3B. Tel. - Rev. Detail x Month'!M428 | CJ53: ='3B. Tel. - Rev. Detail x Month'!N428 | CK53: ='3B. Tel. - Rev. Detail x Month'!O428 | CL53: ='3B. Tel. - Rev. Detail x Month'!P428 | CM53: ='3B. Tel. - Rev. Detail x Month'!Q428 | ... CQ53: ='3B. Tel. - Rev. Detail x Month'!U428 | CS53: =SUM(CF53:CQ53)
B54: ● | C54: Melanie Salvador Commission (paid based on tranches) | I54: 0 | J54: ='[4]$25M Investment'!$H$153 | K54: 0 | L54: 0 | M54: 250000 | Q54: 0 | R54: 0 | S54: 0 | T54: 0 | V54: =SUM(I54:T54) | X54: 0 | Y54: 0 | Z54: 0 | AA54: 0 | AB54: 0 | AC54: 0 | AD54: 0 | AE54: 0 | AF54: 0 | AG54: 0 | AH54: 0 | AI54: 0 | AK54: =SUM(X54:AI54) | AM54: 0 | AN54: 0 | AO54: 0 | AP54: 0 | AQ54: 0 | AR54: 0 | AS54: 0 | AT54: 0 | AU54: 0 | AV54: 0 | AW54: 0 | AX54: 0 | AZ54: =SUM(AM54:AX54) | BB54: 0 | BC54: 0 | BD54: 0 | BE54: 0 | BF54: 0 | BG54: 0 | BH54: 0 | BI54: 0 | BJ54: 0 | BK54: 0 | BL54: 0 | BM54: 0 | BO54: =SUM(BB54:BM54) | BQ54: 0 | BR54: 0 | BS54: 0 | BT54: 0 | BU54: 0 | BV54: 0 | BW54: 0 | BX54: 0 | BY54: 0 | BZ54: 0 | CA54: 0 | CB54: 0 | CD54: =SUM(BQ54:CB54) | CF54: 0 | CG54: 0 | CH54: 0 | CI54: 0 | CJ54: 0 | CK54: 0 | CL54: 0 | CM54: 0 | CN54: 0 | CO54: 0 | CP54: 0 | CQ54: 0 | CS54: =SUM(CF54:CQ54)
B55: ● | C55: Capital Expenditures | I55: ='6B. Pre-Launch Exps. - Detail'!F130 | J55: ='6B. Pre-Launch Exps. - Detail'!G130 | K55: ='6B. Pre-Launch Exps. - Detail'!H130 | L55: ='6B. Pre-Launch Exps. - Detail'!I130 | M55: ='6B. Pre-Launch Exps. - Detail'!J130 | N55: ='6B. Pre-Launch Exps. - Detail'!K130 | O55: ='6B. Pre-Launch Exps. - Detail'!L130 | P55: ='6B. Pre-Launch Exps. - Detail'!M130 | ... T55: ='6B. Pre-Launch Exps. - Detail'!Q130 | V55: =SUM(I55:T55) | X55: =ABS(+'4B. Tel. Expense Assumptions'!F394-'4B. Tel. Expense Assumptions'!G394) | Y55: =ABS(+'4B. Tel. Expense Assumptions'!G394-'4B. Tel. Expense Assumptions'!H394) | Z55: =ABS(+'4B. Tel. Expense Assumptions'!H394-'4B. Tel. Expense Assumptions'!I394) | AA55: =ABS(+'4B. Tel. Expense Assumptions'!I394-'4B. Tel. Expense Assumptions'!J394) | AB55: =ABS(+'4B. Tel. Expense Assumptions'!J394-'4B. Tel. Expense Assumptions'!K394) | AC55: =ABS(+'4B. Tel. Expense Assumptions'!K394-'4B. Tel. Expense Assumptions'!L394) | AD55: =ABS(+'4B. Tel. Expense Assumptions'!L394-'4B. Tel. Expense Assumptions'!M394) | AE55: =ABS(+'4B. Tel. Expense Assumptions'!M394-'4B. Tel. Expense Assumptions'!N394) | ... AI55: =ABS(+'4B. Tel. Expense Assumptions'!Q394-'4B. Tel. Expense Assumptions'!R394) | AK55: =SUM(X55:AI55) | AM55: =ABS(+'4B. Tel. Expense Assumptions'!R394-'4B. Tel. Expense Assumptions'!S394) | AN55: =ABS(+'4B. Tel. Expense Assumptions'!S394-'4B. Tel. Expense Assumptions'!T394) | AO55: =ABS(+'4B. Tel. Expense Assumptions'!T394-'4B. Tel. Expense Assumptions'!U394) | AP55: =ABS(+'4B. Tel. Expense Assumptions'!U394-'4B. Tel. Expense Assumptions'!V394) | AQ55: =ABS(+'4B. Tel. Expense Assumptions'!V394-'4B. Tel. Expense Assumptions'!W394) | AR55: =ABS(+'4B. Tel. Expense Assumptions'!W394-'4B. Tel. Expense Assumptions'!X394) | AS55: =ABS(+'4B. Tel. Expense Assumptions'!X394-'4B. Tel. Expense Assumptions'!Y394) | AT55: =ABS(+'4B. Tel. Expense Assumptions'!Y394-'4B. Tel. Expense Assumptions'!Z394) | ... AX55: =ABS(+'4B. Tel. Expense Assumptions'!AC394-'4B. Tel. Expense Assumptions'!AD394) | AZ55: =SUM(AM55:AX55) | BB55: =ABS(+'4B. Tel. Expense Assumptions'!AD394-'4B. Tel. Expense Assumptions'!AE394) | BC55: =ABS(+'4B. Tel. Expense Assumptions'!AE394-'4B. Tel. Expense Assumptions'!AF394) | BD55: =ABS(+'4B. Tel. Expense Assumptions'!AF394-'4B. Tel. Expense Assumptions'!AG394) | BE55: =ABS(+'4B. Tel. Expense Assumptions'!AG394-'4B. Tel. Expense Assumptions'!AH394) | BF55: =ABS(+'4B. Tel. Expense Assumptions'!AH394-'4B. Tel. Expense Assumptions'!AI394) | BG55: =ABS(+'4B. Tel. Expense Assumptions'!AI394-'4B. Tel. Expense Assumptions'!AJ394) | BH55: =ABS(+'4B. Tel. Expense Assumptions'!AJ394-'4B. Tel. Expense Assumptions'!AK394) | BI55: =ABS(+'4B. Tel. Expense Assumptions'!AK394-'4B. Tel. Expense Assumptions'!AL394) | ... BM55: =ABS(+'4B. Tel. Expense Assumptions'!AO394-'4B. Tel. Expense Assumptions'!AP394) | BO55: =SUM(BB55:BM55) | BQ55: =ABS(+'4B. Tel. Expense Assumptions'!AP394-'4B. Tel. Expense Assumptions'!AQ394) | BR55: =ABS(+'4B. Tel. Expense Assumptions'!AQ394-'4B. Tel. Expense Assumptions'!AR394) | BS55: =ABS(+'4B. Tel. Expense Assumptions'!AR394-'4B. Tel. Expense Assumptions'!AS394) | BT55: =ABS(+'4B. Tel. Expense Assumptions'!AS394-'4B. Tel. Expense Assumptions'!AT394) | BU55: =ABS(+'4B. Tel. Expense Assumptions'!AT394-'4B. Tel. Expense Assumptions'!AU394) | BV55: =ABS(+'4B. Tel. Expense Assumptions'!AU394-'4B. Tel. Expense Assumptions'!AV394) | BW55: =ABS(+'4B. Tel. Expense Assumptions'!AV394-'4B. Tel. Expense Assumptions'!AW394) | BX55: =ABS(+'4B. Tel. Expense Assumptions'!AW394-'4B. Tel. Expense Assumptions'!AX394) | ... CB55: =ABS(+'4B. Tel. Expense Assumptions'!BA394-'4B. Tel. Expense Assumptions'!BB394) | CD55: =SUM(BQ55:CB55) | CF55: =ABS(+'4B. Tel. Expense Assumptions'!BB394-'4B. Tel. Expense Assumptions'!BC394) | CG55: =ABS(+'4B. Tel. Expense Assumptions'!BC394-'4B. Tel. Expense Assumptions'!BD394) | CH55: =ABS(+'4B. Tel. Expense Assumptions'!BD394-'4B. Tel. Expense Assumptions'!BE394) | CI55: =ABS(+'4B. Tel. Expense Assumptions'!BE394-'4B. Tel. Expense Assumptions'!BF394) | CJ55: =ABS(+'4B. Tel. Expense Assumptions'!BF394-'4B. Tel. Expense Assumptions'!BG394) | CK55: =ABS(+'4B. Tel. Expense Assumptions'!BG394-'4B. Tel. Expense Assumptions'!BH394) | CL55: =ABS(+'4B. Tel. Expense Assumptions'!BH394-'4B. Tel. Expense Assumptions'!BI394) | CM55: =ABS(+'4B. Tel. Expense Assumptions'!BI394-'4B. Tel. Expense Assumptions'!BJ394) | ... CQ55: =ABS(+'4B. Tel. Expense Assumptions'!BM394-'4B. Tel. Expense Assumptions'!BN394) | CS55: =SUM(CF55:CQ55)
B56: ● | C56: Pure Influence - Expenditures | Q56: ='7. Pure Influence'!G18 | R56: ='7. Pure Influence'!H18 | S56: ='7. Pure Influence'!I18 | T56: ='7. Pure Influence'!J18 | V56: =SUM(I56:T56) | X56: ='7. Pure Influence'!K18 | Y56: ='7. Pure Influence'!L18 | Z56: ='7. Pure Influence'!M18 | AA56: ='7. Pure Influence'!N18 | AB56: =('7. Pure Influence'!O18) | AC56: =('7. Pure Influence'!P18) | AD56: =('7. Pure Influence'!Q18) | AE56: =('7. Pure Influence'!R18) | AF56: ='7. Pure Influence'!G35 | AG56: ='7. Pure Influence'!H35 | AH56: ='7. Pure Influence'!I35 | AI56: ='7. Pure Influence'!J35 | AK56: =SUM(X56:AI56) | AM56: ='7. Pure Influence'!K35 | AN56: ='7. Pure Influence'!L35 | AO56: ='7. Pure Influence'!M35 | AP56: ='7. Pure Influence'!N35 | AQ56: ='7. Pure Influence'!O35 | AR56: ='7. Pure Influence'!P35 | AS56: ='7. Pure Influence'!Q35 | AT56: ='7. Pure Influence'!R35 | AU56: ='7. Pure Influence'!G52 | AV56: ='7. Pure Influence'!H52 | AW56: ='7. Pure Influence'!I52 | AX56: ='7. Pure Influence'!J52 | AZ56: =SUM(AM56:AX56) | BB56: ='7. Pure Influence'!K52 | BC56: ='7. Pure Influence'!L52 | BD56: ='7. Pure Influence'!M52 | BE56: ='7. Pure Influence'!N52 | BF56: ='7. Pure Influence'!O52 | BG56: ='7. Pure Influence'!P52 | BH56: ='7. Pure Influence'!Q52 | BI56: ='7. Pure Influence'!R52 | BJ56: ='7. Pure Influence'!G69 | BK56: ='7. Pure Influence'!H69 | BL56: ='7. Pure Influence'!I69 | BM56: ='7. Pure Influence'!J69 | BO56: =SUM(BB56:BM56) | BQ56: ='7. Pure Influence'!K69 | BR56: ='7. Pure Influence'!L69 | BS56: ='7. Pure Influence'!M69 | BT56: ='7. Pure Influence'!N69 | BU56: ='7. Pure Influence'!O69 | BV56: ='7. Pure Influence'!P69 | BW56: ='7. Pure Influence'!Q69 | BX56: ='7. Pure Influence'!R69 | BY56: ='7. Pure Influence'!G86 | BZ56: ='7. Pure Influence'!H86 | CA56: ='7. Pure Influence'!I86 | CB56: ='7. Pure Influence'!J86 | CD56: =SUM(BQ56:CB56) | CF56: ='7. Pure Influence'!K86 | CG56: ='7. Pure Influence'!L86 | CH56: ='7. Pure Influence'!M86 | CI56: ='7. Pure Influence'!N86 | CJ56: ='7. Pure Influence'!O86 | CK56: ='7. Pure Influence'!P86 | CL56: ='7. Pure Influence'!Q86 | CM56: ='7. Pure Influence'!R86 | CN56: ='7. Pure Influence'!G103 | CO56: ='7. Pure Influence'!H103 | CP56: ='7. Pure Influence'!I103 | CQ56: ='7. Pure Influence'!J103 | CS56: =SUM(CF56:CQ56) | CU56: ='7. Pure Influence'!K103 | CV56: ='7. Pure Influence'!L103 | CW56: ='7. Pure Influence'!M103 | CX56: ='7. Pure Influence'!N103 | CY56: ='7. Pure Influence'!O103 | CZ56: ='7. Pure Influence'!P103 | DA56: ='7. Pure Influence'!Q103 | DB56: ='7. Pure Influence'!R103
B57: ● | C57: CPG Model - Expenditures | S57: ='10. CPG Projections'!B24 | T57: ='10. CPG Projections'!C24 | V57: =SUM(I57:T57) | X57: ='10. CPG Projections'!D24 | Y57: ='10. CPG Projections'!E24 | Z57: ='10. CPG Projections'!F24 | AA57: ='10. CPG Projections'!G24 | AB57: ='10. CPG Projections'!H24 | AC57: ='10. CPG Projections'!I24 | AD57: ='10. CPG Projections'!J24 | AE57: ='10. CPG Projections'!K24 | ... AG57: ='10. CPG Projections'!M24 | AH57: ='10. CPG Projections'!O24 | AI57: ='10. CPG Projections'!P24 | AK57: =SUM(X57:AI57) | AM57: ='10. CPG Projections'!Q24 | AN57: ='10. CPG Projections'!R24 | AO57: ='10. CPG Projections'!S24 | AP57: ='10. CPG Projections'!T24 | AQ57: ='10. CPG Projections'!U24 | AR57: ='10. CPG Projections'!V24 | AS57: ='10. CPG Projections'!W24 | AT57: ='10. CPG Projections'!X24 | ... AV57: ='10. CPG Projections'!Z24 | AW57: ='10. CPG Projections'!AB24 | AX57: ='10. CPG Projections'!AC24 | AZ57: =SUM(AM57:AX57) | BB57: ='10. CPG Projections'!AD24 | BC57: ='10. CPG Projections'!AE24 | BD57: ='10. CPG Projections'!AF24 | BE57: ='10. CPG Projections'!AG24 | BF57: ='10. CPG Projections'!AH24 | BG57: ='10. CPG Projections'!AI24 | BH57: ='10. CPG Projections'!AJ24 | BI57: ='10. CPG Projections'!AK24 | ... BK57: ='10. CPG Projections'!AM24 | BL57: ='10. CPG Projections'!AO24 | BM57: ='10. CPG Projections'!AP24 | BO57: =SUM(BB57:BM57) | BQ57: ='10. CPG Projections'!AQ24 | BR57: ='10. CPG Projections'!AR24 | BS57: ='10. CPG Projections'!AS24 | BT57: ='10. CPG Projections'!AT24 | BU57: ='10. CPG Projections'!AU24 | BV57: ='10. CPG Projections'!AV24 | BW57: ='10. CPG Projections'!AW24 | BX57: ='10. CPG Projections'!AX24 | ... BZ57: ='10. CPG Projections'!AZ24 | CA57: ='10. CPG Projections'!BB24 | CB57: ='10. CPG Projections'!BC24 | CD57: =SUM(BQ57:CB57) | CF57: ='10. CPG Projections'!BD24 | CG57: ='10. CPG Projections'!BE24 | CH57: ='10. CPG Projections'!BF24 | CI57: ='10. CPG Projections'!BG24 | CJ57: ='10. CPG Projections'!BH24 | CK57: ='10. CPG Projections'!BI24 | CL57: ='10. CPG Projections'!BJ24 | CM57: ='10. CPG Projections'!BK24 | ... CO57: ='10. CPG Projections'!BM24 | CP57: 0 | CQ57: 0 | CS57: =SUM(CF57:CQ57)
B58: ● | C58: Camera Commerce - Expenditures | N58: ='9. Camera Commerce'!B17 | O58: ='9. Camera Commerce'!C17 | P58: ='9. Camera Commerce'!D17 | Q58: ='9. Camera Commerce'!E17 | R58: ='9. Camera Commerce'!F17 | S58: ='9. Camera Commerce'!G17 | T58: ='9. Camera Commerce'!H17 | V58: =SUM(I58:T58) | X58: ='9. Camera Commerce'!I17 | Y58: ='9. Camera Commerce'!J17 | Z58: ='9. Camera Commerce'!K17 | AA58: ='9. Camera Commerce'!L17 | AB58: ='9. Camera Commerce'!M17 | AC58: ='9. Camera Commerce'!O17 | AD58: ='9. Camera Commerce'!P17 | AE58: ='9. Camera Commerce'!Q17 | AF58: ='9. Camera Commerce'!R17 | AG58: ='9. Camera Commerce'!S17 | AH58: ='9. Camera Commerce'!T17 | AI58: ='9. Camera Commerce'!U17 | AK58: =SUM(X58:AI58) | AM58: ='9. Camera Commerce'!V17 | AN58: ='9. Camera Commerce'!W17 | AO58: ='9. Camera Commerce'!X17 | AP58: ='9. Camera Commerce'!Y17 | AQ58: ='9. Camera Commerce'!Z17 | AR58: ='9. Camera Commerce'!AB17 | AS58: ='9. Camera Commerce'!AC17 | AT58: ='9. Camera Commerce'!AD17 | AU58: ='9. Camera Commerce'!AE17 | AV58: ='9. Camera Commerce'!AF17 | AW58: ='9. Camera Commerce'!AG17 | AX58: ='9. Camera Commerce'!AH17 | AZ58: =SUM(AM58:AX58) | BB58: ='9. Camera Commerce'!AI17 | BC58: ='9. Camera Commerce'!AJ17 | BD58: ='9. Camera Commerce'!AK17 | BE58: ='9. Camera Commerce'!AL17 | BF58: ='9. Camera Commerce'!AM17 | BG58: ='9. Camera Commerce'!AO17 | BH58: ='9. Camera Commerce'!AP17 | BI58: ='9. Camera Commerce'!AQ17 | BJ58: ='9. Camera Commerce'!AR17 | BK58: ='9. Camera Commerce'!AS17 | BL58: ='9. Camera Commerce'!AT17 | BM58: ='9. Camera Commerce'!AU17 | BO58: =SUM(BB58:BM58) | BQ58: ='9. Camera Commerce'!AV17 | BR58: ='9. Camera Commerce'!AW17 | BS58: ='9. Camera Commerce'!AX17 | BT58: ='9. Camera Commerce'!AY17 | BU58: ='9. Camera Commerce'!AZ17 | BV58: ='9. Camera Commerce'!BB17 | BW58: ='9. Camera Commerce'!BC17 | BX58: ='9. Camera Commerce'!BD17 | BY58: ='9. Camera Commerce'!BE17 | BZ58: ='9. Camera Commerce'!BF17 | CA58: ='9. Camera Commerce'!BG17 | CB58: ='9. Camera Commerce'!BH17 | CD58: =SUM(BQ58:CB58) | CF58: ='9. Camera Commerce'!BI17 | CG58: ='9. Camera Commerce'!BJ17 | CH58: ='9. Camera Commerce'!BK17 | CI58: ='9. Camera Commerce'!BL17 | CJ58: ='9. Camera Commerce'!BM17 | CS58: =SUM(CF58:CQ58)
B59: ● | C59: Token Raise Expenses | I59: 0 | J59: 0 | K59: 0 | L59: 0 | M59: 0 | N59: 0 | O59: 0 | P59: 0 | Q59: 0 | R59: 0 | S59: 0 | T59: 0 | V59: =SUM(I59:T59) | X59: 0 | Y59: 0 | Z59: 0 | AA59: 0 | AB59: 0 | AC59: 0 | AD59: 0 | AE59: 0 | AF59: 0 | AG59: 0 | AH59: 0 | AI59: 0 | AK59: =SUM(X59:AI59) | AM59: 0 | AN59: 0 | AO59: 0 | AP59: 0 | AQ59: 0 | AR59: =((10000000)/(7)) | AS59: =((10000000)/(7)) | AT59: =((10000000)/(7)) | AU59: =((10000000)/(7)) | AV59: =((10000000)/(7)) | AW59: =((10000000)/(7)) | AX59: =((10000000)/(7)) | AZ59: =SUM(AM59:AX59) | BB59: 0 | BC59: 0 | BD59: 0 | BE59: 0 | BF59: 0 | BG59: 0 | BH59: 0 | BI59: 0 | BJ59: 0 | BK59: 0 | BL59: 0 | BM59: 0 | BO59: =SUM(BB59:BM59) | BQ59: 0 | BR59: 0 | BS59: 0 | BT59: 0 | BU59: 0 | BV59: 0 | BW59: 0 | BX59: 0 | BY59: 0 | BZ59: 0 | CA59: 0 | CB59: 0 | CD59: =SUM(BQ59:CB59) | CF59: 0 | CG59: 0 | CH59: 0 | CI59: 0 | CJ59: 0 | CK59: 0 | CL59: 0 | CM59: 0 | CN59: 0 | CO59: 0 | CP59: 0 | CQ59: 0 | CS59: =SUM(CF59:CQ59)
B60: ● | C60: Working Capital Financing - Repayments | I60: 0 | J60: 0 | K60: 0 | L60: 0 | M60: 0 | N60: 0 | O60: 0 | P60: 0 | Q60: 0 | R60: 0 | S60: 0 | T60: 0 | V60: =SUM(I60:T60) | X60: 0 | Y60: 0 | Z60: 0 | AA60: 0 | AB60: 0 | AC60: 0 | AD60: 0 | AE60: 0 | AF60: 0 | AG60: 0 | AH60: 0 | AI60: 0 | AK60: =SUM(X60:AI60) | AM60: 0 | AN60: 0 | AO60: 0 | AP60: 0 | AQ60: 0 | AR60: 0 | AS60: 0 | AT60: 0 | AU60: 0 | AV60: 0 | AW60: 0 | AX60: 0 | AZ60: =SUM(AM60:AX60) | BO60: =SUM(BB60:BM60) | CD60: =SUM(BQ60:CB60) | CS60: =SUM(CF60:CQ60)
D63: Total Cash Disbursements | I63: =SUM(I43:I60) | J63: =SUM(J43:J60) | K63: =SUM(K43:K60) | L63: =SUM(L43:L60) | M63: =SUM(M43:M60) | N63: =SUM(N43:N60) | O63: =SUM(O43:O60) | P63: =SUM(P43:P60) | ... T63: =SUM(T43:T60) | V63: =SUM(V43:V60) | X63: =SUM(X43:X60) | Y63: =SUM(Y43:Y60) | Z63: =SUM(Z43:Z60) | AA63: =SUM(AA43:AA60) | AB63: =SUM(AB43:AB60) | AC63: =SUM(AC43:AC60) | AD63: =SUM(AD43:AD60) | AE63: =SUM(AE43:AE60) | ... AI63: =SUM(AI43:AI60) | AK63: =SUM(AK43:AK60) | AM63: =SUM(AM43:AM60) | AN63: =SUM(AN43:AN60) | AO63: =SUM(AO43:AO60) | AP63: =SUM(AP43:AP60) | AQ63: =SUM(AQ43:AQ60) | AR63: =SUM(AR43:AR60) | AS63: =SUM(AS43:AS60) | AT63: =SUM(AT43:AT60) | ... AX63: =SUM(AX43:AX60) | AZ63: =SUM(AZ43:AZ60) | BB63: =SUM(BB43:BB60) | BC63: =SUM(BC43:BC60) | BD63: =SUM(BD43:BD60) | BE63: =SUM(BE43:BE60) | BF63: =SUM(BF43:BF60) | BG63: =SUM(BG43:BG60) | BH63: =SUM(BH43:BH60) | BI63: =SUM(BI43:BI60) | ... BM63: =SUM(BM43:BM60) | BO63: =SUM(BO43:BO60) | BQ63: =SUM(BQ43:BQ60) | BR63: =SUM(BR43:BR60) | BS63: =SUM(BS43:BS60) | BT63: =SUM(BT43:BT60) | BU63: =SUM(BU43:BU60) | BV63: =SUM(BV43:BV60) | BW63: =SUM(BW43:BW60) | BX63: =SUM(BX43:BX60) | ... CB63: =SUM(CB43:CB60) | CD63: =SUM(CD43:CD60) | CF63: =SUM(CF43:CF60) | CG63: =SUM(CG43:CG60) | CH63: =SUM(CH43:CH60) | CI63: =SUM(CI43:CI60) | CJ63: =SUM(CJ43:CJ60) | CK63: =SUM(CK43:CK60) | CL63: =SUM(CL43:CL60) | CM63: =SUM(CM43:CM60) | ... CQ63: =SUM(CQ43:CQ60) | CS63: =SUM(CS43:CS60) | CU63: =SUM(CF63:CQ63) | CV63: checked
B68: Cash Generated / (Used) | I68: =((I37)-(I63)) | J68: =((J37)-(J63)) | K68: =((K37)-(K63)) | L68: =((L37)-(L63)) | M68: =((M37)-(M63)) | N68: =((N37)-(N63)) | O68: =((O37)-(O63)) | P68: =((P37)-(P63)) | ... T68: =((T37)-(T63)) | V68: =((V37)-(V63)) | X68: =((X37)-(X63)) | Y68: =((Y37)-(Y63)) | Z68: =((Z37)-(Z63)) | AA68: =((AA37)-(AA63)) | AB68: =((AB37)-(AB63)) | AC68: =((AC37)-(AC63)) | AD68: =((AD37)-(AD63)) | AE68: =((AE37)-(AE63)) | ... AI68: =((AI37)-(AI63)) | AK68: =((AK37)-(AK63)) | AM68: =((AM37)-(AM63)) | AN68: =((AN37)-(AN63)) | AO68: =((AO37)-(AO63)) | AP68: =((AP37)-(AP63)) | AQ68: =((AQ37)-(AQ63)) | AR68: =((AR37)-(AR63)) | AS68: =((AS37)-(AS63)) | AT68: =((AT37)-(AT63)) | ... AX68: =((AX37)-(AX63)) | AZ68: =((AZ37)-(AZ63)) | BB68: =((BB37)-(BB63)) | BC68: =((BC37)-(BC63)) | BD68: =((BD37)-(BD63)) | BE68: =((BE37)-(BE63)) | BF68: =((BF37)-(BF63)) | BG68: =((BG37)-(BG63)) | BH68: =((BH37)-(BH63)) | BI68: =((BI37)-(BI63)) | ... BM68: =((BM37)-(BM63)) | BO68: =((BO37)-(BO63)) | BQ68: =((BQ37)-(BQ63)) | BR68: =((BR37)-(BR63)) | BS68: =((BS37)-(BS63)) | BT68: =((BT37)-(BT63)) | BU68: =((BU37)-(BU63)) | BV68: =((BV37)-(BV63)) | BW68: =((BW37)-(BW63)) | BX68: =((BX37)-(BX63)) | ... CB68: =((CB37)-(CB63)) | CD68: =((CD37)-(CD63)) | CF68: =((CF37)-(CF63)) | CG68: =((CG37)-(CG63)) | CH68: =((CH37)-(CH63)) | CI68: =((CI37)-(CI63)) | CJ68: =((CJ37)-(CJ63)) | CK68: =((CK37)-(CK63)) | CL68: =((CL37)-(CL63)) | CM68: =((CM37)-(CM63)) | ... CQ68: =((CQ37)-(CQ63)) | CS68: =((CS37)-(CS63))
AI69: Double Checked | AK69: =AK63-AK49+'1A. Consolidated - FY P&L'!J42 | AX69: Double Checked | AZ69: =(AZ63-AZ49)+'1A. Consolidated - FY P&L'!K42 | BM69: Double Checked | BO69: =(BO63-BO49)+'1A. Consolidated - FY P&L'!L42 | CB69: Double Checked | CD69: =(CD63-CD49)+'1A. Consolidated - FY P&L'!M42 | CQ69: Double Checked | CS69: =(CS63-CS49)+'1A. Consolidated - FY P&L'!N42 | CU69: Check all of the numbers in this final column from 69-73
AI70: Double Checked | AK70: ='3B. Tel. - Rev. Detail x Month'!W62+'3B. Tel. - Rev. Detail x Month'!W75 | AX70: Double Checked | AZ70: ='3B. Tel. - Rev. Detail x Month'!W100+'3B. Tel. - Rev. Detail x Month'!W109+'3B. Tel. - Rev. Detail x Month'!W113 | BM70: Double Checked | BO70: ='3B. Tel. - Rev. Detail x Month'!W138+'3B. Tel. - Rev. Detail x Month'!W147+'3B. Tel. - Rev. Detail x Month'!W151 | CB70: Double Checked | CD70: ='3B. Tel. - Rev. Detail x Month'!W176+'3B. Tel. - Rev. Detail x Month'!W185+'3B. Tel. - Rev. Detail x Month'!W189 | CQ70: Double Checked | CS70: ='3B. Tel. - Rev. Detail x Month'!W214+'3B. Tel. - Rev. Detail x Month'!W223+'3B. Tel. - Rev. Detail x Month'!W227
AI71: Double Checked | AK71: =AK63-AK49 | AX71: Double Checked | AZ71: =AZ63-(AZ49) | BM71: Double Checked | BO71: =BO63-(BO49) | CB71: Double Checked | CD71: =CD63-(CD49) | CQ71: Double Checked | CS71: =CS63-(CS49) | CU71: ='1A. Consolidated - FY P&L'!N63-'2A. Cash Forecast'!CS71
T72: Double Checked | V72: =V68-5000000 | AI72: Double Checked | AK72: =AK40-AK70-AK71 | AX72: Double Checked | AZ72: =AZ40-AZ70-AZ71 | BM72: Double Checked | BO72: =BO40-BO70-BO71 | CB72: Double Checked | CD72: =CD40-CD70-CD71 | CQ72: Double Checked | CS72: =CS40-CS70-CS71
C73: Ending Balance | I73: =((I21)+(I68)) | J73: =((J21)+(J68)) | K73: =((K21)+(K68)) | L73: =((L21)+(L68)) | M73: =((M21)+(M68)) | N73: =((N21)+(N68)) | O73: =((O21)+(O68)) | P73: =((P21)+(P68)) | ... T73: =((T21)+(T68)) | V73: =((V21)+(V68)) | X73: =((X21)+(X68)) | Y73: =((Y21)+(Y68)) | Z73: =((Z21)+(Z68)) | AA73: =((AA21)+(AA68)) | AB73: =((AB21)+(AB68)) | AC73: =((AC21)+(AC68)) | AD73: =((AD21)+(AD68)) | AE73: =((AE21)+(AE68)) | ... AI73: =((AI21)+(AI68)) | AK73: =((AK21)+(AK68)) | AM73: =((AM21)+(AM68)) | AN73: =((AN21)+(AN68)) | AO73: =((AO21)+(AO68)) | AP73: =((AP21)+(AP68)) | AQ73: =((AQ21)+(AQ68)) | AR73: =((AR21)+(AR68)) | AS73: =((AS21)+(AS68)) | AT73: =((AT21)+(AT68)) | ... AX73: =((AX21)+(AX68)) | AZ73: =((AZ21)+(AZ68)) | BB73: =((BB21)+(BB68)) | BC73: =((BC21)+(BC68)) | BD73: =((BD21)+(BD68)) | BE73: =((BE21)+(BE68)) | BF73: =((BF21)+(BF68)) | BG73: =((BG21)+(BG68)) | BH73: =((BH21)+(BH68)) | BI73: =((BI21)+(BI68)) | ... BM73: =((BM21)+(BM68)) | BO73: =((BO21)+(BO68)) | BQ73: =((BQ21)+(BQ68)) | BR73: =((BR21)+(BR68)) | BS73: =((BS21)+(BS68)) | BT73: =((BT21)+(BT68)) | BU73: =((BU21)+(BU68)) | BV73: =((BV21)+(BV68)) | BW73: =((BW21)+(BW68)) | BX73: =((BX21)+(BX68)) | ... CB73: =((CB21)+(CB68)) | CD73: =((CD21)+(CD68)) | CF73: =((CF21)+(CF68)) | CG73: =((CG21)+(CG68)) | CH73: =((CH21)+(CH68)) | CI73: =((CI21)+(CI68)) | CJ73: =((CJ21)+(CJ68)) | CK73: =((CK21)+(CK68)) | CL73: =((CL21)+(CL68)) | CM73: =((CM21)+(CM68)) | ... CQ73: =((CQ21)+(CQ68)) | CS73: =((CS21)+(CS68))
T77: Core Model | AI77: Core Model | AX77: Core Model | BM77: Core Model | CB77: Core Model | CQ77: Core Model
T78: Double Checked | V78: =V63-(V56+V57) | AI78: Double Checked | AK78: =AK63-(AK56+AK57+AK58+AK49)+'3B. Tel. - Rev. Detail x Month'!W62+'3B. Tel. - Rev. Detail x Month'!W75 | AX78: Double Checked | AZ78: =AZ63-(AZ56+AZ57+AZ58+AZ49)+'3B. Tel. - Rev. Detail x Month'!W100+'3B. Tel. - Rev. Detail x Month'!W109+'3B. Tel. - Rev. Detail x Month'!W113 | BM78: Double Checked | BO78: =BO63-(BO56+BO57+BO58+BO49)+'3B. Tel. - Rev. Detail x Month'!W138+'3B. Tel. - Rev. Detail x Month'!W147+'3B. Tel. - Rev. Detail x Month'!W151 | CB78: Double Checked | CD78: =CD63-(CD56+CD57+CD58+CD49)+'3B. Tel. - Rev. Detail x Month'!W176+'3B. Tel. - Rev. Detail x Month'!W185+'3B. Tel. - Rev. Detail x Month'!W189 | CQ78: Double Checked | CS78: =CS63-(CS56+CS57+CS58+CS49)+'3B. Tel. - Rev. Detail x Month'!W214+'3B. Tel. - Rev. Detail x Month'!W223+'3B. Tel. - Rev. Detail x Month'!W227
T79: Double Checked | AI79: Double Checked | AK79: ='3B. Tel. - Rev. Detail x Month'!W62+'3B. Tel. - Rev. Detail x Month'!W75 | AX79: Double Checked | AZ79: ='3B. Tel. - Rev. Detail x Month'!W100+'3B. Tel. - Rev. Detail x Month'!W109+'3B. Tel. - Rev. Detail x Month'!W113 | BM79: Double Checked | BO79: ='3B. Tel. - Rev. Detail x Month'!W138+'3B. Tel. - Rev. Detail x Month'!W147+'3B. Tel. - Rev. Detail x Month'!W151 | CB79: Double Checked | CD79: ='3B. Tel. - Rev. Detail x Month'!W176+'3B. Tel. - Rev. Detail x Month'!W185+'3B. Tel. - Rev. Detail x Month'!W189 | CQ79: Double Checked | CS79: ='3B. Tel. - Rev. Detail x Month'!W214+'3B. Tel. - Rev. Detail x Month'!W223+'3B. Tel. - Rev. Detail x Month'!W227
T80: Double Checked | AI80: Double Checked | AK80: =AK63-AK49-AK56-AK57-AK58 | AX80: Double Checked | AZ80: =AZ63-AZ49-AZ56-AZ57-AZ58 | BM80: Double Checked | BO80: =BO63-BO49-BO56-BO57-BO58 | CB80: Double Checked | CD80: =CD63-CD49-CD56-CD57-CD58 | CQ80: Double Checked | CS80: =CS63-CS49-CS56-CS57-CS58
T81: Double Checked | V81: =V41-V78 | AI81: Double Checked | AK81: =AK41-AK79-AK80 | AX81: Double Checked | AZ81: =AZ41-AZ79-AZ80 | BM81: Double Checked | BO81: =BO41-BO79-BO80 | CB81: Double Checked | CD81: =CD41-CD79-CD80 | CQ81: Double Checked | CS81: =CS41-CS79-CS80
T88: Total Ops Expense | V88: ='6A. Pre-Launch Exps. - Roll-Up'!X94
T89: Difference | V89: =V63-V88

Sheet Cash Flow
A1: =Summary!A1
B3: Cash Flow Projections
C4: Monthly
Q5: For the Year Ended | AC5: For the Year Ended | AO5: For the Year Ended | BA5: For the Year Ended | BM5: For the Year Ended
Q6: FY1 | AC6: FY2 | AO6: FY3 | BA6: FY4 | BM6: FY5 | CC6: Five Year Projections
E7: -12 | F7: -11 | G7: -10 | H7: -9 | I7: -8 | J7: -7 | K7: -6 | L7: -5 | M7: -4 | N7: -3 | O7: -2 | P7: -1 | Q7: ='Income Statement'!Q6 | R7: ='Income Statement'!R6 | S7: ='Income Statement'!S6 | T7: ='Income Statement'!T6 | U7: ='Income Statement'!U6 | V7: ='Income Statement'!V6 | W7: ='Income Statement'!W6 | X7: ='Income Statement'!X6 | ... BX7: ='Income Statement'!BX6 | CD7: Ramp Up Year | CE7: Year 1 | CF7: Year 2 | CG7: Year 3 | CH7: Year 4 | CI7: Year 5
B8: CASH FLOW FROM OPERATIONS | BZ8: CASH FLOW FROM OPERATIONS
C9: Net Income (Loss) | E9: =+'Income Statement'!E39 | F9: =+'Income Statement'!F39 | G9: =+'Income Statement'!G39 | H9: =+'Income Statement'!H39 | I9: =+'Income Statement'!I39 | J9: =+'Income Statement'!J39 | K9: =+'Income Statement'!K39 | L9: =+'Income Statement'!L39 | ... BX9: =+'Income Statement'!BX39 | CA9: Net Income (Loss) | CD9: =SUM(E9:P9) | CE9: =SUM(Q9:AB9) | CF9: =SUM(AC9:AN9) | CG9: =SUM(AO9:AZ9) | CH9: =SUM(BA9:BL9) | CI9: =SUM(BM9:BX9)
C10: Plus Amortization | E10: =+'Income Statement'!K28 | F10: =+'Income Statement'!L28 | G10: =+'Income Statement'!M28 | H10: =+'Income Statement'!N28 | I10: =+'Income Statement'!O28 | J10: =+'Income Statement'!P28 | K10: =+'Income Statement'!K28 | L10: =+'Income Statement'!L28 | M10: =+'Income Statement'!M28 | N10: =+'Income Statement'!N28 | O10: =+'Income Statement'!O28 | P10: =+'Income Statement'!P28 | Q10: =+'Income Statement'!Q28 | R10: =+'Income Statement'!R28 | ... BX10: =+'Income Statement'!BX28 | CA10: Plus Amortization | CD10: =SUM(E10:P10) | CE10: =SUM(Q10:AB10) | CF10: =SUM(AC10:AN10) | CG10: =SUM(AO10:AZ10) | CH10: =SUM(BA10:BL10) | CI10: =SUM(BM10:BX10)
C12: Changes in Working Capital | CA12: Changes in Working Capital
C13: Changes inventory | E13: =+'Balance Sheet'!D10-'Balance Sheet'!E10 | F13: =+'Balance Sheet'!E10-'Balance Sheet'!F10 | G13: =+'Balance Sheet'!F10-'Balance Sheet'!G10 | H13: =+'Balance Sheet'!G10-'Balance Sheet'!H10 | I13: =+'Balance Sheet'!H10-'Balance Sheet'!I10 | J13: =+'Balance Sheet'!I10-'Balance Sheet'!J10 | K13: =+'Balance Sheet'!J10-'Balance Sheet'!K10 | L13: =+'Balance Sheet'!K10-'Balance Sheet'!L10 | ... BX13: =+'Balance Sheet'!BW10-'Balance Sheet'!BX10 | CA13: Changes inventory | CD13: =SUM(E13:P13) | CE13: =SUM(Q13:AB13) | CF13: =SUM(AC13:AN13) | CG13: =SUM(AO13:AZ13) | CH13: =SUM(BA13:BL13) | CI13: =SUM(BM13:BX13)
C14: Changes in Prepaid Expenses | E14: =+'Balance Sheet'!D12-'Balance Sheet'!E12 | F14: =+'Balance Sheet'!E12-'Balance Sheet'!F12 | G14: =+'Balance Sheet'!F12-'Balance Sheet'!G12 | H14: =+'Balance Sheet'!G12-'Balance Sheet'!H12 | I14: =+'Balance Sheet'!H12-'Balance Sheet'!I12 | J14: =+'Balance Sheet'!I12-'Balance Sheet'!J12 | K14: =+'Balance Sheet'!J12-'Balance Sheet'!K12 | L14: =+'Balance Sheet'!K12-'Balance Sheet'!L12 | ... BX14: =+'Balance Sheet'!BW12-'Balance Sheet'!BX12 | CA14: Changes in Prepaid Expenses | CD14: =SUM(E14:P14) | CE14: =SUM(Q14:AB14) | CF14: =SUM(AC14:AN14) | CG14: =SUM(AO14:AZ14) | CH14: =SUM(BA14:BL14) | CI14: =SUM(BM14:BX14)
C15: Changes in CMO Deposits | E15: =+'Balance Sheet'!D11-'Balance Sheet'!E11 | F15: =+'Balance Sheet'!E11-'Balance Sheet'!F11 | G15: =+'Balance Sheet'!F11-'Balance Sheet'!G11 | H15: =+'Balance Sheet'!G11-'Balance Sheet'!H11 | I15: =+'Balance Sheet'!H11-'Balance Sheet'!I11 | J15: =+'Balance Sheet'!I11-'Balance Sheet'!J11 | K15: =+'Balance Sheet'!J11-'Balance Sheet'!K11 | L15: =+'Balance Sheet'!K11-'Balance Sheet'!L11 | ... BX15: =+'Balance Sheet'!BW11-'Balance Sheet'!BX11 | CA15: Changes in CMO Deposits | CD15: =SUM(E15:P15) | CE15: =SUM(Q15:AB15) | CF15: =SUM(AC15:AN15) | CG15: =SUM(AO15:AZ15) | CH15: =SUM(BA15:BL15) | CI15: =SUM(BM15:BX15)
C16: Changes in Inventory Held for Warranty | E16: =+'Balance Sheet'!D13-'Balance Sheet'!E13 | F16: =+'Balance Sheet'!K13-'Balance Sheet'!L13 | G16: =+'Balance Sheet'!L13-'Balance Sheet'!M13 | H16: =+'Balance Sheet'!M13-'Balance Sheet'!N13 | I16: =+'Balance Sheet'!N13-'Balance Sheet'!O13 | J16: =+'Balance Sheet'!O13-'Balance Sheet'!P13 | K16: =+'Balance Sheet'!D13-'Balance Sheet'!K13 | L16: =+'Balance Sheet'!K13-'Balance Sheet'!L13 | M16: =+'Balance Sheet'!L13-'Balance Sheet'!M13 | N16: =+'Balance Sheet'!M13-'Balance Sheet'!N13 | O16: =+'Balance Sheet'!N13-'Balance Sheet'!O13 | P16: =+'Balance Sheet'!O13-'Balance Sheet'!P13 | Q16: =+'Balance Sheet'!P13-'Balance Sheet'!Q13 | R16: =+'Balance Sheet'!Q13-'Balance Sheet'!R13 | S16: =+'Balance Sheet'!R13-'Balance Sheet'!S13 | ... BX16: =+'Balance Sheet'!BW13-'Balance Sheet'!BX13 | CA16: Changes in Inventory Held for Warranty | CD16: =SUM(E16:P16) | CE16: =SUM(Q16:AB16) | CF16: =SUM(AC16:AN16) | CG16: =SUM(AO16:AZ16) | CH16: =SUM(BA16:BL16) | CI16: =SUM(BM16:BX16)
C17: Changes in Accrued Expenses | E17: =+'Balance Sheet'!E28-'Balance Sheet'!D28 | F17: =+'Balance Sheet'!F28-'Balance Sheet'!E28 | G17: =+'Balance Sheet'!G28-'Balance Sheet'!F28 | H17: =+'Balance Sheet'!H28-'Balance Sheet'!G28 | I17: =+'Balance Sheet'!I28-'Balance Sheet'!H28 | J17: =+'Balance Sheet'!J28-'Balance Sheet'!I28 | K17: 124969 | L17: =+'Balance Sheet'!L28-'Balance Sheet'!K28 | M17: =+'Balance Sheet'!M28-'Balance Sheet'!L28 | N17: =+'Balance Sheet'!N28-'Balance Sheet'!M28 | O17: =+'Balance Sheet'!O28-'Balance Sheet'!N28 | P17: =+'Balance Sheet'!P28-'Balance Sheet'!O28 | Q17: =+'Balance Sheet'!Q28-'Balance Sheet'!P28 | R17: =+'Balance Sheet'!R28-'Balance Sheet'!Q28 | S17: =+'Balance Sheet'!S28-'Balance Sheet'!R28 | ... BX17: =+'Balance Sheet'!BX28-'Balance Sheet'!BW28 | CA17: Changes in Accrued Expenses | CD17: =SUM(E17:P17) | CE17: =SUM(Q17:AB17) | CF17: =SUM(AC17:AN17) | CG17: =SUM(AO17:AZ17) | CH17: =SUM(BA17:BL17) | CI17: =SUM(BM17:BX17)
C18: Changes in Customer Deposits | E18: =+'Balance Sheet'!E29-'Balance Sheet'!D29 | F18: =+'Balance Sheet'!F29-'Balance Sheet'!E29 | G18: =+'Balance Sheet'!G29-'Balance Sheet'!F29 | H18: =+'Balance Sheet'!H29-'Balance Sheet'!G29 | I18: =+'Balance Sheet'!I29-'Balance Sheet'!H29 | J18: =+'Balance Sheet'!J29-'Balance Sheet'!I29 | K18: =+'Balance Sheet'!K29-'Balance Sheet'!J29 | L18: =+'Balance Sheet'!L29-'Balance Sheet'!K29 | ... BX18: =+'Balance Sheet'!BX29-'Balance Sheet'!BW29 | CA18: Changes in Customer Deposits | CD18: =SUM(E18:P18) | CE18: =SUM(Q18:AB18) | CF18: =SUM(AC18:AN18) | CG18: =SUM(AO18:AZ18) | CH18: =SUM(BA18:BL18) | CI18: =SUM(BM18:BX18)
C19: Net Change in Working Capital | E19: =SUM(E13:E18) | F19: =SUM(F13:F18) | G19: =SUM(G13:G18) | H19: =SUM(H13:H18) | I19: =SUM(I13:I18) | J19: =SUM(J13:J18) | K19: =SUM(K13:K18) | L19: =SUM(L13:L18) | ... BX19: =SUM(BX13:BX18) | CA19: Net Change in Working Capital | CD19: =SUM(E19:P19) | CE19: =SUM(Q19:AB19) | CF19: =SUM(AC19:AN19) | CG19: =SUM(AO19:AZ19) | CH19: =SUM(BA19:BL19) | CI19: =SUM(BM19:BX19)
B20: Net Cash Flow from Operations | E20: =+E9+E10+E19 | F20: =+F9+F10+F19 | G20: =+G9+G10+G19 | H20: =+H9+H10+H19 | I20: =+I9+I10+I19 | J20: =+J9+J10+J19 | K20: =+K9+K10+K19 | L20: =+L9+L10+L19 | ... BX20: =+BX9+BX10+BX19 | BZ20: Net Cash Flow from Operations | CD20: =SUM(E20:P20) | CE20: =SUM(Q20:AB20) | CF20: =SUM(AC20:AN20) | CG20: =SUM(AO20:AZ20) | CH20: =SUM(BA20:BL20) | CI20: =SUM(BM20:BX20)
B22: CASH FLOW FROM INVESTMENTS | BZ22: CASH FLOW FROM INVESTMENTS
C23: Purchase of Intangibles & Other Assets | E23: =-'6B. Pre-Launch Exps. - Detail'!L122-'6B. Pre-Launch Exps. - Detail'!L123 | F23: =-'6B. Pre-Launch Exps. - Detail'!M122-'6B. Pre-Launch Exps. - Detail'!M123 | G23: =-'6B. Pre-Launch Exps. - Detail'!N122-'6B. Pre-Launch Exps. - Detail'!N123 | H23: =-'6B. Pre-Launch Exps. - Detail'!O122-'6B. Pre-Launch Exps. - Detail'!O123 | I23: =-'6B. Pre-Launch Exps. - Detail'!O122-'6B. Pre-Launch Exps. - Detail'!O123 | J23: =-'6B. Pre-Launch Exps. - Detail'!Q122-'6B. Pre-Launch Exps. - Detail'!Q123 | K23: =-'6B. Pre-Launch Exps. - Detail'!L122-'6B. Pre-Launch Exps. - Detail'!L123 | L23: =-'6B. Pre-Launch Exps. - Detail'!M122-'6B. Pre-Launch Exps. - Detail'!M123 | M23: =-'6B. Pre-Launch Exps. - Detail'!N122-'6B. Pre-Launch Exps. - Detail'!N123 | N23: =-'6B. Pre-Launch Exps. - Detail'!O122-'6B. Pre-Launch Exps. - Detail'!O123 | O23: =-'6B. Pre-Launch Exps. - Detail'!O122-'6B. Pre-Launch Exps. - Detail'!O123 | P23: =-'6B. Pre-Launch Exps. - Detail'!Q122-'6B. Pre-Launch Exps. - Detail'!Q123 | Q23: =-'4B. Tel. Expense Assumptions'!G406 | R23: =-'4B. Tel. Expense Assumptions'!H406 | S23: =-'4B. Tel. Expense Assumptions'!I406 | T23: =-'4B. Tel. Expense Assumptions'!J406 | U23: =-'4B. Tel. Expense Assumptions'!K406 | V23: =-'4B. Tel. Expense Assumptions'!L406 | W23: =-'4B. Tel. Expense Assumptions'!M406 | X23: =-'4B. Tel. Expense Assumptions'!N406 | ... BX23: =-'4B. Tel. Expense Assumptions'!BN406 | CA23: Purchase of Intangibles & Other Assets | CD23: =SUM(E23:P23) | CE23: =SUM(Q23:AB23) | CF23: =SUM(AC23:AN23) | CG23: =SUM(AO23:AZ23) | CH23: =SUM(BA23:BL23) | CI23: =SUM(BM23:BX23)
C24: Fixed Assets | E24: =-'6B. Pre-Launch Exps. - Detail'!F120-'6B. Pre-Launch Exps. - Detail'!F128 | F24: =-'6B. Pre-Launch Exps. - Detail'!G120-'6B. Pre-Launch Exps. - Detail'!G128 | G24: =-'6B. Pre-Launch Exps. - Detail'!H120-'6B. Pre-Launch Exps. - Detail'!H128 | H24: 0 | I24: =-'6B. Pre-Launch Exps. - Detail'!J120-'6B. Pre-Launch Exps. - Detail'!J128 | J24: =-'6B. Pre-Launch Exps. - Detail'!K120-'6B. Pre-Launch Exps. - Detail'!K128 | K24: =-'6B. Pre-Launch Exps. - Detail'!L120-'6B. Pre-Launch Exps. - Detail'!L128 | L24: =-'6B. Pre-Launch Exps. - Detail'!M120-'6B. Pre-Launch Exps. - Detail'!M128 | M24: =-'6B. Pre-Launch Exps. - Detail'!N120-'6B. Pre-Launch Exps. - Detail'!N128 | N24: =-'6B. Pre-Launch Exps. - Detail'!O120-'6B. Pre-Launch Exps. - Detail'!O128 | O24: =-'6B. Pre-Launch Exps. - Detail'!P120-'6B. Pre-Launch Exps. - Detail'!P128 | P24: =-'6B. Pre-Launch Exps. - Detail'!Q120-'6B. Pre-Launch Exps. - Detail'!Q128 | Q24: =+'4B. Tel. Expense Assumptions'!F394-'4B. Tel. Expense Assumptions'!G394 | R24: =+'4B. Tel. Expense Assumptions'!G394-'4B. Tel. Expense Assumptions'!H394 | S24: =+'4B. Tel. Expense Assumptions'!H394-'4B. Tel. Expense Assumptions'!I394 | T24: =+'4B. Tel. Expense Assumptions'!I394-'4B. Tel. Expense Assumptions'!J394 | U24: =+'4B. Tel. Expense Assumptions'!J394-'4B. Tel. Expense Assumptions'!K394 | V24: =+'4B. Tel. Expense Assumptions'!K394-'4B. Tel. Expense Assumptions'!L394 | W24: =+'4B. Tel. Expense Assumptions'!L394-'4B. Tel. Expense Assumptions'!M394 | X24: =+'4B. Tel. Expense Assumptions'!M394-'4B. Tel. Expense Assumptions'!N394 | ... BX24: =+'4B. Tel. Expense Assumptions'!BM394-'4B. Tel. Expense Assumptions'!BN394 | CA24: Fixed Assets | CD24: =SUM(E24:P24) | CE24: =SUM(Q24:AB24) | CF24: =SUM(AC24:AN24) | CG24: =SUM(AO24:AZ24) | CH24: =SUM(BA24:BL24) | CI24: =SUM(BM24:BX24)
C25: Net Cash Flow from Investments | E25: =SUM(E23:E24) | F25: =SUM(F23:F24) | G25: =SUM(G23:G24) | H25: =SUM(H23:H24) | I25: =SUM(I23:I24) | J25: =SUM(J23:J24) | K25: =SUM(K23:K24) | L25: =SUM(L23:L24) | ... BX25: =SUM(BX23:BX24) | CA25: Net Cash Flow from Investments | CD25: =SUM(E25:P25) | CE25: =SUM(Q25:AB25) | CF25: =SUM(AC25:AN25) | CG25: =SUM(AO25:AZ25) | CH25: =SUM(BA25:BL25) | CI25: =SUM(BM25:BX25)
B27: CASH FLOW FROM FINANCING | BZ27: CASH FLOW FROM FINANCING
C28: Debt | E28: =+'6B. Pre-Launch Exps. - Detail'!L233-'6B. Pre-Launch Exps. - Detail'!E233 | F28: =+'6B. Pre-Launch Exps. - Detail'!M233-'6B. Pre-Launch Exps. - Detail'!L233 | G28: =+'6B. Pre-Launch Exps. - Detail'!N233-'6B. Pre-Launch Exps. - Detail'!M233 | H28: =+'6B. Pre-Launch Exps. - Detail'!O233-'6B. Pre-Launch Exps. - Detail'!N233 | I28: =+'6B. Pre-Launch Exps. - Detail'!P233-'6B. Pre-Launch Exps. - Detail'!O233 | J28: =+'6B. Pre-Launch Exps. - Detail'!Q233-'6B. Pre-Launch Exps. - Detail'!P233 | K28: =+'6B. Pre-Launch Exps. - Detail'!L233-'6B. Pre-Launch Exps. - Detail'!E233 | L28: =+'6B. Pre-Launch Exps. - Detail'!M233-'6B. Pre-Launch Exps. - Detail'!L233 | M28: =+'6B. Pre-Launch Exps. - Detail'!N233-'6B. Pre-Launch Exps. - Detail'!M233 | N28: =+'6B. Pre-Launch Exps. - Detail'!O233-'6B. Pre-Launch Exps. - Detail'!N233 | O28: =+'6B. Pre-Launch Exps. - Detail'!P233-'6B. Pre-Launch Exps. - Detail'!O233 | P28: =+'6B. Pre-Launch Exps. - Detail'!Q233-'6B. Pre-Launch Exps. - Detail'!P233 | Q28: =+'4B. Tel. Expense Assumptions'!G452-'4B. Tel. Expense Assumptions'!F452 | R28: =+'4B. Tel. Expense Assumptions'!H452-'4B. Tel. Expense Assumptions'!G452 | S28: =+'4B. Tel. Expense Assumptions'!I452-'4B. Tel. Expense Assumptions'!H452 | T28: =+'4B. Tel. Expense Assumptions'!J452-'4B. Tel. Expense Assumptions'!I452 | U28: =+'4B. Tel. Expense Assumptions'!K452-'4B. Tel. Expense Assumptions'!J452 | V28: =+'4B. Tel. Expense Assumptions'!L452-'4B. Tel. Expense Assumptions'!K452 | W28: =+'4B. Tel. Expense Assumptions'!M452-'4B. Tel. Expense Assumptions'!L452 | X28: =+'4B. Tel. Expense Assumptions'!N452-'4B. Tel. Expense Assumptions'!M452 | ... BX28: =+'4B. Tel. Expense Assumptions'!BN452-'4B. Tel. Expense Assumptions'!BM452 | CA28: Debt | CD28: =SUM(E28:P28) | CE28: =SUM(P28:AA28) | CF28: =SUM(AC28:AN28) | CG28: =SUM(AN28:AY28) | CH28: =SUM(AZ28:BK28) | CI28: =SUM(BL28:BW28)
C29: Equity Investment | E29: =+'6B. Pre-Launch Exps. - Detail'!L221 | F29: =+'6B. Pre-Launch Exps. - Detail'!M221 | G29: =+'6B. Pre-Launch Exps. - Detail'!N221 | H29: =+'6B. Pre-Launch Exps. - Detail'!O221 | I29: =+'6B. Pre-Launch Exps. - Detail'!P221 | J29: =+'6B. Pre-Launch Exps. - Detail'!Q221 | K29: =+'6B. Pre-Launch Exps. - Detail'!L221 | L29: =+'6B. Pre-Launch Exps. - Detail'!M221 | M29: =+'6B. Pre-Launch Exps. - Detail'!N221 | N29: =+'6B. Pre-Launch Exps. - Detail'!O221 | O29: =+'6B. Pre-Launch Exps. - Detail'!P221 | P29: =+'6B. Pre-Launch Exps. - Detail'!Q221 | Q29: =+'4B. Tel. Expense Assumptions'!G442 | R29: =+'4B. Tel. Expense Assumptions'!H442 | S29: =+'4B. Tel. Expense Assumptions'!I442 | T29: =+'4B. Tel. Expense Assumptions'!J442 | U29: =+'4B. Tel. Expense Assumptions'!K442 | V29: =+'4B. Tel. Expense Assumptions'!L442 | W29: =+'4B. Tel. Expense Assumptions'!M442 | X29: =+'4B. Tel. Expense Assumptions'!N442 | ... BX29: =+'4B. Tel. Expense Assumptions'!BN442 | CA29: Equity Investment | CD29: =SUM(E29:P29) | CE29: =SUM(P29:AA29) | CF29: =SUM(AC29:AN29) | CG29: =SUM(AN29:AY29) | CH29: =SUM(AZ29:BK29) | CI29: =SUM(BL29:BW29)
C30: Trade Finance | E30: 0 | F30: 0 | G30: 0 | H30: 0 | I30: =+'4B. Tel. Expense Assumptions'!E422-'4B. Tel. Expense Assumptions'!D422 | J30: =+'4B. Tel. Expense Assumptions'!F422-'4B. Tel. Expense Assumptions'!E422 | K30: 0 | L30: 0 | M30: 0 | N30: 0 | O30: =+'4B. Tel. Expense Assumptions'!E422-'4B. Tel. Expense Assumptions'!D422 | P30: =+'4B. Tel. Expense Assumptions'!F422-'4B. Tel. Expense Assumptions'!E422 | Q30: =+'4B. Tel. Expense Assumptions'!G422-'4B. Tel. Expense Assumptions'!F422 | R30: =+'4B. Tel. Expense Assumptions'!H422-'4B. Tel. Expense Assumptions'!G422 | S30: =+'4B. Tel. Expense Assumptions'!I422-'4B. Tel. Expense Assumptions'!H422 | T30: =+'4B. Tel. Expense Assumptions'!J422-'4B. Tel. Expense Assumptions'!I422 | U30: =+'4B. Tel. Expense Assumptions'!K422-'4B. Tel. Expense Assumptions'!J422 | V30: =+'4B. Tel. Expense Assumptions'!L422-'4B. Tel. Expense Assumptions'!K422 | ... BX30: =+'4B. Tel. Expense Assumptions'!BN422-'4B. Tel. Expense Assumptions'!BM422 | CA30: Trade Finance | CD30: =SUM(E30:Z30) | CE30: =SUM(P30:AA30) | CF30: =SUM(AC30:AN30) | CG30: =SUM(AN30:AY30) | CH30: =SUM(AZ30:BK30) | CI30: =SUM(BL30:BW30)
C31: Net Cash Flow from Financing | E31: =SUM(E28:E30) | F31: =SUM(F28:F30) | G31: =SUM(G28:G30) | H31: =SUM(H28:H30) | I31: =SUM(I28:I30) | J31: =SUM(J28:J30) | K31: =SUM(K28:K30) | L31: =SUM(L28:L30) | ... BX31: =SUM(BX28:BX30) | CA31: Net Cash Flow from Financing | CD31: =SUM(E31:P31) | CE31: =SUM(P31:AA31) | CF31: =SUM(AC31:AN31) | CG31: =SUM(AN31:AY31) | CH31: =SUM(AZ31:BK31) | CI31: =SUM(BL31:BW31)
CD32: =SUM(E32:Z32) | CE32: =SUM(P32:AA32) | CF32: =SUM(AC32:AN32) | CG32: =SUM(AN32:AY32) | CH32: =SUM(AZ32:BK32) | CI32: =SUM(BL32:BW32)
C33: Net Cash Flow | E33: =+E20+E25+E31 | F33: =+F20+F25+F31 | G33: =+G20+G25+G31 | H33: =+H20+H25+H31 | I33: =+I20+I25+I31 | J33: =+J20+J25+J31 | K33: =+K20+K25+K31 | L33: =+L20+L25+L31 | ... BX33: =+BX20+BX25+BX31 | CA33: Net Cash Flow | CD33: =SUM(E33:P33) | CE33: =SUM(Q33:AB33) | CF33: =SUM(AC33:AN33) | CG33: =SUM(AO33:AZ33) | CH33: =SUM(BA33:BL33) | CI33: =SUM(BM33:BX33)
C34: Cash at Beginning of Period | E34: 0 | F34: =+E35 | G34: =+F35 | H34: =+G35 | I34: =+H35 | J34: =+I35 | K34: 0 | L34: =+K35 | M34: =+L35 | N34: =+M35 | O34: =+N35 | P34: =+O35 | Q34: =+P35 | R34: =+Q35 | S34: =+R35 | ... BX34: =+BW35 | CA34: Cash at Beginning of Period | CD34: =SUM(E34:P34) | CE34: =SUM(Q34:AB34) | CF34: =SUM(AC34:AN34) | CG34: =SUM(AO34:AZ34) | CH34: =SUM(BA34:BL34) | CI34: =SUM(BM34:BX34)
C35: Cash at End of Period | E35: =+E33+E34 | F35: =+F33+F34 | G35: =+G33+G34 | H35: =+H33+H34 | I35: =+I33+I34 | J35: =+J33+J34 | K35: =+K33+K34 | L35: =+L33+L34 | ... BX35: =+BX33+BX34 | CA35: Cash at End of Period | CD35: =SUM(E35:P35) | CE35: =SUM(Q35:AB35) | CF35: =SUM(AC35:AN35) | CG35: =SUM(AO35:AZ35) | CH35: =SUM(BA35:BL35) | CI35: =SUM(BM35:BX35)

Sheet 2B. Cash Collections
L6: Pre-Launch | X6: Post-Launch | AM6: Post-Launch | BB6: Post-Launch | BQ6: Post-Launch | CF6: Post-Launch
I9: Month | J9: Month | K9: Month | L9: Month | M9: Month | N9: Month | O9: Month | P9: Month | Q9: Month | R9: Month | S9: Month | T9: Month | V9: Total | X9: Month | Y9: Month | Z9: Month | AA9: Month | AB9: Month | AC9: Month | AD9: Month | AE9: Month | AF9: Month | AG9: Month | AH9: Month | AI9: Month | AK9: Total | AM9: Month | AN9: Month | AO9: Month | AP9: Month | AQ9: Month | AR9: Month | AS9: Month | AT9: Month | AU9: Month | AV9: Month | AW9: Month | AX9: Month | AZ9: Total | BB9: Month | BC9: Month | BD9: Month | BE9: Month | BF9: Month | BG9: Month | BH9: Month | BI9: Month | BJ9: Month | BK9: Month | BL9: Month | BM9: Month | BO9: Total | BQ9: Month | BR9: Month | BS9: Month | BT9: Month | BU9: Month | BV9: Month | BW9: Month | BX9: Month | BY9: Month | BZ9: Month | CA9: Month | CB9: Month | CD9: Total | CF9: Month | CG9: Month | CH9: Month | CI9: Month | CJ9: Month | CK9: Month | CL9: Month | CM9: Month | CN9: Month | CO9: Month | CP9: Month | CQ9: Month | CS9: Total
I10: -12 | J10: -11 | K10: -10 | L10: -9 | M10: =((L10)+(1)) | N10: =((M10)+(1)) | O10: =((N10)+(1)) | P10: =((O10)+(1)) | Q10: =((P10)+(1)) | R10: =((Q10)+(1)) | S10: =((R10)+(1)) | T10: =((S10)+(1)) | V10: Months -12 to -1 | X10: 1 | Y10: =((X10)+(1)) | Z10: =((Y10)+(1)) | AA10: =((Z10)+(1)) | AB10: =((AA10)+(1)) | AC10: =((AB10)+(1)) | AD10: =((AC10)+(1)) | AE10: =((AD10)+(1)) | AF10: =((AE10)+(1)) | ... AI10: =((AH10)+(1)) | AK10: Months 1 - 12 | AM10: 13 | AN10: =((AM10)+(1)) | AO10: =((AN10)+(1)) | AP10: =((AO10)+(1)) | AQ10: =((AP10)+(1)) | AR10: =((AQ10)+(1)) | AS10: =((AR10)+(1)) | AT10: =((AS10)+(1)) | AU10: =((AT10)+(1)) | ... AX10: =((AW10)+(1)) | AZ10: Months 13 - 24 | BB10: 25 | BC10: =((BB10)+(1)) | BD10: =((BC10)+(1)) | BE10: =((BD10)+(1)) | BF10: =((BE10)+(1)) | BG10: =((BF10)+(1)) | BH10: =((BG10)+(1)) | BI10: =((BH10)+(1)) | BJ10: =((BI10)+(1)) | ... BM10: =((BL10)+(1)) | BO10: Months 25 - 36 | BQ10: 37 | BR10: =((BQ10)+(1)) | BS10: =((BR10)+(1)) | BT10: =((BS10)+(1)) | BU10: =((BT10)+(1)) | BV10: =((BU10)+(1)) | BW10: =((BV10)+(1)) | BX10: =((BW10)+(1)) | BY10: =((BX10)+(1)) | ... CB10: =((CA10)+(1)) | CD10: Months 37 - 48 | CF10: 49 | CG10: =((CF10)+(1)) | CH10: =((CG10)+(1)) | CI10: =((CH10)+(1)) | CJ10: =((CI10)+(1)) | CK10: =((CJ10)+(1)) | CL10: =((CK10)+(1)) | CM10: =((CL10)+(1)) | CN10: =((CM10)+(1)) | ... CQ10: =((CP10)+(1)) | CS10: Months 49 - 60
B14: Telephone Sales and Activation
B18: ● | C18: Revenue Recognition | G18: Revenue recognized in month of sale | I18: 0 | J18: 0 | K18: 0 | L18: 0 | M18: 0 | N18: 0 | O18: 0 | P18: 0 | Q18: 0 | R18: 0 | S18: 1000000 | T18: 1000000 | V18: =SUM(L18:T18) | X18: ='3B. Tel. - Rev. Detail x Month'!$J55 | Y18: ='3B. Tel. - Rev. Detail x Month'!$K55 | Z18: ='3B. Tel. - Rev. Detail x Month'!$L55 | AA18: ='3B. Tel. - Rev. Detail x Month'!$M55 | AB18: ='3B. Tel. - Rev. Detail x Month'!$N55 | AC18: ='3B. Tel. - Rev. Detail x Month'!$O55 | AD18: ='3B. Tel. - Rev. Detail x Month'!$P55 | AE18: ='3B. Tel. - Rev. Detail x Month'!$Q55 | AF18: ='3B. Tel. - Rev. Detail x Month'!$R55 | AG18: ='3B. Tel. - Rev. Detail x Month'!$S55 | AH18: ='3B. Tel. - Rev. Detail x Month'!$T55 | AI18: ='3B. Tel. - Rev. Detail x Month'!$U55 | AK18: =SUM(X18:AI18) | AM18: =('3B. Tel. - Rev. Detail x Month'!$J93) | AN18: =('3B. Tel. - Rev. Detail x Month'!$K93) | AO18: =('3B. Tel. - Rev. Detail x Month'!$L93) | AP18: =('3B. Tel. - Rev. Detail x Month'!$M93) | AQ18: =('3B. Tel. - Rev. Detail x Month'!$N93) | AR18: =('3B. Tel. - Rev. Detail x Month'!$O93) | AS18: =('3B. Tel. - Rev. Detail x Month'!$P93) | AT18: =('3B. Tel. - Rev. Detail x Month'!$Q93) | AU18: =('3B. Tel. - Rev. Detail x Month'!$R93) | AV18: =('3B. Tel. - Rev. Detail x Month'!$S93) | AW18: =('3B. Tel. - Rev. Detail x Month'!$T93) | AX18: =('3B. Tel. - Rev. Detail x Month'!$U93) | AZ18: =SUM(AM18:AX18) | BB18: =('3B. Tel. - Rev. Detail x Month'!$J131) | BC18: =('3B. Tel. - Rev. Detail x Month'!$K131) | BD18: =('3B. Tel. - Rev. Detail x Month'!$L131) | BE18: =('3B. Tel. - Rev. Detail x Month'!$M131) | BF18: =('3B. Tel. - Rev. Detail x Month'!$N131) | BG18: =('3B. Tel. - Rev. Detail x Month'!$O131) | BH18: =('3B. Tel. - Rev. Detail x Month'!$P131) | BI18: =('3B. Tel. - Rev. Detail x Month'!$Q131) | BJ18: =('3B. Tel. - Rev. Detail x Month'!$R131) | BK18: =('3B. Tel. - Rev. Detail x Month'!$S131) | BL18: =('3B. Tel. - Rev. Detail x Month'!$T131) | BM18: =('3B. Tel. - Rev. Detail x Month'!$U131) | BO18: =SUM(BB18:BM18) | BQ18: =('3B. Tel. - Rev. Detail x Month'!$J169) | BR18: =('3B. Tel. - Rev. Detail x Month'!$K169) | BS18: =('3B. Tel. - Rev. Detail x Month'!$L169) | BT18: =('3B. Tel. - Rev. Detail x Month'!$M169) | BU18: =('3B. Tel. - Rev. Detail x Month'!$N169) | BV18: =('3B. Tel. - Rev. Detail x Month'!$O169) | BW18: =('3B. Tel. - Rev. Detail x Month'!$P169) | BX18: =('3B. Tel. - Rev. Detail x Month'!$Q169) | BY18: =('3B. Tel. - Rev. Detail x Month'!$R169) | BZ18: =('3B. Tel. - Rev. Detail x Month'!$S169) | CA18: =('3B. Tel. - Rev. Detail x Month'!$T169) | CB18: =('3B. Tel. - Rev. Detail x Month'!$U169) | CD18: =SUM(BQ18:CB18) | CF18: =('3B. Tel. - Rev. Detail x Month'!$J207) | CG18: =('3B. Tel. - Rev. Detail x Month'!$K207) | CH18: =('3B. Tel. - Rev. Detail x Month'!$L207) | CI18: =('3B. Tel. - Rev. Detail x Month'!$M207) | CJ18: =('3B. Tel. - Rev. Detail x Month'!$N207) | CK18: =('3B. Tel. - Rev. Detail x Month'!$O207) | CL18: =('3B. Tel. - Rev. Detail x Month'!$P207) | CM18: =('3B. Tel. - Rev. Detail x Month'!$Q207) | CN18: =('3B. Tel. - Rev. Detail x Month'!$R207) | CO18: =('3B. Tel. - Rev. Detail x Month'!$S207) | CP18: =('3B. Tel. - Rev. Detail x Month'!$T207) | CQ18: =('3B. Tel. - Rev. Detail x Month'!$U207) | CS18: =SUM(CF18:CQ18)
B20: ● | C20: Cash Collection | G20: Cash received in same month as subscription | I20: 0 | J20: 0 | K20: 0 | L20: 0 | M20: 0 | N20: 0 | O20: 0 | P20: 0 | Q20: 0 | S20: 1000000 | T20: 1000000 | V20: =SUM(L20:T20) | X20: =((X18)+('2D. Crowd Funding'!G45)) | Y20: =(Y18) | Z20: =(Z18) | AA20: =(AA18) | AB20: =(AB18) | AC20: =(AC18) | AD20: =(AD18) | AE20: =(AE18) | AF20: =(AF18) | ... AI20: =(AI18) | AK20: =SUM(X20:AI20) | AM20: =(AM18) | AN20: =(AN18) | AO20: =(AO18) | AP20: =(AP18) | AQ20: =(AQ18) | AR20: =(AR18) | AS20: =(AS18) | AT20: =(AT18) | ... AX20: =(AX18) | AZ20: =SUM(AM20:AX20) | BB20: =(BB18) | BC20: =(BC18) | BD20: =(BD18) | BE20: =(BE18) | BF20: =(BF18) | BG20: =(BG18) | BH20: =(BH18) | BI20: =(BI18) | ... BM20: =(BM18) | BO20: =SUM(BB20:BM20) | BQ20: =(BQ18) | BR20: =(BR18) | BS20: =(BS18) | BT20: =(BT18) | BU20: =(BU18) | BV20: =(BV18) | BW20: =(BW18) | BX20: =(BX18) | ... CB20: =(CB18) | CD20: =SUM(BQ20:CB20) | CF20: =(CF18) | CG20: =(CG18) | CH20: =(CH18) | CI20: =(CI18) | CJ20: =(CJ18) | CK20: =(CK18) | CL20: =(CL18) | CM20: =(CM18) | ... CQ20: =(CQ18) | CS20: =SUM(CF20:CQ20)
B25: Market Research Services
B29: ● | C29: Revenue Recognition | G29: Revenue recognized in month of sale | I29: 0 | J29: 0 | K29: 0 | L29: 0 | M29: 0 | N29: 0 | O29: 0 | P29: 0 | Q29: 0 | R29: 0 | S29: 0 | T29: 0 | V29: =SUM(L29:T29) | X29: ='3B. Tel. - Rev. Detail x Month'!$J296 | Y29: ='3B. Tel. - Rev. Detail x Month'!$K296 | Z29: ='3B. Tel. - Rev. Detail x Month'!$L296 | AA29: ='3B. Tel. - Rev. Detail x Month'!$M296 | AB29: ='3B. Tel. - Rev. Detail x Month'!$N296 | AC29: ='3B. Tel. - Rev. Detail x Month'!$O296 | AD29: ='3B. Tel. - Rev. Detail x Month'!$P296 | AE29: ='3B. Tel. - Rev. Detail x Month'!$Q296 | AF29: ='3B. Tel. - Rev. Detail x Month'!$R296 | AG29: ='3B. Tel. - Rev. Detail x Month'!$S296 | AH29: ='3B. Tel. - Rev. Detail x Month'!$T296 | AI29: ='3B. Tel. - Rev. Detail x Month'!$U296 | AK29: =SUM(X29:AI29) | AM29: ='3B. Tel. - Rev. Detail x Month'!$J328 | AN29: ='3B. Tel. - Rev. Detail x Month'!$K328 | AO29: ='3B. Tel. - Rev. Detail x Month'!$L328 | AP29: ='3B. Tel. - Rev. Detail x Month'!$M328 | AQ29: ='3B. Tel. - Rev. Detail x Month'!$N328 | AR29: ='3B. Tel. - Rev. Detail x Month'!$O328 | AS29: ='3B. Tel. - Rev. Detail x Month'!$P328 | AT29: ='3B. Tel. - Rev. Detail x Month'!$Q328 | AU29: ='3B. Tel. - Rev. Detail x Month'!$R328 | AV29: ='3B. Tel. - Rev. Detail x Month'!$S328 | AW29: ='3B. Tel. - Rev. Detail x Month'!$T328 | AX29: ='3B. Tel. - Rev. Detail x Month'!$U328 | AZ29: =SUM(AM29:AX29) | BB29: ='3B. Tel. - Rev. Detail x Month'!$J360 | BC29: ='3B. Tel. - Rev. Detail x Month'!$K360 | BD29: ='3B. Tel. - Rev. Detail x Month'!$L360 | BE29: ='3B. Tel. - Rev. Detail x Month'!$M360 | BF29: ='3B. Tel. - Rev. Detail x Month'!$N360 | BG29: ='3B. Tel. - Rev. Detail x Month'!$O360 | BH29: ='3B. Tel. - Rev. Detail x Month'!$P360 | BI29: ='3B. Tel. - Rev. Detail x Month'!$Q360 | BJ29: ='3B. Tel. - Rev. Detail x Month'!$R360 | BK29: ='3B. Tel. - Rev. Detail x Month'!$S360 | BL29: ='3B. Tel. - Rev. Detail x Month'!$T360 | BM29: ='3B. Tel. - Rev. Detail x Month'!$U360 | BO29: =SUM(BB29:BM29) | BQ29: ='3B. Tel. - Rev. Detail x Month'!$J392 | BR29: ='3B. Tel. - Rev. Detail x Month'!$K392 | BS29: ='3B. Tel. - Rev. Detail x Month'!$L392 | BT29: ='3B. Tel. - Rev. Detail x Month'!$M392 | BU29: ='3B. Tel. - Rev. Detail x Month'!$N392 | BV29: ='3B. Tel. - Rev. Detail x Month'!$O392 | BW29: ='3B. Tel. - Rev. Detail x Month'!$P392 | BX29: ='3B. Tel. - Rev. Detail x Month'!$Q392 | BY29: ='3B. Tel. - Rev. Detail x Month'!$R392 | BZ29: ='3B. Tel. - Rev. Detail x Month'!$S392 | CA29: ='3B. Tel. - Rev. Detail x Month'!$T392 | CB29: ='3B. Tel. - Rev. Detail x Month'!$U392 | CD29: =SUM(BQ29:CB29) | CF29: ='3B. Tel. - Rev. Detail x Month'!$J424 | CG29: ='3B. Tel. - Rev. Detail x Month'!$K424 | CH29: ='3B. Tel. - Rev. Detail x Month'!$L424 | CI29: ='3B. Tel. - Rev. Detail x Month'!$M424 | CJ29: ='3B. Tel. - Rev. Detail x Month'!$N424 | CK29: ='3B. Tel. - Rev. Detail x Month'!$O424 | CL29: ='3B. Tel. - Rev. Detail x Month'!$P424 | CM29: ='3B. Tel. - Rev. Detail x Month'!$Q424 | CN29: ='3B. Tel. - Rev. Detail x Month'!$R424 | CO29: ='3B. Tel. - Rev. Detail x Month'!$S424 | CP29: ='3B. Tel. - Rev. Detail x Month'!$T424 | CQ29: ='3B. Tel. - Rev. Detail x Month'!$U424 | CS29: =SUM(CF29:CQ29)
B31: ● | C31: Cash Collection | G31: Client payment terms 30 days | I31: 0 | J31: 0 | K31: 0 | L31: 0 | M31: 0 | N31: 0 | O31: 0 | P31: 0 | Q31: 0 | R31: 0 | S31: 0 | T31: 0 | V31: =SUM(L31:T31) | X31: 0 | Y31: 0 | Z31: =(Z29) | AA31: =(AA29) | AB31: =(AB29) | AC31: =(AC29) | AD31: =(AD29) | AE31: =(AE29) | AF31: =(AF29) | AG31: =(AG29) | ... AI31: =(AI29) | AK31: =SUM(X31:AI31) | AM31: =(AM29) | AN31: =(AN29) | AO31: =(AO29) | AP31: =(AP29) | AQ31: =(AQ29) | AR31: =(AR29) | AS31: =(AS29) | AT31: =(AT29) | ... AX31: =(AX29) | AZ31: =SUM(AM31:AX31) | BB31: =(BB29) | BC31: =(BC29) | BD31: =(BD29) | BE31: =(BE29) | BF31: =(BF29) | BG31: =(BG29) | BH31: =(BH29) | BI31: =(BI29) | ... BM31: =(BM29) | BO31: =SUM(BB31:BM31) | BQ31: =(BQ29) | BR31: =(BR29) | BS31: =(BS29) | BT31: =(BT29) | BU31: =(BU29) | BV31: =(BV29) | BW31: =(BW29) | BX31: =(BX29) | ... CB31: =(CB29) | CD31: =SUM(BQ31:CB31) | CF31: =(CF29) | CG31: =(CG29) | CH31: =(CH29) | CI31: =(CI29) | CJ31: =(CJ29) | CK31: =(CK29) | CL31: =(CL29) | CM31: =(CM29) | ... CQ31: =(CQ29) | CS31: =SUM(CF31:CQ31)

Sheet 2C. Inventory Cash Disburse.
J1: ***PLEASE NOTE THAT IT IS ESTIMATED BASED ON OUR GO TO MARKET STRATEGY THAT UP TO 50% OF ALL PHONES WILL BE PAID FOR 100% BEFORE WE SUPPLY THE 30% DEPOSIT TO OUR VENDOR PARTNERS. FOR EXAMPLE: 1a. Brand Option 1: Brand pays for market research, PT conducts market research, PT pays consumer with a free phone, PT gives brand unique access to consumer. 1b. Brand Option 2: Brand pays for branded phones to give to super fans. 2. Influencer Option: PT & Influencers run social media giveaways, 100 people pay $10,000 to each gain 100k followers, influencers instruct their followers to follow these 100 people, the 100k people following the 100 people are entered to win prizes (phones/experiences), influencer earns $250k, PT earns $100k, and gives away $650k worth of phones, etc. 3. Pre-Pay Option: PT drives traffic to our own landing pages where people can opt into our program and pay via something like Affirm, AfterPay, Klarna, or our own version to finance an $800+ phone, consumer puts down deposit to finance our phone, consumer pays monthly offset cost of phone, PT earns consumers enough money to offset and make the phone free. In all the previous scenarios someone else pays for the phone ahead of time and then we order and deploy the phones, this is not to say we wont keep some phones in inventory, and as we grow of course this is how things will progess. That said, we estimate that at least for the first 1-2 years we can run this model with 100% of the offset costs for at least 50% of all phone inventory. Thus, the model below is very conservative as we didn't take any of this into account!
B3: I. | D3: Cash Disbursements Calendar for Telephone Inventory
M7: Pre-Launch | Y7: Year 1 | AN7: Year 2 | BC7: Year 3 | BR7: Year 4 | CG7: Year 5 | CV7: Year 6
F10: Month of Costomer Sale | J10: -12 | K10: -11 | L10: -10 | M10: -9 | N10: =((M10)+(1)) | O10: =((N10)+(1)) | P10: =((O10)+(1)) | Q10: =((P10)+(1)) | R10: =((Q10)+(1)) | S10: =((R10)+(1)) | T10: =((S10)+(1)) | U10: =((T10)+(1)) | W10: ∑, -12 to -1 | Y10: 1 | Z10: =((Y10)+(1)) | AA10: =((Z10)+(1)) | AB10: =((AA10)+(1)) | AC10: =((AB10)+(1)) | AD10: =((AC10)+(1)) | AE10: =((AD10)+(1)) | AF10: =((AE10)+(1)) | AG10: =((AF10)+(1)) | ... AJ10: =((AI10)+(1)) | AL10: ∑, 1 - 12 | AN10: =((AJ10)+(1)) | AO10: =((AN10)+(1)) | AP10: =((AO10)+(1)) | AQ10: =((AP10)+(1)) | AR10: =((AQ10)+(1)) | AS10: =((AR10)+(1)) | AT10: =((AS10)+(1)) | AU10: =((AT10)+(1)) | AV10: =((AU10)+(1)) | ... AY10: =((AX10)+(1)) | BA10: ∑, 13 - 24 | BC10: =((AY10)+(1)) | BD10: =((BC10)+(1)) | BE10: =((BD10)+(1)) | BF10: =((BE10)+(1)) | BG10: =((BF10)+(1)) | BH10: =((BG10)+(1)) | BI10: =((BH10)+(1)) | BJ10: =((BI10)+(1)) | BK10: =((BJ10)+(1)) | ... BN10: =((BM10)+(1)) | BP10: ∑, 25 - 36 | BR10: =((BN10)+(1)) | BS10: =((BR10)+(1)) | BT10: =((BS10)+(1)) | BU10: =((BT10)+(1)) | BV10: =((BU10)+(1)) | BW10: =((BV10)+(1)) | BX10: =((BW10)+(1)) | BY10: =((BX10)+(1)) | BZ10: =((BY10)+(1)) | ... CC10: =((CB10)+(1)) | CE10: ∑, 37 - 48 | CG10: =((CC10)+(1)) | CH10: =((CG10)+(1)) | CI10: =((CH10)+(1)) | CJ10: =((CI10)+(1)) | CK10: =((CJ10)+(1)) | CL10: =((CK10)+(1)) | CM10: =((CL10)+(1)) | CN10: =((CM10)+(1)) | CO10: =((CN10)+(1)) | ... CR10: =((CQ10)+(1)) | CT10: ∑, 49 - 60 | CV10: =((CR10)+(1)) | CW10: =((CV10)+(1)) | CX10: =((CW10)+(1)) | CY10: =((CX10)+(1)) | CZ10: =((CY10)+(1)) | DA10: =((CZ10)+(1)) | DB10: =((DA10)+(1)) | DC10: =((DB10)+(1)) | DD10: =((DC10)+(1)) | ... DG10: =((DF10)+(1)) | DI10: ∑, 61 - 72
F14: Month of Vendor PO and Deposit | Y14: -1 | Z14: =((Y14)+(2)) | AA14: =((Z14)+(1)) | AB14: =((AA14)+(1)) | AC14: =((AB14)+(1)) | AD14: =((AC14)+(1)) | AE14: =((AD14)+(1)) | AF14: =((AE14)+(1)) | AG14: =((AF14)+(1)) | AH14: =((AG14)+(1)) | ... AJ14: =((AI14)+(1)) | AN14: =((AJ14)+(1)) | AO14: =((AN14)+(1)) | AP14: =((AO14)+(1)) | AQ14: =((AP14)+(1)) | AR14: =((AQ14)+(1)) | AS14: =((AR14)+(1)) | AT14: =((AS14)+(1)) | AU14: =((AT14)+(1)) | AV14: =((AU14)+(1)) | ... AY14: =((AX14)+(1)) | BC14: =((AY14)+(1)) | BD14: =((BC14)+(1)) | BE14: =((BD14)+(1)) | BF14: =((BE14)+(1)) | BG14: =((BF14)+(1)) | BH14: =((BG14)+(1)) | BI14: =((BH14)+(1)) | BJ14: =((BI14)+(1)) | BK14: =((BJ14)+(1)) | ... BN14: =((BM14)+(1)) | BR14: =((BN14)+(1)) | BS14: =((BR14)+(1)) | BT14: =((BS14)+(1)) | BU14: =((BT14)+(1)) | BV14: =((BU14)+(1)) | BW14: =((BV14)+(1)) | BX14: =((BW14)+(1)) | BY14: =((BX14)+(1)) | BZ14: =((BY14)+(1)) | ... CC14: =((CB14)+(1)) | CG14: =((CC14)+(1)) | CH14: =((CG14)+(1)) | CI14: =((CH14)+(1)) | CJ14: =((CI14)+(1)) | CK14: =((CJ14)+(1)) | CL14: =((CK14)+(1)) | CM14: =((CL14)+(1)) | CN14: =((CM14)+(1)) | CO14: =((CN14)+(1)) | ... CR14: =((CQ14)+(1)) | CV14: =((CR14)+(1)) | CW14: =((CV14)+(1)) | CX14: =((CW14)+(1)) | CY14: =((CX14)+(1)) | CZ14: =((CY14)+(1)) | DA14: =((CZ14)+(1)) | DB14: =((DA14)+(1)) | DC14: =((DB14)+(1)) | DD14: =((DC14)+(1)) | ... DG14: =((DF14)+(1))
F16: Month of Shipment and Vendor Balance | Y16: 1 | Z16: 2 | AA16: =((Z16)+(1)) | AB16: =((AA16)+(1)) | AC16: =((AB16)+(1)) | AD16: =((AC16)+(1)) | AE16: =((AD16)+(1)) | AF16: =((AE16)+(1)) | AG16: =((AF16)+(1)) | AH16: =((AG16)+(1)) | ... AJ16: =((AI16)+(1)) | AN16: =((AJ16)+(1)) | AO16: =((AN16)+(1)) | AP16: =((AO16)+(1)) | AQ16: =((AP16)+(1)) | AR16: =((AQ16)+(1)) | AS16: =((AR16)+(1)) | AT16: =((AS16)+(1)) | AU16: =((AT16)+(1)) | AV16: =((AU16)+(1)) | ... AY16: =((AX16)+(1)) | BC16: =((AY16)+(1)) | BD16: =((BC16)+(1)) | BE16: =((BD16)+(1)) | BF16: =((BE16)+(1)) | BG16: =((BF16)+(1)) | BH16: =((BG16)+(1)) | BI16: =((BH16)+(1)) | BJ16: =((BI16)+(1)) | BK16: =((BJ16)+(1)) | ... BN16: =((BM16)+(1)) | BR16: =((BN16)+(1)) | BS16: =((BR16)+(1)) | BT16: =((BS16)+(1)) | BU16: =((BT16)+(1)) | BV16: =((BU16)+(1)) | BW16: =((BV16)+(1)) | BX16: =((BW16)+(1)) | BY16: =((BX16)+(1)) | BZ16: =((BY16)+(1)) | ... CC16: =((CB16)+(1)) | CG16: =((CC16)+(1)) | CH16: =((CG16)+(1)) | CI16: =((CH16)+(1)) | CJ16: =((CI16)+(1)) | CK16: =((CJ16)+(1)) | CL16: =((CK16)+(1)) | CM16: =((CL16)+(1)) | CN16: =((CM16)+(1)) | CO16: =((CN16)+(1)) | ... CR16: =((CQ16)+(1)) | CV16: =((CR16)+(1)) | CW16: =((CV16)+(1)) | CX16: =((CW16)+(1)) | CY16: =((CX16)+(1)) | CZ16: =((CY16)+(1)) | DA16: =((CZ16)+(1)) | DB16: =((DA16)+(1)) | DC16: =((DB16)+(1)) | DD16: =((DC16)+(1)) | ... DG16: =((DF16)+(1))
B21: II. | D21: Cash Disbursements for Telephone Inventory
M25: Pre-Launch | Y25: Year 1 | AN25: Year 2 | BC25: Year 3 | BR25: Year 4 | CG25: Year 5 | CV25: Year 6
D29: Month of Sale to Customers | J29: -12 | K29: -11 | L29: -10 | M29: -9 | N29: =((M29)+(1)) | O29: =((N29)+(1)) | P29: =((O29)+(1)) | Q29: =((P29)+(1)) | R29: =((Q29)+(1)) | S29: =((R29)+(1)) | T29: =((S29)+(1)) | U29: =((T29)+(1)) | W29: ∑, -12 to -1 | Y29: 1 | Z29: =((Y29)+(1)) | AA29: =((Z29)+(1)) | AB29: =((AA29)+(1)) | AC29: =((AB29)+(1)) | AD29: =((AC29)+(1)) | AE29: =((AD29)+(1)) | AF29: =((AE29)+(1)) | AG29: =((AF29)+(1)) | ... AJ29: =((AI29)+(1)) | AL29: ∑, 1 - 12 | AN29: =((AJ29)+(1)) | AO29: =((AN29)+(1)) | AP29: =((AO29)+(1)) | AQ29: =((AP29)+(1)) | AR29: =((AQ29)+(1)) | AS29: =((AR29)+(1)) | AT29: =((AS29)+(1)) | AU29: =((AT29)+(1)) | AV29: =((AU29)+(1)) | ... AY29: =((AX29)+(1)) | BA29: ∑, 13 - 24 | BC29: =((AY29)+(1)) | BD29: =((BC29)+(1)) | BE29: =((BD29)+(1)) | BF29: =((BE29)+(1)) | BG29: =((BF29)+(1)) | BH29: =((BG29)+(1)) | BI29: =((BH29)+(1)) | BJ29: =((BI29)+(1)) | BK29: =((BJ29)+(1)) | ... BN29: =((BM29)+(1)) | BP29: ∑, 25 - 36 | BR29: =((BN29)+(1)) | BS29: =((BR29)+(1)) | BT29: =((BS29)+(1)) | BU29: =((BT29)+(1)) | BV29: =((BU29)+(1)) | BW29: =((BV29)+(1)) | BX29: =((BW29)+(1)) | BY29: =((BX29)+(1)) | BZ29: =((BY29)+(1)) | ... CC29: =((CB29)+(1)) | CE29: ∑, 37 - 48 | CG29: =((CC29)+(1)) | CH29: =((CG29)+(1)) | CI29: =((CH29)+(1)) | CJ29: =((CI29)+(1)) | CK29: =((CJ29)+(1)) | CL29: =((CK29)+(1)) | CM29: =((CL29)+(1)) | CN29: =((CM29)+(1)) | CO29: =((CN29)+(1)) | ... CR29: =((CQ29)+(1)) | CT29: ∑, 49 - 60 | CV29: =((CR29)+(1)) | CW29: =((CV29)+(1)) | CX29: =((CW29)+(1)) | CY29: =((CX29)+(1)) | CZ29: =((CY29)+(1)) | DA29: =((CZ29)+(1)) | DB29: =((DA29)+(1)) | DC29: =((DB29)+(1)) | DD29: =((DC29)+(1)) | ... DG29: =((DF29)+(1)) | DI29: ∑, 61 - 72
D31: Units Sold, by Month | J31: Pre-Launch | Y31: =(('3B. Tel. - Rev. Detail x Month'!J51)+('3B. Tel. - Rev. Detail x Month'!J67)) | Z31: =(('3B. Tel. - Rev. Detail x Month'!K51)+('3B. Tel. - Rev. Detail x Month'!K67)) | AA31: =(('3B. Tel. - Rev. Detail x Month'!L51)+('3B. Tel. - Rev. Detail x Month'!L67)) | AB31: =(('3B. Tel. - Rev. Detail x Month'!M51)+('3B. Tel. - Rev. Detail x Month'!M67)) | AC31: =(('3B. Tel. - Rev. Detail x Month'!N51)+('3B. Tel. - Rev. Detail x Month'!N67)) | AD31: =(('3B. Tel. - Rev. Detail x Month'!O51)+('3B. Tel. - Rev. Detail x Month'!O67)) | AE31: =(('3B. Tel. - Rev. Detail x Month'!P51)+('3B. Tel. - Rev. Detail x Month'!P67)) | AF31: =(('3B. Tel. - Rev. Detail x Month'!Q51)+('3B. Tel. - Rev. Detail x Month'!Q67)) | ... AI31: =(('3B. Tel. - Rev. Detail x Month'!T51)+('3B. Tel. - Rev. Detail x Month'!T67)) | AJ31: =(('3B. Tel. - Rev. Detail x Month'!Q51)+('3B. Tel. - Rev. Detail x Month'!Q67)) | AL31: =SUM(T31:AJ31) | AN31: =(('3B. Tel. - Rev. Detail x Month'!J89)+('3B. Tel. - Rev. Detail x Month'!J105)) | AO31: =(('3B. Tel. - Rev. Detail x Month'!K89)+('3B. Tel. - Rev. Detail x Month'!K105)) | AP31: =(('3B. Tel. - Rev. Detail x Month'!L89)+('3B. Tel. - Rev. Detail x Month'!L105)) | AQ31: =(('3B. Tel. - Rev. Detail x Month'!M89)+('3B. Tel. - Rev. Detail x Month'!M105)) | AR31: =(('3B. Tel. - Rev. Detail x Month'!N89)+('3B. Tel. - Rev. Detail x Month'!N105)) | AS31: =(('3B. Tel. - Rev. Detail x Month'!O89)+('3B. Tel. - Rev. Detail x Month'!O105)) | AT31: =(('3B. Tel. - Rev. Detail x Month'!P89)+('3B. Tel. - Rev. Detail x Month'!P105)) | AU31: =(('3B. Tel. - Rev. Detail x Month'!Q89)+('3B. Tel. - Rev. Detail x Month'!Q105)) | ... AY31: =(('3B. Tel. - Rev. Detail x Month'!U89)+('3B. Tel. - Rev. Detail x Month'!U105)) | BA31: =SUM(AN31:AY31) | BC31: =(('3B. Tel. - Rev. Detail x Month'!J127)+('3B. Tel. - Rev. Detail x Month'!J143)) | BD31: =(('3B. Tel. - Rev. Detail x Month'!K127)+('3B. Tel. - Rev. Detail x Month'!K143)) | BE31: =(('3B. Tel. - Rev. Detail x Month'!L127)+('3B. Tel. - Rev. Detail x Month'!L143)) | BF31: =(('3B. Tel. - Rev. Detail x Month'!M127)+('3B. Tel. - Rev. Detail x Month'!M143)) | BG31: =(('3B. Tel. - Rev. Detail x Month'!N127)+('3B. Tel. - Rev. Detail x Month'!N143)) | BH31: =(('3B. Tel. - Rev. Detail x Month'!O127)+('3B. Tel. - Rev. Detail x Month'!O143)) | BI31: =(('3B. Tel. - Rev. Detail x Month'!P127)+('3B. Tel. - Rev. Detail x Month'!P143)) | BJ31: =(('3B. Tel. - Rev. Detail x Month'!Q127)+('3B. Tel. - Rev. Detail x Month'!Q143)) | ... BN31: =(('3B. Tel. - Rev. Detail x Month'!U127)+('3B. Tel. - Rev. Detail x Month'!U143)) | BP31: =SUM(BC31:BN31) | BR31: =(('3B. Tel. - Rev. Detail x Month'!J165)+('3B. Tel. - Rev. Detail x Month'!J181)) | BS31: =(('3B. Tel. - Rev. Detail x Month'!K165)+('3B. Tel. - Rev. Detail x Month'!K181)) | BT31: =(('3B. Tel. - Rev. Detail x Month'!L165)+('3B. Tel. - Rev. Detail x Month'!L181)) | BU31: =(('3B. Tel. - Rev. Detail x Month'!M165)+('3B. Tel. - Rev. Detail x Month'!M181)) | BV31: =(('3B. Tel. - Rev. Detail x Month'!N165)+('3B. Tel. - Rev. Detail x Month'!N181)) | BW31: =(('3B. Tel. - Rev. Detail x Month'!O165)+('3B. Tel. - Rev. Detail x Month'!O181)) | BX31: =(('3B. Tel. - Rev. Detail x Month'!P165)+('3B. Tel. - Rev. Detail x Month'!P181)) | BY31: =(('3B. Tel. - Rev. Detail x Month'!Q165)+('3B. Tel. - Rev. Detail x Month'!Q181)) | ... CC31: =(('3B. Tel. - Rev. Detail x Month'!U165)+('3B. Tel. - Rev. Detail x Month'!U181)) | CE31: =SUM(BR31:CC31) | CG31: =(('3B. Tel. - Rev. Detail x Month'!J203)+('3B. Tel. - Rev. Detail x Month'!J219)) | CH31: =(('3B. Tel. - Rev. Detail x Month'!K203)+('3B. Tel. - Rev. Detail x Month'!K219)) | CI31: =(('3B. Tel. - Rev. Detail x Month'!L203)+('3B. Tel. - Rev. Detail x Month'!L219)) | CJ31: =(('3B. Tel. - Rev. Detail x Month'!M203)+('3B. Tel. - Rev. Detail x Month'!M219)) | CK31: =(('3B. Tel. - Rev. Detail x Month'!N203)+('3B. Tel. - Rev. Detail x Month'!N219)) | CL31: =(('3B. Tel. - Rev. Detail x Month'!O203)+('3B. Tel. - Rev. Detail x Month'!O219)) | CM31: =(('3B. Tel. - Rev. Detail x Month'!P203)+('3B. Tel. - Rev. Detail x Month'!P219)) | CN31: =(('3B. Tel. - Rev. Detail x Month'!Q203)+('3B. Tel. - Rev. Detail x Month'!Q219)) | ... CR31: =(('3B. Tel. - Rev. Detail x Month'!U203)+('3B. Tel. - Rev. Detail x Month'!U219)) | CT31: =SUM(CG31:CR31) | CV31: =(('3B. Tel. - Rev. Detail x Month'!J241)+('3B. Tel. - Rev. Detail x Month'!J257)) | CW31: =(('3B. Tel. - Rev. Detail x Month'!K241)+('3B. Tel. - Rev. Detail x Month'!K257)) | CX31: =(('3B. Tel. - Rev. Detail x Month'!L241)+('3B. Tel. - Rev. Detail x Month'!L257)) | CY31: =(('3B. Tel. - Rev. Detail x Month'!M241)+('3B. Tel. - Rev. Detail x Month'!M257)) | CZ31: =(('3B. Tel. - Rev. Detail x Month'!N241)+('3B. Tel. - Rev. Detail x Month'!N257)) | DA31: =(('3B. Tel. - Rev. Detail x Month'!O241)+('3B. Tel. - Rev. Detail x Month'!O257)) | DB31: =(('3B. Tel. - Rev. Detail x Month'!P241)+('3B. Tel. - Rev. Detail x Month'!P257)) | DC31: =(('3B. Tel. - Rev. Detail x Month'!Q241)+('3B. Tel. - Rev. Detail x Month'!Q257)) | ... DG31: =(('3B. Tel. - Rev. Detail x Month'!U241)+('3B. Tel. - Rev. Detail x Month'!U257)) | DI31: =SUM(CV31:DG31)
D33: COGS by Month | R33: 0 | S33: 0 | T33: 0 | Y33: =(('3B. Tel. - Rev. Detail x Month'!J62)+('3B. Tel. - Rev. Detail x Month'!J71)) | Z33: =(('3B. Tel. - Rev. Detail x Month'!K62)+('3B. Tel. - Rev. Detail x Month'!K71)) | AA33: =(('3B. Tel. - Rev. Detail x Month'!L62)+('3B. Tel. - Rev. Detail x Month'!L71)) | AB33: =(('3B. Tel. - Rev. Detail x Month'!M62)+('3B. Tel. - Rev. Detail x Month'!M71)) | AC33: =(('3B. Tel. - Rev. Detail x Month'!N62)+('3B. Tel. - Rev. Detail x Month'!N71)) | AD33: =(('3B. Tel. - Rev. Detail x Month'!O62)+('3B. Tel. - Rev. Detail x Month'!O71)) | AE33: =(('3B. Tel. - Rev. Detail x Month'!P62)+('3B. Tel. - Rev. Detail x Month'!P71)) | AF33: =(('3B. Tel. - Rev. Detail x Month'!Q62)+('3B. Tel. - Rev. Detail x Month'!Q71)) | ... AI33: =(('3B. Tel. - Rev. Detail x Month'!T62)+('3B. Tel. - Rev. Detail x Month'!T71)) | AJ33: =(('3B. Tel. - Rev. Detail x Month'!Q62)+('3B. Tel. - Rev. Detail x Month'!Q71)) | AL33: =SUM(T33:AJ33) | AN33: =(('3B. Tel. - Rev. Detail x Month'!J100)+('3B. Tel. - Rev. Detail x Month'!J109)) | AO33: =(('3B. Tel. - Rev. Detail x Month'!K100)+('3B. Tel. - Rev. Detail x Month'!K109)) | AP33: =(('3B. Tel. - Rev. Detail x Month'!L100)+('3B. Tel. - Rev. Detail x Month'!L109)) | AQ33: =(('3B. Tel. - Rev. Detail x Month'!M100)+('3B. Tel. - Rev. Detail x Month'!M109)) | AR33: =(('3B. Tel. - Rev. Detail x Month'!N100)+('3B. Tel. - Rev. Detail x Month'!N109)) | AS33: =(('3B. Tel. - Rev. Detail x Month'!O100)+('3B. Tel. - Rev. Detail x Month'!O109)) | AT33: =(('3B. Tel. - Rev. Detail x Month'!P100)+('3B. Tel. - Rev. Detail x Month'!P109)) | AU33: =(('3B. Tel. - Rev. Detail x Month'!Q100)+('3B. Tel. - Rev. Detail x Month'!Q109)) | ... AY33: =(('3B. Tel. - Rev. Detail x Month'!U100)+('3B. Tel. - Rev. Detail x Month'!U109)) | BA33: =SUM(AN33:AY33) | BC33: =(('3B. Tel. - Rev. Detail x Month'!J138)+('3B. Tel. - Rev. Detail x Month'!J147)) | BD33: =(('3B. Tel. - Rev. Detail x Month'!K138)+('3B. Tel. - Rev. Detail x Month'!K147)) | BE33: =(('3B. Tel. - Rev. Detail x Month'!L138)+('3B. Tel. - Rev. Detail x Month'!L147)) | BF33: =(('3B. Tel. - Rev. Detail x Month'!M138)+('3B. Tel. - Rev. Detail x Month'!M147)) | BG33: =(('3B. Tel. - Rev. Detail x Month'!N138)+('3B. Tel. - Rev. Detail x Month'!N147)) | BH33: =(('3B. Tel. - Rev. Detail x Month'!O138)+('3B. Tel. - Rev. Detail x Month'!O147)) | BI33: =(('3B. Tel. - Rev. Detail x Month'!P138)+('3B. Tel. - Rev. Detail x Month'!P147)) | BJ33: =(('3B. Tel. - Rev. Detail x Month'!Q138)+('3B. Tel. - Rev. Detail x Month'!Q147)) | ... BN33: =(('3B. Tel. - Rev. Detail x Month'!U138)+('3B. Tel. - Rev. Detail x Month'!U147)) | BP33: =SUM(BC33:BN33) | BR33: =(('3B. Tel. - Rev. Detail x Month'!J176)+('3B. Tel. - Rev. Detail x Month'!J185)) | BS33: =(('3B. Tel. - Rev. Detail x Month'!K176)+('3B. Tel. - Rev. Detail x Month'!K185)) | BT33: =(('3B. Tel. - Rev. Detail x Month'!L176)+('3B. Tel. - Rev. Detail x Month'!L185)) | BU33: =(('3B. Tel. - Rev. Detail x Month'!M176)+('3B. Tel. - Rev. Detail x Month'!M185)) | BV33: =(('3B. Tel. - Rev. Detail x Month'!N176)+('3B. Tel. - Rev. Detail x Month'!N185)) | BW33: =(('3B. Tel. - Rev. Detail x Month'!O176)+('3B. Tel. - Rev. Detail x Month'!O185)) | BX33: =(('3B. Tel. - Rev. Detail x Month'!P176)+('3B. Tel. - Rev. Detail x Month'!P185)) | BY33: =(('3B. Tel. - Rev. Detail x Month'!Q176)+('3B. Tel. - Rev. Detail x Month'!Q185)) | ... CC33: =(('3B. Tel. - Rev. Detail x Month'!U176)+('3B. Tel. - Rev. Detail x Month'!U185)) | CE33: =SUM(BR33:CC33) | CG33: =(('3B. Tel. - Rev. Detail x Month'!J214)+('3B. Tel. - Rev. Detail x Month'!J223)) | CH33: =(('3B. Tel. - Rev. Detail x Month'!K214)+('3B. Tel. - Rev. Detail x Month'!K223)) | CI33: =(('3B. Tel. - Rev. Detail x Month'!L214)+('3B. Tel. - Rev. Detail x Month'!L223)) | CJ33: =(('3B. Tel. - Rev. Detail x Month'!M214)+('3B. Tel. - Rev. Detail x Month'!M223)) | CK33: =(('3B. Tel. - Rev. Detail x Month'!N214)+('3B. Tel. - Rev. Detail x Month'!N223)) | CL33: =(('3B. Tel. - Rev. Detail x Month'!O214)+('3B. Tel. - Rev. Detail x Month'!O223)) | CM33: =(('3B. Tel. - Rev. Detail x Month'!P214)+('3B. Tel. - Rev. Detail x Month'!P223)) | CN33: =(('3B. Tel. - Rev. Detail x Month'!Q214)+('3B. Tel. - Rev. Detail x Month'!Q223)) | ... CR33: =(('3B. Tel. - Rev. Detail x Month'!U214)+('3B. Tel. - Rev. Detail x Month'!U223)) | CT33: =SUM(CG33:CR33) | CV33: =(('3B. Tel. - Rev. Detail x Month'!J252)+('3B. Tel. - Rev. Detail x Month'!J261)) | CW33: =(('3B. Tel. - Rev. Detail x Month'!K252)+('3B. Tel. - Rev. Detail x Month'!K261)) | CX33: =(('3B. Tel. - Rev. Detail x Month'!L252)+('3B. Tel. - Rev. Detail x Month'!L261)) | CY33: =(('3B. Tel. - Rev. Detail x Month'!M252)+('3B. Tel. - Rev. Detail x Month'!M261)) | CZ33: =(('3B. Tel. - Rev. Detail x Month'!N252)+('3B. Tel. - Rev. Detail x Month'!N261)) | DA33: =(('3B. Tel. - Rev. Detail x Month'!O252)+('3B. Tel. - Rev. Detail x Month'!O261)) | DB33: =(('3B. Tel. - Rev. Detail x Month'!P252)+('3B. Tel. - Rev. Detail x Month'!P261)) | DC33: =(('3B. Tel. - Rev. Detail x Month'!Q252)+('3B. Tel. - Rev. Detail x Month'!Q261)) | ... DG33: =(('3B. Tel. - Rev. Detail x Month'!U252)+('3B. Tel. - Rev. Detail x Month'!U261)) | DI33: =SUM(CV33:DG33)
D35: Vendor PO and Deposit, by Month | U35: =((Y31)*($G$68)*($G$78)) | Y35: =((Z31)*($G$68)*($G$78)) | Z35: =((AA31)*($G$68)*($G$78)) | AA35: =((AB31)*($G$68)*($G$78)) | AB35: =((AC31)*($G$68)*($G$78)) | AC35: =((AD31)*($G$68)*($G$78)) | AD35: =((AE31)*($G$68)*($G$78)) | AE35: =((AF31)*($G$68)*($G$78)) | AF35: =((AG31)*($G$68)*($G$78)) | ... AI35: =((AJ31)*($G$68)*($G$78)) | AJ35: =((AN31)*($G$68)*($G$78)) | AL35: =SUM(U35:AJ35) | AN35: =((AO31)*($G$68)*($G$78)) | AO35: =((AP31)*($G$68)*($G$78)) | AP35: =((AQ31)*($G$68)*($G$78)) | AQ35: =((AR31)*($G$69)*($G$78)) | AR35: =((AS31)*($G$69)*($G$78)) | AS35: =((AT31)*($G$69)*($G$78)) | AT35: =((AU31)*($G$69)*($G$78)) | AU35: =((AV31)*($G$69)*($G$78)) | AV35: =((AW31)*($G$69)*($G$78)) | AW35: =((AX31)*($G$69)*($G$78)) | AX35: =((AY31)*($G$69)*($G$78)) | AY35: =((BC31)*($G$69)*($G$78)) | BA35: =SUM(AN35:AY35) | BC35: =((BD31)*($G$69)*($G$78)) | BD35: =((BE31)*($G$69)*($G$78)) | BE35: =((BF31)*($G$69)*($G$78)) | BF35: =((BG31)*($G$70)*($G$78)) | BG35: =((BH31)*($G$70)*($G$78)) | BH35: =((BI31)*($G$70)*($G$78)) | BI35: =((BJ31)*($G$70)*($G$78)) | BJ35: =((BK31)*($G$70)*($G$78)) | BK35: =((BL31)*($G$70)*($G$78)) | BL35: =((BM31)*($G$70)*($G$78)) | BM35: =((BN31)*($G$70)*($G$78)) | BN35: =((BR31)*($G$70)*($G$78)) | BP35: =SUM(BC35:BN35) | BR35: =((BS31)*($G$70)*($G$78)) | BS35: =((BT31)*($G$70)*($G$78)) | BT35: =((BU31)*($G$70)*($G$78)) | BU35: =((BV31)*($G$71)*($G$78)) | BV35: =((BW31)*($G$71)*($G$78)) | BW35: =((BX31)*($G$71)*($G$78)) | BX35: =((BY31)*($G$71)*($G$78)) | BY35: =((BZ31)*($G$71)*($G$78)) | BZ35: =((CA31)*($G$71)*($G$78)) | CA35: =((CB31)*($G$71)*($G$78)) | CB35: =((CC31)*($G$71)*($G$78)) | CC35: =((CG31)*($G$71)*($G$78)) | CE35: =SUM(BR35:CC35) | CG35: =((CH31)*($G$71)*($G$78)) | CH35: =((CI31)*($G$71)*($G$78)) | CI35: =((CJ31)*($G$71)*($G$78)) | CJ35: =((CK31)*($G$72)*($G$78)) | CK35: =((CL31)*($G$72)*($G$78)) | CL35: =((CM31)*($G$72)*($G$78)) | CM35: =((CN31)*($G$72)*($G$78)) | CN35: =((CO31)*($G$72)*($G$78)) | CO35: =((CP31)*($G$72)*($G$78)) | CP35: =((CQ31)*($G$72)*($G$78)) | CQ35: =((CR31)*($G$72)*($G$78)) | CR35: =((CV31)*($G$72)*($G$78)) | CT35: =SUM(CG35:CR35) | CV35: =((CW31)*($G$72)*($G$78)) | CW35: =((CX31)*($G$72)*($G$78)) | CX35: =((CY31)*($G$72)*($G$78)) | CY35: =((CZ31)*($G$73)*($G$78)) | CZ35: =((DA31)*($G$73)*($G$78)) | DA35: =((DB31)*($G$73)*($G$78)) | DB35: =((DC31)*($G$73)*($G$78)) | DC35: =((DD31)*($G$73)*($G$78)) | DD35: =((DE31)*($G$73)*($G$78)) | DE35: =((DF31)*($G$73)*($G$78)) | DF35: =((DG31)*($G$73)*($G$78)) | DG35: 0 | DI35: =SUM(CV35:DG35)
D37: Vendor Balance, by Month | R37: 0 | Y37: =((Y31)*($G$68)*($G$79)) | Z37: =((Z31)*($G$68)*($G$79)) | AA37: =((AA31)*($G$68)*($G$79)) | AB37: =((AB31)*($G$68)*($G$79)) | AC37: =((AC31)*($G$68)*($G$79)) | AD37: =((AD31)*($G$68)*($G$79)) | AE37: =((AE31)*($G$68)*($G$79)) | AF37: =((AF31)*($G$68)*($G$79)) | ... AJ37: =((AJ31)*($G$68)*($G$79)) | AL37: =SUM(T37:AJ37) | AN37: =((AN31)*($G$68)*($G$79)) | AO37: =((AO31)*($G$68)*($G$79)) | AP37: =((AP31)*($G$68)*($G$79)) | AQ37: =((AQ31)*($G$68)*($G$79)) | AR37: =((AR31)*($G$69)*($G$79)) | AS37: =((AS31)*($G$69)*($G$79)) | AT37: =((AT31)*($G$69)*($G$79)) | AU37: =((AU31)*($G$69)*($G$79)) | AV37: =((AV31)*($G$69)*($G$79)) | AW37: =((AW31)*($G$69)*($G$79)) | AX37: =((AX31)*($G$69)*($G$79)) | AY37: =((AY31)*($G$69)*($G$79)) | BA37: =SUM(AN37:AY37) | BC37: =((BC31)*($G$69)*($G$79)) | BD37: =((BD31)*($G$69)*($G$79)) | BE37: =((BE31)*($G$69)*($G$79)) | BF37: =((BF31)*($G$69)*($G$79)) | BG37: =((BG31)*($G$70)*($G$79)) | BH37: =((BH31)*($G$70)*($G$79)) | BI37: =((BI31)*($G$70)*($G$79)) | BJ37: =((BJ31)*($G$70)*($G$79)) | BK37: =((BK31)*($G$70)*($G$79)) | BL37: =((BL31)*($G$70)*($G$79)) | BM37: =((BM31)*($G$70)*($G$79)) | BN37: =((BN31)*($G$70)*($G$79)) | BP37: =SUM(BC37:BN37) | BR37: =((BR31)*($G$70)*($G$79)) | BS37: =((BS31)*($G$70)*($G$79)) | BT37: =((BT31)*($G$70)*($G$79)) | BU37: =((BU31)*($G$70)*($G$79)) | BV37: =((BV31)*($G$71)*($G$79)) | BW37: =((BW31)*($G$71)*($G$79)) | BX37: =((BX31)*($G$71)*($G$79)) | BY37: =((BY31)*($G$71)*($G$79)) | BZ37: =((BZ31)*($G$71)*($G$79)) | CA37: =((CA31)*($G$71)*($G$79)) | CB37: =((CB31)*($G$71)*($G$79)) | CC37: =((CC31)*($G$71)*($G$79)) | CE37: =SUM(BR37:CC37) | CG37: =((CG31)*($G$71)*($G$79)) | CH37: =((CH31)*($G$71)*($G$79)) | CI37: =((CI31)*($G$71)*($G$79)) | CJ37: =((CJ31)*($G$71)*($G$79)) | CK37: =((CK31)*($G$72)*($G$79)) | CL37: =((CL31)*($G$72)*($G$79)) | CM37: =((CM31)*($G$72)*($G$79)) | CN37: =((CN31)*($G$72)*($G$79)) | CO37: =((CO31)*($G$72)*($G$79)) | CP37: =((CP31)*($G$72)*($G$79)) | CQ37: =((CQ31)*($G$72)*($G$79)) | CR37: =((CR31)*($G$72)*($G$79)) | CT37: =SUM(CG37:CR37) | CV37: =((CV31)*($G$72)*($G$79)) | CW37: =((CW31)*($G$72)*($G$79)) | CX37: =((CX31)*($G$72)*($G$79)) | CY37: =((CY31)*($G$72)*($G$79)) | CZ37: =((CZ31)*($G$73)*($G$79)) | DA37: =((DA31)*($G$73)*($G$79)) | DB37: =((DB31)*($G$73)*($G$79)) | DC37: =((DC31)*($G$73)*($G$79)) | DD37: =((DD31)*($G$73)*($G$79)) | DE37: =((DE31)*($G$73)*($G$79)) | DF37: =((DF31)*($G$73)*($G$79)) | DG37: =((DG31)*($G$73)*($G$79)) | DI37: =SUM(CV37:DG37)
F40: Total Vendor Payments, by Month | J40: 0 | K40: 0 | L40: 0 | M40: 0 | N40: 0 | O40: 0 | P40: 0 | Q40: 0 | R40: 0 | S40: 0 | T40: =((T35)+(T37)) | U40: =((U35)+(U37)) | Y40: =((Y35)+(Y37)) | Z40: =((Z35)+(Z37)) | AA40: =((AA35)+(AA37)) | AB40: =((AB35)+(AB37)) | AC40: =((AC35)+(AC37)) | AD40: =((AD35)+(AD37)) | AE40: =((AE35)+(AE37)) | AF40: =((AF35)+(AF37)) | ... AJ40: =((AJ35)+(AJ37)) | AL40: =((AL35)+(AL37)) | AN40: =((AN35)+(AN37)) | AO40: =((AO35)+(AO37)) | AP40: =((AP35)+(AP37)) | AQ40: =((AQ35)+(AQ37)) | AR40: =((AR35)+(AR37)) | AS40: =((AS35)+(AS37)) | AT40: =((AT35)+(AT37)) | AU40: =((AU35)+(AU37)) | ... AY40: =((AY35)+(AY37)) | BA40: =((BA35)+(BA37)) | BC40: =((BC35)+(BC37)) | BD40: =((BD35)+(BD37)) | BE40: =((BE35)+(BE37)) | BF40: =((BF35)+(BF37)) | BG40: =((BG35)+(BG37)) | BH40: =((BH35)+(BH37)) | BI40: =((BI35)+(BI37)) | BJ40: =((BJ35)+(BJ37)) | ... BN40: =((BN35)+(BN37)) | BP40: =((BP35)+(BP37)) | BR40: =((BR35)+(BR37)) | BS40: =((BS35)+(BS37)) | BT40: =((BT35)+(BT37)) | BU40: =((BU35)+(BU37)) | BV40: =((BV35)+(BV37)) | BW40: =((BW35)+(BW37)) | BX40: =((BX35)+(BX37)) | BY40: =((BY35)+(BY37)) | ... CC40: =((CC35)+(CC37)) | CE40: =((CE35)+(CE37)) | CG40: =((CG35)+(CG37)) | CH40: =((CH35)+(CH37)) | CI40: =((CI35)+(CI37)) | CJ40: =((CJ35)+(CJ37)) | CK40: =((CK35)+(CK37)) | CL40: =((CL35)+(CL37)) | CM40: =((CM35)+(CM37)) | CN40: =((CN35)+(CN37)) | ... CR40: =((CR35)+(CR37)) | CT40: =((CT35)+(CT37)) | CV40: =((CV35)+(CV37)) | CW40: =((CW35)+(CW37)) | CX40: =((CX35)+(CX37)) | CY40: =((CY35)+(CY37)) | CZ40: =((CZ35)+(CZ37)) | DA40: =((DA35)+(DA37)) | DB40: =((DB35)+(DB37)) | DC40: =((DC35)+(DC37)) | ... DG40: =((DG35)+(DG37)) | DI40: =((DI35)+(DI37))
F44: COGS Check | Y44: =((U35)+(Y37)) | Z44: =((Y35)+(Z37)) | AA44: =((Z35)+(AA37)) | AB44: =((AA35)+(AB37)) | AC44: =((AB35)+(AC37)) | AD44: =((AC35)+(AD37)) | AE44: =((AD35)+(AE37)) | AF44: =((AE35)+(AF37)) | AG44: =((AF35)+(AG37)) | ... AJ44: =((AI35)+(AJ37)) | AL44: =SUM(Y44:AJ44) | AN44: =((AJ35)+(AN37)) | AO44: =((AN35)+(AO37)) | AP44: =((AO35)+(AP37)) | AQ44: =((AP35)+(AQ37)) | AR44: =((AQ35)+(AR37)) | AS44: =((AR35)+(AS37)) | AT44: =((AS35)+(AT37)) | AU44: =((AT35)+(AU37)) | AV44: =((AU35)+(AV37)) | ... AY44: =((AX35)+(AY37)) | BA44: =SUM(AN44:AY44) | BC44: =((AY35)+(BC37)) | BD44: =((BC35)+(BD37)) | BE44: =((BD35)+(BE37)) | BF44: =((BE35)+(BF37)) | BG44: =((BF35)+(BG37)) | BH44: =((BG35)+(BH37)) | BI44: =((BH35)+(BI37)) | BJ44: =((BI35)+(BJ37)) | BK44: =((BJ35)+(BK37)) | ... BN44: =((BM35)+(BN37)) | BP44: =SUM(BC44:BN44) | BR44: =((BN35)+(BR37)) | BS44: =((BR35)+(BS37)) | BT44: =((BS35)+(BT37)) | BU44: =((BT35)+(BU37)) | BV44: =((BU35)+(BV37)) | BW44: =((BV35)+(BW37)) | BX44: =((BW35)+(BX37)) | BY44: =((BX35)+(BY37)) | BZ44: =((BY35)+(BZ37)) | ... CC44: =((CB35)+(CC37)) | CE44: =SUM(BR44:CC44) | CG44: =((CC35)+(CG37)) | CH44: =((CG35)+(CH37)) | CI44: =((CH35)+(CI37)) | CJ44: =((CI35)+(CJ37)) | CK44: =((CJ35)+(CK37)) | CL44: =((CK35)+(CL37)) | CM44: =((CL35)+(CM37)) | CN44: =((CM35)+(CN37)) | CO44: =((CN35)+(CO37)) | ... CR44: =((CQ35)+(CR37)) | CT44: =SUM(CG44:CR44) | CV44: =((CR35)+(CV37)) | CW44: =((CV35)+(CW37)) | CX44: =((CW35)+(CX37)) | CY44: =((CX35)+(CY37)) | CZ44: =((CY35)+(CZ37)) | DA44: =((CZ35)+(DA37)) | DB44: =((DA35)+(DB37)) | DC44: =((DB35)+(DC37)) | DD44: =((DC35)+(DD37)) | ... DG44: =((DF35)+(DG37)) | DI44: =SUM(CV44:DG44)
F45: COGS Check | U45: =((Y33)-(Y44)) | Y45: =((Y33)-(Y44)) | Z45: =((Z33)-(Z44)) | AA45: =((AA33)-(AA44)) | AB45: =((AB33)-(AB44)) | AC45: =((AC33)-(AC44)) | AD45: =((AD33)-(AD44)) | AE45: =((AE33)-(AE44)) | AF45: =((AF33)-(AF44)) | ... AJ45: =((AJ33)-(AJ44)) | AL45: =((AL33)-(AL44)) | AN45: =((AN33)-(AN44)) | AO45: =((AO33)-(AO44)) | AP45: =((AP33)-(AP44)) | AQ45: =((AQ33)-(AQ44)) | AR45: =((AR33)-(AR44)) | AS45: =((AS33)-(AS44)) | AT45: =((AT33)-(AT44)) | AU45: =((AU33)-(AU44)) | ... AY45: =((AY33)-(AY44)) | BA45: =((BA33)-(BA44)) | BC45: =((BC33)-(BC44)) | BD45: =((BD33)-(BD44)) | BE45: =((BE33)-(BE44)) | BF45: =((BF33)-(BF44)) | BG45: =((BG33)-(BG44)) | BH45: =((BH33)-(BH44)) | BI45: =((BI33)-(BI44)) | BJ45: =((BJ33)-(BJ44)) | ... BN45: =((BN33)-(BN44)) | BP45: =((BP33)-(BP44)) | BR45: =((BR33)-(BR44)) | BS45: =((BS33)-(BS44)) | BT45: =((BT33)-(BT44)) | BU45: =((BU33)-(BU44)) | BV45: =((BV33)-(BV44)) | BW45: =((BW33)-(BW44)) | BX45: =((BX33)-(BX44)) | BY45: =((BY33)-(BY44)) | ... CC45: =((CC33)-(CC44)) | CE45: =((CE33)-(CE44)) | CG45: =((CG33)-(CG44)) | CH45: =((CH33)-(CH44)) | CI45: =((CI33)-(CI44)) | CJ45: =((CJ33)-(CJ44)) | CK45: =((CK33)-(CK44)) | CL45: =((CL33)-(CL44)) | CM45: =((CM33)-(CM44)) | CN45: =((CN33)-(CN44)) | ... CR45: =((CR33)-(CR44)) | CT45: =((CT33)-(CT44)) | CV45: =((CV33)-(CV44)) | CW45: =((CW33)-(CW44)) | CX45: =((CX33)-(CX44)) | CY45: =((CY33)-(CY44)) | CZ45: =((CZ33)-(CZ44)) | DA45: =((DA33)-(DA44)) | DB45: =((DB33)-(DB44)) | DC45: =((DC33)-(DC44)) | ... DG45: =((DG33)-(DG44)) | DI45: =((DI33)-(DI44))
U46: =G68 | AQ46: =G69 | BF46: =G70 | BU46: =G71 | CJ46: =G72 | CY46: =G73
F47: Deposit | U47: Unit Cost (Deposit) - Orders Placed With Vendor Months -1 - 15 | AQ47: Unit Cost (Deposit) - Orders Placed With Vendor Months 16 - 27 | BF47: Unit Cost (Deposit) - Orders Placed With Vendor Months 28 - 39 | BU47: Unit Cost (Deposit) - Orders Placed With Vendor Months 40 - 51 | CJ47: Unit Cost (Deposit) - Orders Placed With Vendor Months 52 - 63 | CY47: Unit Cost (Deposit) - Orders Placed With Vendor Months 64 - 76
F49: Balance | Y49: Unit Cost (Balance) - Delivery + Orders Shipped/Sold to Customers Months 1 - 16 | AR49: Unit Cost (Balance) - Delivery + Orders Shipped/Sold to Customers Months 17 - 28 | BG49: Unit Cost (Balance) - Delivery + Orders Shipped/Sold to Customers Months 29 - 40 | BV49: Unit Cost (Balance) - Delivery + Orders Shipped/Sold to Customers Months 41 - 52 | CK49: Unit Cost (Balance) - Delivery + Orders Shipped/Sold to Customers Months 53 - 64 | CZ49: Unit Cost (Balance) - Delivery + Orders Shipped/Sold to Customers Months 65 - 77
Y50: =G68 | AR50: =G69 | BG50: =G70 | BV50: =G71 | CK50: =G72 | CZ50: =G73
AJ52: Double Check | AL52: =SUM(Y40:AJ40) | AY52: Double Check | BA52: =SUM(AN40:AY40) | BN52: Double Check | BP52: =SUM(BC40:BN40) | CC52: Double Check | CE52: =SUM(BR40:CC40) | CR52: Double Check | CT52: =SUM(CG40:CR40) | DG52: Double Check | DI52: =SUM(CV40:DG40)
AJ53: Double Check | AL53: =AL40-AL52
B54: III. | D54: ASSUMPTIONS: UNIT COST, VENDOR TERMS AND ORDER-TO CASH-CYCLE
D58: ● | E58: Order Deposit (30%) Placed in Month -1 = 1st Month
D59: ● | E59: Order Balance Paid at Shipment / Delivered in Beginning of Month 1 = 2nd Month
D60: ● | E60: Units Delivered to PT in Month 1, Delivered to Customers by the end of Month 1 = 2nd Month
D61: ● | E61: Total Order-to-Cash Cycle = 60 Days (Order Place to Deliver, 30 Days + Sale/Customer Payment (IF NOT ALREADY GENERATED), 30 Days = 60 Days)
D63: Unit Cost and Order-to-Cash Cycle
D66: ● | E66: Orders Placed 30 Days in Advance of Delivery to PT
D67: ● | E67: Orders Placed 60 Days in Advance of Delivery to Customer
D68: ● | E68: Orders Placed Months - 1 through 15 | G68: ='3B. Tel. - Rev. Detail x Month'!J28 | I68: For Delivery to PT Months 1 through 16 and Sale/Delivery to Customers Months 1 - 16
D69: ● | E69: Orders Placed Months 16 - 27 | G69: ='3B. Tel. - Rev. Detail x Month'!J29 | I69: For Delivery to PT Months 17 through 28 and Sale/Delivery to Customers Months 17 - 28
D70: ● | E70: Orders Placed Months 28 - 39 | G70: ='3B. Tel. - Rev. Detail x Month'!J30 | I70: For Delivery to PT Months 29 through 40 and Sale/Delivery to Customers Months 29 - 40
D71: ● | E71: Orders Placed Months 40 - 51 | G71: ='3B. Tel. - Rev. Detail x Month'!J31 | I71: For Delivery to PT Months 41 through 52 and Sale/Delivery to Customers Months 41 - 52
D72: ● | E72: Orders Placed Months 52 - 63 | G72: ='3B. Tel. - Rev. Detail x Month'!J32 | I72: For Delivery to PT Months 53 through 64 and Sale/Delivery to Customers Months 53 - 64
D73: ● | E73: Orders Placed Months 64 - 75 | G73: ='3B. Tel. - Rev. Detail x Month'!J33 | I73: For Delivery to PT Months 65 through 76 and Sale/Delivery to Customers Months 65 - 76
D75: Vendor Payment Terms
D78: ● | E78: Deposit with PO | G78: 0.3
D79: ● | E79: Balance at Shipment | G79: =((1)-(G78))
D80: ● | E80: Deposit - 60 days prior to anticipated sale
D81: ● | E81: Balance - 30 days prior to anticipated sale
B86: IV. | D86: WARRANTY
D90: ● | E90: Assume purchase of an insurance policy to fund customer warranty claims
E92: Warranty Payments, by Month | Y92: ='3B. Tel. - Rev. Detail x Month'!$J75 | Z92: ='3B. Tel. - Rev. Detail x Month'!$K75 | AA92: ='3B. Tel. - Rev. Detail x Month'!$L75 | AB92: ='3B. Tel. - Rev. Detail x Month'!$M75 | AC92: ='3B. Tel. - Rev. Detail x Month'!$N75 | AD92: ='3B. Tel. - Rev. Detail x Month'!$O75 | AE92: ='3B. Tel. - Rev. Detail x Month'!$P75 | AF92: ='3B. Tel. - Rev. Detail x Month'!$Q75 | AG92: ='3B. Tel. - Rev. Detail x Month'!$R75 | AH92: ='3B. Tel. - Rev. Detail x Month'!$S75 | AI92: ='3B. Tel. - Rev. Detail x Month'!$T75 | AJ92: ='3B. Tel. - Rev. Detail x Month'!$U75 | AL92: =SUM(Y92:AJ92) | AN92: ='3B. Tel. - Rev. Detail x Month'!$J113 | AO92: ='3B. Tel. - Rev. Detail x Month'!$K113 | AP92: ='3B. Tel. - Rev. Detail x Month'!$L113 | AQ92: ='3B. Tel. - Rev. Detail x Month'!$M113 | AR92: ='3B. Tel. - Rev. Detail x Month'!$N113 | AS92: ='3B. Tel. - Rev. Detail x Month'!$O113 | AT92: ='3B. Tel. - Rev. Detail x Month'!$P113 | AU92: ='3B. Tel. - Rev. Detail x Month'!$Q113 | AV92: ='3B. Tel. - Rev. Detail x Month'!$R113 | AW92: ='3B. Tel. - Rev. Detail x Month'!$S113 | AX92: ='3B. Tel. - Rev. Detail x Month'!$T113 | AY92: ='3B. Tel. - Rev. Detail x Month'!$U113 | BA92: =SUM(AN92:AY92) | BC92: ='3B. Tel. - Rev. Detail x Month'!$J151 | BD92: ='3B. Tel. - Rev. Detail x Month'!$K151 | BE92: ='3B. Tel. - Rev. Detail x Month'!$L151 | BF92: ='3B. Tel. - Rev. Detail x Month'!$M151 | BG92: ='3B. Tel. - Rev. Detail x Month'!$N151 | BH92: ='3B. Tel. - Rev. Detail x Month'!$O151 | BI92: ='3B. Tel. - Rev. Detail x Month'!$P151 | BJ92: ='3B. Tel. - Rev. Detail x Month'!$Q151 | BK92: ='3B. Tel. - Rev. Detail x Month'!$R151 | BL92: ='3B. Tel. - Rev. Detail x Month'!$S151 | BM92: ='3B. Tel. - Rev. Detail x Month'!$T151 | BN92: ='3B. Tel. - Rev. Detail x Month'!$U151 | BP92: =SUM(BC92:BN92) | BR92: ='3B. Tel. - Rev. Detail x Month'!$J189 | BS92: ='3B. Tel. - Rev. Detail x Month'!$K189 | BT92: ='3B. Tel. - Rev. Detail x Month'!$L189 | BU92: ='3B. Tel. - Rev. Detail x Month'!$M189 | BV92: ='3B. Tel. - Rev. Detail x Month'!$N189 | BW92: ='3B. Tel. - Rev. Detail x Month'!$O189 | BX92: ='3B. Tel. - Rev. Detail x Month'!$P189 | BY92: ='3B. Tel. - Rev. Detail x Month'!$Q189 | BZ92: ='3B. Tel. - Rev. Detail x Month'!$R189 | CA92: ='3B. Tel. - Rev. Detail x Month'!$S189 | CB92: ='3B. Tel. - Rev. Detail x Month'!$T189 | CC92: ='3B. Tel. - Rev. Detail x Month'!$U189 | CE92: =SUM(BR92:CC92) | CG92: ='3B. Tel. - Rev. Detail x Month'!$J227 | CH92: ='3B. Tel. - Rev. Detail x Month'!$K227 | CI92: ='3B. Tel. - Rev. Detail x Month'!$L227 | CJ92: ='3B. Tel. - Rev. Detail x Month'!$M227 | CK92: ='3B. Tel. - Rev. Detail x Month'!$N227 | CL92: ='3B. Tel. - Rev. Detail x Month'!$O227 | CM92: ='3B. Tel. - Rev. Detail x Month'!$P227 | CN92: ='3B. Tel. - Rev. Detail x Month'!$Q227 | CO92: ='3B. Tel. - Rev. Detail x Month'!$R227 | CP92: ='3B. Tel. - Rev. Detail x Month'!$S227 | CQ92: ='3B. Tel. - Rev. Detail x Month'!$T227 | CR92: ='3B. Tel. - Rev. Detail x Month'!$U227 | CT92: =SUM(CG92:CR92)

Sheet 2D. Crowd Funding
B2: Impact of Crowdfunding Capital Raise on Month 1 Cash Receipts Associated With Telephone Sales
B8: Anticipated Number of Investors/Consumer Opt Ins | G8: 10000
B9: Amount Invested/Per Investor/Consumer | G9: =G20
J12: Perks
D13: Total Capital Raised | G13: =((G8)*(G9)) | J13: grandfather # - e.g. your phones are limited edition and within the platform other people can see you were one of the first to have this
B20: Selling price of Telephone, Year 1 | G20: ='3B. Tel. - Rev. Detail x Month'!J18
B21: Investors | G21: =(G8)
C25: Amount Allocated to Customers Deposits | G25: =((G20)*(G21))
C27: Amount Allocated to Capital | G27: =((G13)-(G25))
D31: Total | G31: =((G25)+(G27))
B36: First 3,000 investors fund cost of Pre-Launch Investory Investment
C37: Amount credited to revenue upon shipment of telephones to customers
C38: Cash paid during Crowdfunding
B40: Next 6,000 Customers fund Month 1 telephone purchases | G40: =(((10000)-(4000))*(G20))
C41: Amount credited to revenue upon shipment of telephones to customers
C44: Month 1 - planned revenue and cash from telephone sales | G44: =('3B. Tel. - Rev. Detail x Month'!J55)
C45: Less: Month 1 telephone sales paid in advance through Crowdfunding - 4,000 units | G45: =(-G40)
D48: Month 1 cash from sales of telephones | G48: =SUM(G44:G45)
E52: Check | G52: ='2B. Cash Collections'!X20
B59: Anticipated Number of Pre-Sales/Program Opt ins | G59: 0
B60: Amount Invested/Per Investor | G60: =G9
D64: Total Capital Raised | G64: =((G59)*(G60))
B71: Selling price of Telephone, Year 1 | G71: =G20
B72: Investors | G72: =(G59)
C76: Amount Allocated to Customers Deposits | G76: =((G71)*(G72))
C78: Amount Allocated to Capital | G78: =((G64)-(G76))
D82: Total - Pre-Sales / Program Opt Ins | G82: =((G76)+(G78))

Sheet 3A. Tel. - Roll-Up Rev. x Mth.
B2: PURE TECHNOLOGY
B4: REVENUE ROLL-UP BY MONTH, POST-LAUNCH
B6: MONTHS 1 - 60
J11: Year 1
J14: Month 1 | L14: Month 2 | N14: Month 3 | P14: Month 4 | R14: Month 5 | T14: Month 6 | V14: Month 7 | X14: Month 8 | Z14: Month 9 | AB14: Month 10 | AD14: Month 11 | AF14: Month 12 | AH14: Full-Year
B17: Total Net Revenue, Hardware | J17: ='3B. Tel. - Rev. Detail x Month'!J448 | L17: ='3B. Tel. - Rev. Detail x Month'!K448 | N17: ='3B. Tel. - Rev. Detail x Month'!L448 | P17: ='3B. Tel. - Rev. Detail x Month'!M448 | R17: ='3B. Tel. - Rev. Detail x Month'!N448 | T17: ='3B. Tel. - Rev. Detail x Month'!O448 | V17: ='3B. Tel. - Rev. Detail x Month'!P448 | X17: ='3B. Tel. - Rev. Detail x Month'!Q448 | Z17: ='3B. Tel. - Rev. Detail x Month'!R448 | AB17: ='3B. Tel. - Rev. Detail x Month'!S448 | AD17: ='3B. Tel. - Rev. Detail x Month'!T448 | AF17: ='3B. Tel. - Rev. Detail x Month'!U448 | AH17: =((J17)+(L17)+(N17)+(P17)+(R17)+(T17)+(V17)+(X17)+(Z17)+(AB17)+(AD17)+(AF17))
B18: Total Net Revenue, Market Research Services | J18: ='3B. Tel. - Rev. Detail x Month'!J449 | L18: ='3B. Tel. - Rev. Detail x Month'!K449 | N18: ='3B. Tel. - Rev. Detail x Month'!L449 | P18: ='3B. Tel. - Rev. Detail x Month'!M449 | R18: ='3B. Tel. - Rev. Detail x Month'!N449 | T18: ='3B. Tel. - Rev. Detail x Month'!O449 | V18: ='3B. Tel. - Rev. Detail x Month'!P449 | X18: ='3B. Tel. - Rev. Detail x Month'!Q449 | Z18: ='3B. Tel. - Rev. Detail x Month'!R449 | AB18: ='3B. Tel. - Rev. Detail x Month'!S449 | AD18: ='3B. Tel. - Rev. Detail x Month'!T449 | AF18: ='3B. Tel. - Rev. Detail x Month'!U449 | AH18: =((J18)+(L18)+(N18)+(P18)+(R18)+(T18)+(V18)+(X18)+(Z18)+(AB18)+(AD18)+(AF18))
C21: Total Net Revenue, Hardware + Market Research Services | J21: =SUM(J17:J18) | L21: =SUM(L17:L18) | N21: =SUM(N17:N18) | P21: =SUM(P17:P18) | R21: =SUM(R17:R18) | T21: =SUM(T17:T18) | V21: =SUM(V17:V18) | X21: =SUM(X17:X18) | Z21: =SUM(Z17:Z18) | AB21: =SUM(AB17:AB18) | AD21: =SUM(AD17:AD18) | AF21: =SUM(AF17:AF18) | AH21: =((J21)+(L21)+(N21)+(P21)+(R21)+(T21)+(V21)+(X21)+(Z21)+(AB21)+(AD21)+(AF21)) | AJ21: ='3B. Tel. - Rev. Detail x Month'!W452
J26: Year 2
J29: Month 13 | L29: Month 14 | N29: Month 15 | P29: Month 16 | R29: Month 17 | T29: Month 18 | V29: Month 19 | X29: Month 20 | Z29: Month 21 | AB29: Month 22 | AD29: Month 23 | AF29: Month 24 | AH29: Full-Year
B32: Total Net Revenue, Hardware | J32: ='3B. Tel. - Rev. Detail x Month'!J463 | L32: ='3B. Tel. - Rev. Detail x Month'!K463 | N32: ='3B. Tel. - Rev. Detail x Month'!L463 | P32: ='3B. Tel. - Rev. Detail x Month'!M463 | R32: ='3B. Tel. - Rev. Detail x Month'!N463 | T32: ='3B. Tel. - Rev. Detail x Month'!O463 | V32: ='3B. Tel. - Rev. Detail x Month'!P463 | X32: ='3B. Tel. - Rev. Detail x Month'!Q463 | Z32: ='3B. Tel. - Rev. Detail x Month'!R463 | AB32: ='3B. Tel. - Rev. Detail x Month'!S463 | AD32: ='3B. Tel. - Rev. Detail x Month'!T463 | AF32: ='3B. Tel. - Rev. Detail x Month'!U463 | AH32: =((J32)+(L32)+(N32)+(P32)+(R32)+(T32)+(V32)+(X32)+(Z32)+(AB32)+(AD32)+(AF32))
B33: Total Net Revenue, Market Research Services | J33: ='3B. Tel. - Rev. Detail x Month'!J464 | L33: ='3B. Tel. - Rev. Detail x Month'!K464 | N33: ='3B. Tel. - Rev. Detail x Month'!L464 | P33: ='3B. Tel. - Rev. Detail x Month'!M464 | R33: ='3B. Tel. - Rev. Detail x Month'!N464 | T33: ='3B. Tel. - Rev. Detail x Month'!O464 | V33: ='3B. Tel. - Rev. Detail x Month'!P464 | X33: ='3B. Tel. - Rev. Detail x Month'!Q464 | Z33: ='3B. Tel. - Rev. Detail x Month'!R464 | AB33: ='3B. Tel. - Rev. Detail x Month'!S464 | AD33: ='3B. Tel. - Rev. Detail x Month'!T464 | AF33: ='3B. Tel. - Rev. Detail x Month'!U464 | AH33: =((J33)+(L33)+(N33)+(P33)+(R33)+(T33)+(V33)+(X33)+(Z33)+(AB33)+(AD33)+(AF33))
C36: Total Net Revenue, Hardware + Market Research Services | J36: =SUM(J32:J33) | L36: =SUM(L32:L33) | N36: =SUM(N32:N33) | P36: =SUM(P32:P33) | R36: =SUM(R32:R33) | T36: =SUM(T32:T33) | V36: =SUM(V32:V33) | X36: =SUM(X32:X33) | Z36: =SUM(Z32:Z33) | AB36: =SUM(AB32:AB33) | AD36: =SUM(AD32:AD33) | AF36: =SUM(AF32:AF33) | AH36: =((J36)+(L36)+(N36)+(P36)+(R36)+(T36)+(V36)+(X36)+(Z36)+(AB36)+(AD36)+(AF36)) | AJ36: ='3B. Tel. - Rev. Detail x Month'!W467
J41: Year 3
J44: Month 25 | L44: Month 26 | N44: Month 27 | P44: Month 28 | R44: Month 29 | T44: Month 30 | V44: Month 31 | X44: Month 32 | Z44: Month 33 | AB44: Month 34 | AD44: Month 35 | AF44: Month 36 | AH44: Full-Year
B47: Total Net Revenue, Hardware | J47: ='3B. Tel. - Rev. Detail x Month'!J478 | L47: ='3B. Tel. - Rev. Detail x Month'!K478 | N47: ='3B. Tel. - Rev. Detail x Month'!L478 | P47: ='3B. Tel. - Rev. Detail x Month'!M478 | R47: ='3B. Tel. - Rev. Detail x Month'!N478 | T47: ='3B. Tel. - Rev. Detail x Month'!O478 | V47: ='3B. Tel. - Rev. Detail x Month'!P478 | X47: ='3B. Tel. - Rev. Detail x Month'!Q478 | Z47: ='3B. Tel. - Rev. Detail x Month'!R478 | AB47: ='3B. Tel. - Rev. Detail x Month'!S478 | AD47: ='3B. Tel. - Rev. Detail x Month'!T478 | AF47: ='3B. Tel. - Rev. Detail x Month'!U478 | AH47: =((J47)+(L47)+(N47)+(P47)+(R47)+(T47)+(V47)+(X47)+(Z47)+(AB47)+(AD47)+(AF47))
B48: Total Net Revenue, Market Research Services | J48: ='3B. Tel. - Rev. Detail x Month'!J479 | L48: ='3B. Tel. - Rev. Detail x Month'!K479 | N48: ='3B. Tel. - Rev. Detail x Month'!L479 | P48: ='3B. Tel. - Rev. Detail x Month'!M479 | R48: ='3B. Tel. - Rev. Detail x Month'!N479 | T48: ='3B. Tel. - Rev. Detail x Month'!O479 | V48: ='3B. Tel. - Rev. Detail x Month'!P479 | X48: ='3B. Tel. - Rev. Detail x Month'!Q479 | Z48: ='3B. Tel. - Rev. Detail x Month'!R479 | AB48: ='3B. Tel. - Rev. Detail x Month'!S479 | AD48: ='3B. Tel. - Rev. Detail x Month'!T479 | AF48: ='3B. Tel. - Rev. Detail x Month'!U479 | AH48: =((J48)+(L48)+(N48)+(P48)+(R48)+(T48)+(V48)+(X48)+(Z48)+(AB48)+(AD48)+(AF48))
C51: Total Net Revenue, Hardware + Market Research Services | J51: =SUM(J47:J48) | L51: =SUM(L47:L48) | N51: =SUM(N47:N48) | P51: =SUM(P47:P48) | R51: =SUM(R47:R48) | T51: =SUM(T47:T48) | V51: =SUM(V47:V48) | X51: =SUM(X47:X48) | Z51: =SUM(Z47:Z48) | AB51: =SUM(AB47:AB48) | AD51: =SUM(AD47:AD48) | AF51: =SUM(AF47:AF48) | AH51: =((J51)+(L51)+(N51)+(P51)+(R51)+(T51)+(V51)+(X51)+(Z51)+(AB51)+(AD51)+(AF51)) | AJ51: ='3B. Tel. - Rev. Detail x Month'!W482
J56: Year 4
J59: Month 37 | L59: Month 38 | N59: Month 39 | P59: Month 40 | R59: Month 41 | T59: Month 42 | V59: Month 43 | X59: Month 44 | Z59: Month 45 | AB59: Month 46 | AD59: Month 47 | AF59: Month 48 | AH59: Full-Year
B62: Total Net Revenue, Hardware | J62: ='3B. Tel. - Rev. Detail x Month'!J493 | L62: ='3B. Tel. - Rev. Detail x Month'!K493 | N62: ='3B. Tel. - Rev. Detail x Month'!L493 | P62: ='3B. Tel. - Rev. Detail x Month'!M493 | R62: ='3B. Tel. - Rev. Detail x Month'!N493 | T62: ='3B. Tel. - Rev. Detail x Month'!O493 | V62: ='3B. Tel. - Rev. Detail x Month'!P493 | X62: ='3B. Tel. - Rev. Detail x Month'!Q493 | Z62: ='3B. Tel. - Rev. Detail x Month'!R493 | AB62: ='3B. Tel. - Rev. Detail x Month'!S493 | AD62: ='3B. Tel. - Rev. Detail x Month'!T493 | AF62: ='3B. Tel. - Rev. Detail x Month'!U493 | AH62: =((J62)+(L62)+(N62)+(P62)+(R62)+(T62)+(V62)+(X62)+(Z62)+(AB62)+(AD62)+(AF62))
B63: Total Net Revenue, Market Research Services | J63: ='3B. Tel. - Rev. Detail x Month'!J494 | L63: ='3B. Tel. - Rev. Detail x Month'!K494 | N63: ='3B. Tel. - Rev. Detail x Month'!L494 | P63: ='3B. Tel. - Rev. Detail x Month'!M494 | R63: ='3B. Tel. - Rev. Detail x Month'!N494 | T63: ='3B. Tel. - Rev. Detail x Month'!O494 | V63: ='3B. Tel. - Rev. Detail x Month'!P494 | X63: ='3B. Tel. - Rev. Detail x Month'!Q494 | Z63: ='3B. Tel. - Rev. Detail x Month'!R494 | AB63: ='3B. Tel. - Rev. Detail x Month'!S494 | AD63: ='3B. Tel. - Rev. Detail x Month'!T494 | AF63: ='3B. Tel. - Rev. Detail x Month'!U494 | AH63: =((J63)+(L63)+(N63)+(P63)+(R63)+(T63)+(V63)+(X63)+(Z63)+(AB63)+(AD63)+(AF63))
C66: Total Net Revenue, Hardware + Market Research Services | J66: =SUM(J62:J63) | L66: =SUM(L62:L63) | N66: =SUM(N62:N63) | P66: =SUM(P62:P63) | R66: =SUM(R62:R63) | T66: =SUM(T62:T63) | V66: =SUM(V62:V63) | X66: =SUM(X62:X63) | Z66: =SUM(Z62:Z63) | AB66: =SUM(AB62:AB63) | AD66: =SUM(AD62:AD63) | AF66: =SUM(AF62:AF63) | AH66: =((J66)+(L66)+(N66)+(P66)+(R66)+(T66)+(V66)+(X66)+(Z66)+(AB66)+(AD66)+(AF66)) | AJ66: ='3B. Tel. - Rev. Detail x Month'!W497
J71: Year 5
J74: Month 49 | L74: Month 50 | N74: Month 51 | P74: Month 52 | R74: Month 53 | T74: Month 54 | V74: Month 55 | X74: Month 56 | Z74: Month 57 | AB74: Month 58 | AD74: Month 59 | AF74: Month 60 | AH74: Full-Year
B77: Total Net Revenue, Hardware | J77: ='3B. Tel. - Rev. Detail x Month'!J508 | K77: ='3B. Tel. - Rev. Detail x Month'!#REF! | L77: ='3B. Tel. - Rev. Detail x Month'!K508 | M77: ='3B. Tel. - Rev. Detail x Month'!#REF! | N77: ='3B. Tel. - Rev. Detail x Month'!L508 | O77: ='3B. Tel. - Rev. Detail x Month'!#REF! | P77: ='3B. Tel. - Rev. Detail x Month'!M508 | Q77: ='3B. Tel. - Rev. Detail x Month'!#REF! | R77: ='3B. Tel. - Rev. Detail x Month'!N508 | S77: ='3B. Tel. - Rev. Detail x Month'!#REF! | T77: ='3B. Tel. - Rev. Detail x Month'!O508 | U77: ='3B. Tel. - Rev. Detail x Month'!#REF! | V77: ='3B. Tel. - Rev. Detail x Month'!P508 | W77: ='3B. Tel. - Rev. Detail x Month'!#REF! | X77: ='3B. Tel. - Rev. Detail x Month'!Q508 | Y77: ='3B. Tel. - Rev. Detail x Month'!#REF! | Z77: ='3B. Tel. - Rev. Detail x Month'!R508 | AA77: ='3B. Tel. - Rev. Detail x Month'!#REF! | AB77: ='3B. Tel. - Rev. Detail x Month'!S508 | AC77: ='3B. Tel. - Rev. Detail x Month'!#REF! | AD77: ='3B. Tel. - Rev. Detail x Month'!T508 | AE77: ='3B. Tel. - Rev. Detail x Month'!#REF! | AF77: ='3B. Tel. - Rev. Detail x Month'!U508 | AH77: =((J77)+(L77)+(N77)+(P77)+(R77)+(T77)+(V77)+(X77)+(Z77)+(AB77)+(AD77)+(AF77))
B78: Total Net Revenue, Market Research Services | J78: ='3B. Tel. - Rev. Detail x Month'!J509 | K78: ='3B. Tel. - Rev. Detail x Month'!#REF! | L78: ='3B. Tel. - Rev. Detail x Month'!K509 | M78: ='3B. Tel. - Rev. Detail x Month'!#REF! | N78: ='3B. Tel. - Rev. Detail x Month'!L509 | O78: ='3B. Tel. - Rev. Detail x Month'!#REF! | P78: ='3B. Tel. - Rev. Detail x Month'!M509 | Q78: ='3B. Tel. - Rev. Detail x Month'!#REF! | R78: ='3B. Tel. - Rev. Detail x Month'!N509 | S78: ='3B. Tel. - Rev. Detail x Month'!#REF! | T78: ='3B. Tel. - Rev. Detail x Month'!O509 | U78: ='3B. Tel. - Rev. Detail x Month'!#REF! | V78: ='3B. Tel. - Rev. Detail x Month'!P509 | W78: ='3B. Tel. - Rev. Detail x Month'!#REF! | X78: ='3B. Tel. - Rev. Detail x Month'!Q509 | Y78: ='3B. Tel. - Rev. Detail x Month'!#REF! | Z78: ='3B. Tel. - Rev. Detail x Month'!R509 | AA78: ='3B. Tel. - Rev. Detail x Month'!#REF! | AB78: ='3B. Tel. - Rev. Detail x Month'!S509 | AC78: ='3B. Tel. - Rev. Detail x Month'!#REF! | AD78: ='3B. Tel. - Rev. Detail x Month'!T509 | AE78: ='3B. Tel. - Rev. Detail x Month'!#REF! | AF78: ='3B. Tel. - Rev. Detail x Month'!U509 | AH78: =((J78)+(L78)+(N78)+(P78)+(R78)+(T78)+(V78)+(X78)+(Z78)+(AB78)+(AD78)+(AF78))
C81: Total Net Revenue, Hardware + Market Research Services | J81: =SUM(J77:J78) | K81: =SUM(K77:K78) | L81: =SUM(L77:L78) | M81: =SUM(M77:M78) | N81: =SUM(N77:N78) | O81: =SUM(O77:O78) | P81: =SUM(P77:P78) | Q81: =SUM(Q77:Q78) | ... AF81: =SUM(AF77:AF78) | AH81: =((J81)+(L81)+(N81)+(P81)+(R81)+(T81)+(V81)+(X81)+(Z81)+(AB81)+(AD81)+(AF81)) | AJ81: ='3B. Tel. - Rev. Detail x Month'!W512

Sheet 3B. Tel. - Rev. Detail x Month
B2: PURE TECHNOLOGY
B4: REVENUE DETAIL BY MONTH, POST-LAUNCH
B6: MONTHS 1 - 60
B11: Revenue Assumptions
B15: Telephone - selling price/unit (cost/unit + $50) | J15: Price/Unit | K15: Margin | L15: Percent
D18: Months 1 - 12 | J18: =((J28)+(180)) | K18: =J18-J28 | L18: =K18/J28
D19: Months 13 - 24 | J19: =((J29)+(185)) | K19: =J19-J29 | L19: =K19/J29
D20: Months 25 - 36 | J20: =((J30)+(190)) | K20: =J20-J30 | L20: =K20/J30
D21: Months 37 - 48 | J21: =((J31)+(195)) | K21: =J21-J31 | L21: =K21/J31
D22: Months 49 - 60 | J22: =((J32)+(200)) | K22: =J22-J32 | L22: =K22/J32
D23: Months 61 - 72 | J23: =((J33)+(205)) | K23: =J23-J33 | L23: =K23/J33
B25: Telephone - cost/unit | J25: Cost/Unit
D28: Orders Placed Months - 1 through 15 | J28: ='3F. Revenue & COGS Assumptions'!G35 | K28: For Delivery to PT Months -1 through 16
D29: Orders Placed Months 16 - 27 | J29: ='3F. Revenue & COGS Assumptions'!S35 | K29: For Delivery to PT Months 17 through 28
D30: Orders Placed Months 28 - 39 | J30: ='3F. Revenue & COGS Assumptions'!AE35 | K30: For Delivery to PT Months 29 through 40
D31: Orders Placed Months 40 - 51 | J31: ='3F. Revenue & COGS Assumptions'!AQ35 | K31: For Delivery to PT Months 41 through 52
D32: Orders Placed Months 52 - 63 | J32: ='3F. Revenue & COGS Assumptions'!BC35 | K32: For Delivery to PT Months 53 through 64
D33: Orders Placed Months 64 - 75 | J33: ='3F. Revenue & COGS Assumptions'!BO35 | K33: For Delivery to PT Months 65 through 76
B37: Revenue and CoGS - Telephone Handsets
B41: I. | D41: Hardware - Handsets Sold and Replaced
J44: Year 1
J47: Month 1 | K47: Month 2 | L47: Month 3 | M47: Month 4 | N47: Month 5 | O47: Month 6 | P47: Month 7 | Q47: Month 8 | R47: Month 9 | S47: Month 10 | T47: Month 11 | U47: Month 12 | W47: Full-Year
D50: ● | E50: New Users
F51: Number of Activated Telephones | J51: =(('3C. Tel. - Revenue Drivers - 1 '!J83)+(3000)) | K51: =('3C. Tel. - Revenue Drivers - 1 '!K83) | L51: =('3C. Tel. - Revenue Drivers - 1 '!L83) | M51: =('3C. Tel. - Revenue Drivers - 1 '!M83) | N51: =('3C. Tel. - Revenue Drivers - 1 '!N83) | O51: =('3C. Tel. - Revenue Drivers - 1 '!O83) | P51: =('3C. Tel. - Revenue Drivers - 1 '!P83) | Q51: =('3C. Tel. - Revenue Drivers - 1 '!Q83) | R51: =('3C. Tel. - Revenue Drivers - 1 '!R83) | ... U51: =('3C. Tel. - Revenue Drivers - 1 '!U83) | W51: =((J51)+(K51)+(L51)+(M51)+(N51)+(O51)+(P51)+(Q51)+(R51)+(S51)+(T51)+(U51))
F52: Selling Price/Handset, including logistics | J52: =($J$18) | K52: =($J$18) | L52: =($J$18) | M52: =($J$18) | N52: =($J$18) | O52: =($J$18) | P52: =($J$18) | Q52: =($J$18) | ... U52: =($J$18)
G55: Revenue, Handsets to New Users | J55: =((J51)*(J52)) | K55: =((K51)*(K52)) | L55: =((L51)*(L52)) | M55: =((M51)*(M52)) | N55: =((N51)*(N52)) | O55: =((O51)*(O52)) | P55: =((P51)*(P52)) | Q55: =((Q51)*(Q52)) | ... U55: =((U51)*(U52)) | W55: =((J55)+(K55)+(L55)+(M55)+(N55)+(O55)+(P55)+(Q55)+(R55)+(S55)+(T55)+(U55))
F59: Cost/handset, including logistics | J59: =($J$28) | K59: =($J$28) | L59: =($J$28) | M59: =($J$28) | N59: =($J$28) | O59: =($J$28) | P59: =($J$28) | Q59: =($J$28) | ... U59: =($J$28)
G62: CoGS, Handsets to New Users | J62: =((J51)*(J59)) | K62: =((K51)*(K59)) | L62: =((L51)*(L59)) | M62: =((M51)*(M59)) | N62: =((N51)*(N59)) | O62: =((O51)*(O59)) | P62: =((P51)*(P59)) | Q62: =((Q51)*(Q59)) | ... U62: =((U51)*(U59)) | W62: =((J62)+(K62)+(L62)+(M62)+(N62)+(O62)+(P62)+(Q62)+(R62)+(S62)+(T62)+(U62))
D66: ● | E66: Renewals
F67: Number of Renewals | J67: ='3C. Tel. - Revenue Drivers - 1 '!J84 | K67: ='3C. Tel. - Revenue Drivers - 1 '!K84 | L67: ='3C. Tel. - Revenue Drivers - 1 '!L84 | M67: ='3C. Tel. - Revenue Drivers - 1 '!M84 | N67: ='3C. Tel. - Revenue Drivers - 1 '!N84 | O67: ='3C. Tel. - Revenue Drivers - 1 '!O84 | P67: ='3C. Tel. - Revenue Drivers - 1 '!P84 | Q67: ='3C. Tel. - Revenue Drivers - 1 '!Q84 | ... U67: ='3C. Tel. - Revenue Drivers - 1 '!U84 | W67: =((J67)+(K67)+(L67)+(M67)+(N67)+(O67)+(P67)+(Q67)+(R67)+(S67)+(T67)+(U67))
F68: Cost/handset, including logistics | J68: =($J$28) | K68: =($J$28) | L68: =($J$28) | M68: =($J$28) | N68: =($J$28) | O68: =($J$28) | P68: =($J$28) | Q68: =($J$28) | ... U68: =($J$28)
G71: CoGS, Handsets to Renewals | J71: =((J67)*(J68)) | K71: =((K67)*(K68)) | L71: =((L67)*(L68)) | M71: =((M67)*(M68)) | N71: =((N67)*(N68)) | O71: =((O67)*(O68)) | P71: =((P67)*(P68)) | Q71: =((Q67)*(Q68)) | ... U71: =((U67)*(U68)) | W71: =((J71)+(K71)+(L71)+(M71)+(N71)+(O71)+(P71)+(Q71)+(R71)+(S71)+(T71)+(U71))
D75: ● | E75: Warranty (0.11% of Hardware Revenue) | J75: =((0.001)*(J55)) | K75: =((0.001)*(K55)) | L75: =((0.001)*(L55)) | M75: =((0.001)*(M55)) | N75: =((0.001)*(N55)) | O75: =((0.001)*(O55)) | P75: =((0.001)*(P55)) | Q75: =((0.001)*(Q55)) | ... U75: =((0.001)*(U55)) | W75: =((J75)+(K75)+(L75)+(M75)+(N75)+(O75)+(P75)+(Q75)+(R75)+(S75)+(T75)+(U75))
H77: Net Revenue = Revenue Less CoGS Less Warranty | J77: =((J55)-(J62)-(J71)-(J75)) | K77: =((K55)-(K62)-(K71)-(K75)) | L77: =((L55)-(L62)-(L71)-(L75)) | M77: =((M55)-(M62)-(M71)-(M75)) | N77: =((N55)-(N62)-(N71)-(N75)) | O77: =((O55)-(O62)-(O71)-(O75)) | P77: =((P55)-(P62)-(P71)-(P75)) | Q77: =((Q55)-(Q62)-(Q71)-(Q75)) | ... U77: =((U55)-(U62)-(U71)-(U75)) | W77: =((W55)-(W62)-(W71)-(W75))
J82: Year 2
J85: Month 13 | K85: Month 14 | L85: Month 15 | M85: Month 16 | N85: Month 17 | O85: Month 18 | P85: Month 19 | Q85: Month 20 | R85: Month 21 | S85: Month 22 | T85: Month 23 | U85: Month 24 | W85: Full-Year
D88: ● | E88: New Users
F89: Number of Activated Telephones | J89: ='3C. Tel. - Revenue Drivers - 1 '!J101 | K89: =('3C. Tel. - Revenue Drivers - 1 '!K101) | L89: =('3C. Tel. - Revenue Drivers - 1 '!L101) | M89: =('3C. Tel. - Revenue Drivers - 1 '!M101) | N89: =('3C. Tel. - Revenue Drivers - 1 '!N101) | O89: =('3C. Tel. - Revenue Drivers - 1 '!O101) | P89: =('3C. Tel. - Revenue Drivers - 1 '!P101) | Q89: =('3C. Tel. - Revenue Drivers - 1 '!Q101) | R89: =('3C. Tel. - Revenue Drivers - 1 '!R101) | ... U89: =('3C. Tel. - Revenue Drivers - 1 '!U101) | W89: =((J89)+(K89)+(L89)+(M89)+(N89)+(O89)+(P89)+(Q89)+(R89)+(S89)+(T89)+(U89))
F90: Selling Price/Handset, including logistics | J90: =($J$19) | K90: =($J$19) | L90: =($J$19) | M90: =($J$19) | N90: =($J$19) | O90: =($J$19) | P90: =($J$19) | Q90: =($J$19) | ... U90: =($J$19)
G93: Revenue, Handsets to New Users | J93: =((J89)*(J90)) | K93: =((K89)*(K90)) | L93: =((L89)*(L90)) | M93: =((M89)*(M90)) | N93: =((N89)*(N90)) | O93: =((O89)*(O90)) | P93: =((P89)*(P90)) | Q93: =((Q89)*(Q90)) | ... U93: =((U89)*(U90)) | W93: =((J93)+(K93)+(L93)+(M93)+(N93)+(O93)+(P93)+(Q93)+(R93)+(S93)+(T93)+(U93))
F97: Cost/handset, including logistics | J97: =($J$28) | K97: =($J$28) | L97: =($J$28) | M97: =($J$28) | N97: =($J$29) | O97: =($J$29) | P97: =($J$29) | Q97: =($J$29) | R97: =($J$29) | S97: =($J$29) | T97: =($J$29) | U97: =($J$29)
G100: CoGS, Handsets to New Users | J100: =((J89)*(J97)) | K100: =((K89)*(K97)) | L100: =((L89)*(L97)) | M100: =((M89)*(M97)) | N100: =((N89)*(N97)) | O100: =((O89)*(O97)) | P100: =((P89)*(P97)) | Q100: =((Q89)*(Q97)) | ... U100: =((U89)*(U97)) | W100: =((J100)+(K100)+(L100)+(M100)+(N100)+(O100)+(P100)+(Q100)+(R100)+(S100)+(T100)+(U100))
D104: ● | E104: Renewals
F105: Number of Renewals | J105: ='3C. Tel. - Revenue Drivers - 1 '!J102 | K105: =('3C. Tel. - Revenue Drivers - 1 '!K102) | L105: =('3C. Tel. - Revenue Drivers - 1 '!L102) | M105: =('3C. Tel. - Revenue Drivers - 1 '!M102) | N105: =('3C. Tel. - Revenue Drivers - 1 '!N102) | O105: =('3C. Tel. - Revenue Drivers - 1 '!O102) | P105: =('3C. Tel. - Revenue Drivers - 1 '!P102) | Q105: =('3C. Tel. - Revenue Drivers - 1 '!Q102) | R105: =('3C. Tel. - Revenue Drivers - 1 '!R102) | ... U105: =('3C. Tel. - Revenue Drivers - 1 '!U102) | W105: =((J105)+(K105)+(L105)+(M105)+(N105)+(O105)+(P105)+(Q105)+(R105)+(S105)+(T105)+(U105))
F106: Cost/handset, including logistics | J106: =($J$28) | K106: =($J$28) | L106: =($J$28) | M106: =($J$28) | N106: =($J$29) | O106: =($J$29) | P106: =($J$29) | Q106: =($J$29) | R106: =($J$29) | S106: =($J$29) | T106: =($J$29) | U106: =($J$29)
G109: CoGS, Handsets to Renewals | J109: =((J105)*(J106)) | K109: =((K105)*(K106)) | L109: =((L105)*(L106)) | M109: =((M105)*(M106)) | N109: =((N105)*(N106)) | O109: =((O105)*(O106)) | P109: =((P105)*(P106)) | Q109: =((Q105)*(Q106)) | ... U109: =((U105)*(U106)) | W109: =((J109)+(K109)+(L109)+(M109)+(N109)+(O109)+(P109)+(Q109)+(R109)+(S109)+(T109)+(U109))
D113: ● | E113: Warranty (0.11% of Hardware Revenue) | J113: =((0.001)*(J93)) | K113: =((0.001)*(K93)) | L113: =((0.001)*(L93)) | M113: =((0.001)*(M93)) | N113: =((0.001)*(N93)) | O113: =((0.001)*(O93)) | P113: =((0.001)*(P93)) | Q113: =((0.001)*(Q93)) | ... U113: =((0.001)*(U93)) | W113: =((J113)+(K113)+(L113)+(M113)+(N113)+(O113)+(P113)+(Q113)+(R113)+(S113)+(T113)+(U113))
H115: Net Revenue = Revenue Less CoGS | J115: =((J93)-(J100)-(J109)-(J113)) | K115: =((K93)-(K100)-(K109)-(K113)) | L115: =((L93)-(L100)-(L109)-(L113)) | M115: =((M93)-(M100)-(M109)-(M113)) | N115: =((N93)-(N100)-(N109)-(N113)) | O115: =((O93)-(O100)-(O109)-(O113)) | P115: =((P93)-(P100)-(P109)-(P113)) | Q115: =((Q93)-(Q100)-(Q109)-(Q113)) | ... U115: =((U93)-(U100)-(U109)-(U113)) | W115: =((W93)-(W100)-(W109)-(W113)) | Y115: =((W93)-(W100)-(W109)-(W113))
J120: Year 3
J123: Month 25 | K123: Month 26 | L123: Month 27 | M123: Month 28 | N123: Month 29 | O123: Month 30 | P123: Month 31 | Q123: Month 32 | R123: Month 33 | S123: Month 34 | T123: Month 35 | U123: Month 36 | W123: Full-Year
D126: ● | E126: New Users
F127: Number of Activated Telephones | J127: ='3C. Tel. - Revenue Drivers - 1 '!J119 | K127: ='3C. Tel. - Revenue Drivers - 1 '!K119 | L127: ='3C. Tel. - Revenue Drivers - 1 '!L119 | M127: ='3C. Tel. - Revenue Drivers - 1 '!M119 | N127: ='3C. Tel. - Revenue Drivers - 1 '!N119 | O127: ='3C. Tel. - Revenue Drivers - 1 '!O119 | P127: ='3C. Tel. - Revenue Drivers - 1 '!P119 | Q127: ='3C. Tel. - Revenue Drivers - 1 '!Q119 | ... U127: ='3C. Tel. - Revenue Drivers - 1 '!U119 | W127: =((J127)+(K127)+(L127)+(M127)+(N127)+(O127)+(P127)+(Q127)+(R127)+(S127)+(T127)+(U127))
F128: Selling Price/Handset, including logistics | J128: =($J$20) | K128: =($J$20) | L128: =($J$20) | M128: =($J$20) | N128: =($J$20) | O128: =($J$20) | P128: =($J$20) | Q128: =($J$20) | ... U128: =($J$20)
G131: Revenue, Handsets to New Users | J131: =((J127)*(J128)) | K131: =((K127)*(K128)) | L131: =((L127)*(L128)) | M131: =((M127)*(M128)) | N131: =((N127)*(N128)) | O131: =((O127)*(O128)) | P131: =((P127)*(P128)) | Q131: =((Q127)*(Q128)) | ... U131: =((U127)*(U128)) | W131: =((J131)+(K131)+(L131)+(M131)+(N131)+(O131)+(P131)+(Q131)+(R131)+(S131)+(T131)+(U131))
F135: Cost/handset, including logistics | J135: =($J$29) | K135: =($J$29) | L135: =($J$29) | M135: =($J$29) | N135: =($J$30) | O135: =($J$30) | P135: =($J$30) | Q135: =($J$30) | R135: =($J$30) | S135: =($J$30) | T135: =($J$30) | U135: =($J$30)
G138: CoGS, Handsets to New Users | J138: =((J127)*(J135)) | K138: =((K127)*(K135)) | L138: =((L127)*(L135)) | M138: =((M127)*(M135)) | N138: =((N127)*(N135)) | O138: =((O127)*(O135)) | P138: =((P127)*(P135)) | Q138: =((Q127)*(Q135)) | ... U138: =((U127)*(U135)) | W138: =((J138)+(K138)+(L138)+(M138)+(N138)+(O138)+(P138)+(Q138)+(R138)+(S138)+(T138)+(U138))
D142: ● | E142: Renewals
F143: Number of Renewals | J143: ='3C. Tel. - Revenue Drivers - 1 '!J120 | K143: ='3C. Tel. - Revenue Drivers - 1 '!K120 | L143: ='3C. Tel. - Revenue Drivers - 1 '!L120 | M143: ='3C. Tel. - Revenue Drivers - 1 '!M120 | N143: ='3C. Tel. - Revenue Drivers - 1 '!N120 | O143: ='3C. Tel. - Revenue Drivers - 1 '!O120 | P143: ='3C. Tel. - Revenue Drivers - 1 '!P120 | Q143: ='3C. Tel. - Revenue Drivers - 1 '!Q120 | ... U143: ='3C. Tel. - Revenue Drivers - 1 '!U120 | W143: =((J143)+(K143)+(L143)+(M143)+(N143)+(O143)+(P143)+(Q143)+(R143)+(S143)+(T143)+(U143))
F144: Cost/handset, including logistics | J144: =($J$29) | K144: =($J$29) | L144: =($J$29) | M144: =($J$29) | N144: =($J$30) | O144: =($J$30) | P144: =($J$30) | Q144: =($J$30) | R144: =($J$30) | S144: =($J$30) | T144: =($J$30) | U144: =($J$30)
G147: CoGS, Handsets to Renewals | J147: =((J143)*(J144)) | K147: =((K143)*(K144)) | L147: =((L143)*(L144)) | M147: =((M143)*(M144)) | N147: =((N143)*(N144)) | O147: =((O143)*(O144)) | P147: =((P143)*(P144)) | Q147: =((Q143)*(Q144)) | ... U147: =((U143)*(U144)) | W147: =((J147)+(K147)+(L147)+(M147)+(N147)+(O147)+(P147)+(Q147)+(R147)+(S147)+(T147)+(U147))
D151: ● | E151: Warranty (0.11% of Hardware Revenue) | J151: =((0.001)*(J131)) | K151: =((0.001)*(K131)) | L151: =((0.001)*(L131)) | M151: =((0.001)*(M131)) | N151: =((0.001)*(N131)) | O151: =((0.001)*(O131)) | P151: =((0.001)*(P131)) | Q151: =((0.001)*(Q131)) | ... U151: =((0.001)*(U131)) | W151: =((J151)+(K151)+(L151)+(M151)+(N151)+(O151)+(P151)+(Q151)+(R151)+(S151)+(T151)+(U151))
H153: Net Revenue = Revenue Less CoGS | J153: =((J131)-(J138)-(J147)-(J151)) | K153: =((K131)-(K138)-(K147)-(K151)) | L153: =((L131)-(L138)-(L147)-(L151)) | M153: =((M131)-(M138)-(M147)-(M151)) | N153: =((N131)-(N138)-(N147)-(N151)) | O153: =((O131)-(O138)-(O147)-(O151)) | P153: =((P131)-(P138)-(P147)-(P151)) | Q153: =((Q131)-(Q138)-(Q147)-(Q151)) | ... U153: =((U131)-(U138)-(U147)-(U151)) | W153: =((W131)-(W138)-(W147)-(W151)) | Y153: =((W131)-(W138)-(W147)-(W151))
J158: Year 4
J161: Month 37 | K161: Month 38 | L161: Month 39 | M161: Month 40 | N161: Month 41 | O161: Month 42 | P161: Month 43 | Q161: Month 44 | R161: Month 45 | S161: Month 46 | T161: Month 47 | U161: Month 48 | W161: Full-Year
D164: ● | E164: New Users
F165: Number of Activated Telephones | J165: ='3C. Tel. - Revenue Drivers - 1 '!J137 | K165: ='3C. Tel. - Revenue Drivers - 1 '!K137 | L165: ='3C. Tel. - Revenue Drivers - 1 '!L137 | M165: ='3C. Tel. - Revenue Drivers - 1 '!M137 | N165: ='3C. Tel. - Revenue Drivers - 1 '!N137 | O165: ='3C. Tel. - Revenue Drivers - 1 '!O137 | P165: ='3C. Tel. - Revenue Drivers - 1 '!P137 | Q165: ='3C. Tel. - Revenue Drivers - 1 '!Q137 | ... U165: ='3C. Tel. - Revenue Drivers - 1 '!U137 | W165: =((J165)+(K165)+(L165)+(M165)+(N165)+(O165)+(P165)+(Q165)+(R165)+(S165)+(T165)+(U165))
F166: Selling Price/Handset, including logistics | J166: =($J$21) | K166: =($J$21) | L166: =($J$21) | M166: =($J$21) | N166: =($J$21) | O166: =($J$21) | P166: =($J$21) | Q166: =($J$21) | ... U166: =($J$21)
G169: Revenue, Handsets to New Users | J169: =((J165)*(J166)) | K169: =((K165)*(K166)) | L169: =((L165)*(L166)) | M169: =((M165)*(M166)) | N169: =((N165)*(N166)) | O169: =((O165)*(O166)) | P169: =((P165)*(P166)) | Q169: =((Q165)*(Q166)) | ... U169: =((U165)*(U166)) | W169: =((J169)+(K169)+(L169)+(M169)+(N169)+(O169)+(P169)+(Q169)+(R169)+(S169)+(T169)+(U169))
F173: Cost/handset, including logistics | J173: =($J$30) | K173: =($J$30) | L173: =($J$30) | M173: =($J$30) | N173: =($J$31) | O173: =($J$31) | P173: =($J$31) | Q173: =($J$31) | R173: =($J$31) | S173: =($J$31) | T173: =($J$31) | U173: =($J$31)
G176: CoGS, Handsets to New Users | J176: =((J165)*(J173)) | K176: =((K165)*(K173)) | L176: =((L165)*(L173)) | M176: =((M165)*(M173)) | N176: =((N165)*(N173)) | O176: =((O165)*(O173)) | P176: =((P165)*(P173)) | Q176: =((Q165)*(Q173)) | ... U176: =((U165)*(U173)) | W176: =((J176)+(K176)+(L176)+(M176)+(N176)+(O176)+(P176)+(Q176)+(R176)+(S176)+(T176)+(U176))
D180: ● | E180: Renewals
F181: Number of Renewals | J181: ='3C. Tel. - Revenue Drivers - 1 '!J138 | K181: ='3C. Tel. - Revenue Drivers - 1 '!K138 | L181: ='3C. Tel. - Revenue Drivers - 1 '!L138 | M181: ='3C. Tel. - Revenue Drivers - 1 '!M138 | N181: ='3C. Tel. - Revenue Drivers - 1 '!N138 | O181: ='3C. Tel. - Revenue Drivers - 1 '!O138 | P181: ='3C. Tel. - Revenue Drivers - 1 '!P138 | Q181: ='3C. Tel. - Revenue Drivers - 1 '!Q138 | ... U181: ='3C. Tel. - Revenue Drivers - 1 '!U138 | W181: =((J181)+(K181)+(L181)+(M181)+(N181)+(O181)+(P181)+(Q181)+(R181)+(S181)+(T181)+(U181))
F182: Cost/handset, including logistics | J182: =($J$30) | K182: =($J$30) | L182: =($J$30) | M182: =($J$30) | N182: =($J$31) | O182: =($J$31) | P182: =($J$31) | Q182: =($J$31) | R182: =($J$31) | S182: =($J$31) | T182: =($J$31) | U182: =($J$31)
G185: CoGS, Handsets to Renewals | J185: =((J181)*(J182)) | K185: =((K181)*(K182)) | L185: =((L181)*(L182)) | M185: =((M181)*(M182)) | N185: =((N181)*(N182)) | O185: =((O181)*(O182)) | P185: =((P181)*(P182)) | Q185: =((Q181)*(Q182)) | ... U185: =((U181)*(U182)) | W185: =((J185)+(K185)+(L185)+(M185)+(N185)+(O185)+(P185)+(Q185)+(R185)+(S185)+(T185)+(U185))
D189: ● | E189: Warranty (0.11% of Hardware Revenue) | J189: =((0.001)*(J169)) | K189: =((0.001)*(K169)) | L189: =((0.001)*(L169)) | M189: =((0.001)*(M169)) | N189: =((0.001)*(N169)) | O189: =((0.001)*(O169)) | P189: =((0.001)*(P169)) | Q189: =((0.001)*(Q169)) | ... U189: =((0.001)*(U169)) | W189: =((J189)+(K189)+(L189)+(M189)+(N189)+(O189)+(P189)+(Q189)+(R189)+(S189)+(T189)+(U189))
H191: Net Revenue = Revenue Less CoGS | J191: =((J169)-(J176)-(J185)-(J189)) | K191: =((K169)-(K176)-(K185)-(K189)) | L191: =((L169)-(L176)-(L185)-(L189)) | M191: =((M169)-(M176)-(M185)-(M189)) | N191: =((N169)-(N176)-(N185)-(N189)) | O191: =((O169)-(O176)-(O185)-(O189)) | P191: =((P169)-(P176)-(P185)-(P189)) | Q191: =((Q169)-(Q176)-(Q185)-(Q189)) | ... U191: =((U169)-(U176)-(U185)-(U189)) | W191: =((W169)-(W176)-(W185)-(W189)) | Y191: =((W169)-(W176)-(W185)-(W189))
J196: Year 5
J199: Month 49 | K199: Month 50 | L199: Month 51 | M199: Month 52 | N199: Month 53 | O199: Month 54 | P199: Month 55 | Q199: Month 56 | R199: Month 57 | S199: Month 58 | T199: Month 59 | U199: Month 60 | W199: Full-Year
D202: ● | E202: New Users
F203: Number of Activated Telephones | J203: ='3C. Tel. - Revenue Drivers - 1 '!J155 | K203: ='3C. Tel. - Revenue Drivers - 1 '!K155 | L203: ='3C. Tel. - Revenue Drivers - 1 '!L155 | M203: ='3C. Tel. - Revenue Drivers - 1 '!M155 | N203: ='3C. Tel. - Revenue Drivers - 1 '!N155 | O203: ='3C. Tel. - Revenue Drivers - 1 '!O155 | P203: ='3C. Tel. - Revenue Drivers - 1 '!P155 | Q203: ='3C. Tel. - Revenue Drivers - 1 '!Q155 | ... U203: ='3C. Tel. - Revenue Drivers - 1 '!U155 | W203: =((J203)+(K203)+(L203)+(M203)+(N203)+(O203)+(P203)+(Q203)+(R203)+(S203)+(T203)+(U203))
F204: Selling Price/Handset, including logistics | J204: =($J$22) | K204: =($J$22) | L204: =($J$22) | M204: =($J$22) | N204: =($J$22) | O204: =($J$22) | P204: =($J$22) | Q204: =($J$22) | ... U204: =($J$22)
G207: Revenue, Handsets to New Users | J207: =((J203)*(J204)) | K207: =((K203)*(K204)) | L207: =((L203)*(L204)) | M207: =((M203)*(M204)) | N207: =((N203)*(N204)) | O207: =((O203)*(O204)) | P207: =((P203)*(P204)) | Q207: =((Q203)*(Q204)) | ... U207: =((U203)*(U204)) | W207: =((J207)+(K207)+(L207)+(M207)+(N207)+(O207)+(P207)+(Q207)+(R207)+(S207)+(T207)+(U207))
F211: Cost/handset, including logistics | J211: =($J$31) | K211: =($J$31) | L211: =($J$31) | M211: =($J$31) | N211: =($J$32) | O211: =($J$32) | P211: =($J$32) | Q211: =($J$32) | R211: =($J$32) | S211: =($J$32) | T211: =($J$32) | U211: =($J$32)
G214: CoGS, Handsets to New Users | J214: =((J203)*(J211)) | K214: =((K203)*(K211)) | L214: =((L203)*(L211)) | M214: =((M203)*(M211)) | N214: =((N203)*(N211)) | O214: =((O203)*(O211)) | P214: =((P203)*(P211)) | Q214: =((Q203)*(Q211)) | ... U214: =((U203)*(U211)) | W214: =((J214)+(K214)+(L214)+(M214)+(N214)+(O214)+(P214)+(Q214)+(R214)+(S214)+(T214)+(U214))
D218: ● | E218: Renewals
F219: Number of Renewals | J219: ='3C. Tel. - Revenue Drivers - 1 '!J156 | K219: ='3C. Tel. - Revenue Drivers - 1 '!K156 | L219: ='3C. Tel. - Revenue Drivers - 1 '!L156 | M219: ='3C. Tel. - Revenue Drivers - 1 '!M156 | N219: ='3C. Tel. - Revenue Drivers - 1 '!N156 | O219: ='3C. Tel. - Revenue Drivers - 1 '!O156 | P219: ='3C. Tel. - Revenue Drivers - 1 '!P156 | Q219: ='3C. Tel. - Revenue Drivers - 1 '!Q156 | ... U219: ='3C. Tel. - Revenue Drivers - 1 '!U156 | W219: =((J219)+(K219)+(L219)+(M219)+(N219)+(O219)+(P219)+(Q219)+(R219)+(S219)+(T219)+(U219))
F220: Cost/handset, including logistics | J220: =($J$31) | K220: =($J$31) | L220: =($J$31) | M220: =($J$31) | N220: =($J$32) | O220: =($J$32) | P220: =($J$32) | Q220: =($J$32) | R220: =($J$32) | S220: =($J$32) | T220: =($J$32) | U220: =($J$32)
G223: CoGS, Handsets to Renewals | J223: =((J219)*(J220)) | K223: =((K219)*(K220)) | L223: =((L219)*(L220)) | M223: =((M219)*(M220)) | N223: =((N219)*(N220)) | O223: =((O219)*(O220)) | P223: =((P219)*(P220)) | Q223: =((Q219)*(Q220)) | ... U223: =((U219)*(U220)) | W223: =((J223)+(K223)+(L223)+(M223)+(N223)+(O223)+(P223)+(Q223)+(R223)+(S223)+(T223)+(U223))
D227: ● | E227: Warranty (0.11% of Hardware Revenue) | J227: =((0.001)*(J207)) | K227: =((0.001)*(K207)) | L227: =((0.001)*(L207)) | M227: =((0.001)*(M207)) | N227: =((0.001)*(N207)) | O227: =((0.001)*(O207)) | P227: =((0.001)*(P207)) | Q227: =((0.001)*(Q207)) | ... U227: =((0.001)*(U207)) | W227: =((J227)+(K227)+(L227)+(M227)+(N227)+(O227)+(P227)+(Q227)+(R227)+(S227)+(T227)+(U227))
H229: Net Revenue = Revenue Less CoGS | J229: =((J207)-(J214)-(J223)-(J227)) | K229: =((K207)-(K214)-(K223)-(K227)) | L229: =((L207)-(L214)-(L223)-(L227)) | M229: =((M207)-(M214)-(M223)-(M227)) | N229: =((N207)-(N214)-(N223)-(N227)) | O229: =((O207)-(O214)-(O223)-(O227)) | P229: =((P207)-(P214)-(P223)-(P227)) | Q229: =((Q207)-(Q214)-(Q223)-(Q227)) | ... U229: =((U207)-(U214)-(U223)-(U227)) | W229: =((W207)-(W214)-(W223)-(W227)) | Y229: =((W207)-(W214)-(W223)-(W227))
J234: Year 6
J237: Month 61 | K237: Month 62 | L237: Month 63 | M237: Month 64 | N237: Month 65 | O237: Month 66 | P237: Month 67 | Q237: Month 68 | R237: Month 69 | S237: Month 70 | T237: Month 71 | U237: Month 72 | W237: Full-Year
D240: ● | E240: New Users
F241: Number of Activated Telephones | J241: ='3C. Tel. - Revenue Drivers - 1 '!J173 | K241: ='3C. Tel. - Revenue Drivers - 1 '!K173 | L241: ='3C. Tel. - Revenue Drivers - 1 '!L173 | M241: ='3C. Tel. - Revenue Drivers - 1 '!M173 | N241: ='3C. Tel. - Revenue Drivers - 1 '!N173 | O241: ='3C. Tel. - Revenue Drivers - 1 '!O173 | P241: ='3C. Tel. - Revenue Drivers - 1 '!P173 | Q241: ='3C. Tel. - Revenue Drivers - 1 '!Q173 | ... U241: ='3C. Tel. - Revenue Drivers - 1 '!U173 | W241: =((J241)+(K241)+(L241)+(M241)+(N241)+(O241)+(P241)+(Q241)+(R241)+(S241)+(T241)+(U241))
F242: Selling Price/Handset, including logistics | J242: =($J$23) | K242: =($J$23) | L242: =($J$23) | M242: =($J$23) | N242: =($J$23) | O242: =($J$23) | P242: =($J$23) | Q242: =($J$23) | ... U242: =($J$23)
G245: Revenue, Handsets to New Users | J245: =((J241)*(J242)) | K245: =((K241)*(K242)) | L245: =((L241)*(L242)) | M245: =((M241)*(M242)) | N245: =((N241)*(N242)) | O245: =((O241)*(O242)) | P245: =((P241)*(P242)) | Q245: =((Q241)*(Q242)) | ... U245: =((U241)*(U242)) | W245: =((J245)+(K245)+(L245)+(M245)+(N245)+(O245)+(P245)+(Q245)+(R245)+(S245)+(T245)+(U245))
F249: Cost/handset, including logistics | J249: =($J$32) | K249: =($J$32) | L249: =($J$32) | M249: =($J$32) | N249: =($J$33) | O249: =($J$33) | P249: =($J$33) | Q249: =($J$33) | R249: =($J$33) | S249: =($J$33) | T249: =($J$33) | U249: =($J$33)
G252: CoGS, Handsets to New Users | J252: =((J241)*(J249)) | K252: =((K241)*(K249)) | L252: =((L241)*(L249)) | M252: =((M241)*(M249)) | N252: =((N241)*(N249)) | O252: =((O241)*(O249)) | P252: =((P241)*(P249)) | Q252: =((Q241)*(Q249)) | ... U252: =((U241)*(U249)) | W252: =((J252)+(K252)+(L252)+(M252)+(N252)+(O252)+(P252)+(Q252)+(R252)+(S252)+(T252)+(U252))
D256: ● | E256: Renewals
F257: Number of Renewals | J257: ='3C. Tel. - Revenue Drivers - 1 '!J174 | K257: ='3C. Tel. - Revenue Drivers - 1 '!K174 | L257: ='3C. Tel. - Revenue Drivers - 1 '!L174 | M257: ='3C. Tel. - Revenue Drivers - 1 '!M174 | N257: ='3C. Tel. - Revenue Drivers - 1 '!N174 | O257: ='3C. Tel. - Revenue Drivers - 1 '!O174 | P257: ='3C. Tel. - Revenue Drivers - 1 '!P174 | Q257: ='3C. Tel. - Revenue Drivers - 1 '!Q174 | ... U257: ='3C. Tel. - Revenue Drivers - 1 '!U174 | W257: =((J257)+(K257)+(L257)+(M257)+(N257)+(O257)+(P257)+(Q257)+(R257)+(S257)+(T257)+(U257))
...

Sheet 3C. Tel. - Revenue Drivers - 1 
B2: PURE TECHNOLOGY
B4: TELEPHONE - REVENUE DRIVERS
B6: MONTHS 1 - 60
B11: A. | D11: Revenue Drivers
B15: I. | D15: New Phones Activated | J15: Fiscal Years 1 - 6
D18: Year | F18: Months | J18: Month 1 | K18: Month 2 | L18: Month 3 | M18: Month 4 | N18: Month 5 | O18: Month 6 | P18: Month 7 | Q18: Month 8 | R18: Month 9 | S18: Month 10 | T18: Month 11 | U18: Month 12 | V18: Ʃ, Full-Year
D21: Year 0 | F21: -12 - -1
D22: Year 1 | F22: 1 - 12 | J22: ='3F. Revenue & COGS Assumptions'!G12 | K22: ='3F. Revenue & COGS Assumptions'!H12 | L22: ='3F. Revenue & COGS Assumptions'!I12 | M22: ='3F. Revenue & COGS Assumptions'!J12 | N22: ='3F. Revenue & COGS Assumptions'!K12 | O22: ='3F. Revenue & COGS Assumptions'!L12 | P22: ='3F. Revenue & COGS Assumptions'!M12 | Q22: ='3F. Revenue & COGS Assumptions'!N12 | ... U22: ='3F. Revenue & COGS Assumptions'!R12 | V22: =((J22)+(K22)+(L22)+(M22)+(N22)+(O22)+(P22)+(Q22)+(R22)+(S22)+(T22)+(U22))
D23: Year 2 | F23: 13 - 24 | J23: ='3F. Revenue & COGS Assumptions'!G13 | K23: ='3F. Revenue & COGS Assumptions'!H13 | L23: ='3F. Revenue & COGS Assumptions'!I13 | M23: ='3F. Revenue & COGS Assumptions'!J13 | N23: ='3F. Revenue & COGS Assumptions'!K13 | O23: ='3F. Revenue & COGS Assumptions'!L13 | P23: ='3F. Revenue & COGS Assumptions'!M13 | Q23: ='3F. Revenue & COGS Assumptions'!N13 | ... U23: ='3F. Revenue & COGS Assumptions'!R13 | V23: =((J23)+(K23)+(L23)+(M23)+(N23)+(O23)+(P23)+(Q23)+(R23)+(S23)+(T23)+(U23))
D24: Year 3 | F24: 25 - 36 | J24: ='3F. Revenue & COGS Assumptions'!G14 | K24: ='3F. Revenue & COGS Assumptions'!H14 | L24: ='3F. Revenue & COGS Assumptions'!I14 | M24: ='3F. Revenue & COGS Assumptions'!J14 | N24: ='3F. Revenue & COGS Assumptions'!K14 | O24: ='3F. Revenue & COGS Assumptions'!L14 | P24: ='3F. Revenue & COGS Assumptions'!M14 | Q24: ='3F. Revenue & COGS Assumptions'!N14 | ... U24: ='3F. Revenue & COGS Assumptions'!R14 | V24: =((J24)+(K24)+(L24)+(M24)+(N24)+(O24)+(P24)+(Q24)+(R24)+(S24)+(T24)+(U24))
D25: Year 4 | F25: 37 - 48 | J25: ='3F. Revenue & COGS Assumptions'!G15 | K25: ='3F. Revenue & COGS Assumptions'!H15 | L25: ='3F. Revenue & COGS Assumptions'!I15 | M25: ='3F. Revenue & COGS Assumptions'!J15 | N25: ='3F. Revenue & COGS Assumptions'!K15 | O25: ='3F. Revenue & COGS Assumptions'!L15 | P25: ='3F. Revenue & COGS Assumptions'!M15 | Q25: ='3F. Revenue & COGS Assumptions'!N15 | ... U25: ='3F. Revenue & COGS Assumptions'!R15 | V25: =((J25)+(K25)+(L25)+(M25)+(N25)+(O25)+(P25)+(Q25)+(R25)+(S25)+(T25)+(U25))
D26: Year 5 | F26: 49 - 60 | J26: ='3F. Revenue & COGS Assumptions'!G16 | K26: ='3F. Revenue & COGS Assumptions'!H16 | L26: ='3F. Revenue & COGS Assumptions'!I16 | M26: ='3F. Revenue & COGS Assumptions'!J16 | N26: ='3F. Revenue & COGS Assumptions'!K16 | O26: ='3F. Revenue & COGS Assumptions'!L16 | P26: ='3F. Revenue & COGS Assumptions'!M16 | Q26: ='3F. Revenue & COGS Assumptions'!N16 | ... U26: ='3F. Revenue & COGS Assumptions'!R16 | V26: =((J26)+(K26)+(L26)+(M26)+(N26)+(O26)+(P26)+(Q26)+(R26)+(S26)+(T26)+(U26))
D27: Year 6 | F27: 61 - 72 | J27: ='3F. Revenue & COGS Assumptions'!G17 | K27: ='3F. Revenue & COGS Assumptions'!H17 | L27: ='3F. Revenue & COGS Assumptions'!I17 | M27: ='3F. Revenue & COGS Assumptions'!J17 | N27: ='3F. Revenue & COGS Assumptions'!K17 | O27: ='3F. Revenue & COGS Assumptions'!L17 | P27: ='3F. Revenue & COGS Assumptions'!M17 | Q27: ='3F. Revenue & COGS Assumptions'!N17 | ... U27: ='3F. Revenue & COGS Assumptions'!R17 | V27: =((J27)+(K27)+(L27)+(M27)+(N27)+(O27)+(P27)+(Q27)+(R27)+(S27)+(T27)+(U27))
B30: II. | D30: Customer Attrition | J30: Fiscal Years 1 - 6
D33: Year | F33: Months | J33: Month 1 | K33: Month 2 | L33: Month 3 | M33: Month 4 | N33: Month 5 | O33: Month 6 | P33: Month 7 | Q33: Month 8 | R33: Month 9 | S33: Month 10 | T33: Month 11 | U33: Month 12 | V33: Ʃ, Full-Year
D36: Year 0 | F36: -12 - -1
D37: Year 1 | F37: 1 - 12 | J37: ='3E. Tel. Attrit. Renew. Reward'!G100 | K37: ='3E. Tel. Attrit. Renew. Reward'!H100 | L37: ='3E. Tel. Attrit. Renew. Reward'!I100 | M37: ='3E. Tel. Attrit. Renew. Reward'!J100 | N37: ='3E. Tel. Attrit. Renew. Reward'!K100 | O37: ='3E. Tel. Attrit. Renew. Reward'!L100 | P37: ='3E. Tel. Attrit. Renew. Reward'!M100 | Q37: ='3E. Tel. Attrit. Renew. Reward'!N100 | ... U37: ='3E. Tel. Attrit. Renew. Reward'!R100 | V37: =((J37)+(K37)+(L37)+(M37)+(N37)+(O37)+(P37)+(Q37)+(R37)+(S37)+(T37)+(U37))
D38: Year 2 | F38: 13 - 24 | J38: ='3E. Tel. Attrit. Renew. Reward'!S100 | K38: ='3E. Tel. Attrit. Renew. Reward'!T100 | L38: ='3E. Tel. Attrit. Renew. Reward'!U100 | M38: ='3E. Tel. Attrit. Renew. Reward'!V100 | N38: ='3E. Tel. Attrit. Renew. Reward'!W100 | O38: ='3E. Tel. Attrit. Renew. Reward'!X100 | P38: ='3E. Tel. Attrit. Renew. Reward'!Y100 | Q38: ='3E. Tel. Attrit. Renew. Reward'!Z100 | ... U38: ='3E. Tel. Attrit. Renew. Reward'!AD100 | V38: =((J38)+(K38)+(L38)+(M38)+(N38)+(O38)+(P38)+(Q38)+(R38)+(S38)+(T38)+(U38))
D39: Year 3 | F39: 25 - 36 | J39: ='3E. Tel. Attrit. Renew. Reward'!AE100 | K39: ='3E. Tel. Attrit. Renew. Reward'!AF100 | L39: ='3E. Tel. Attrit. Renew. Reward'!AG100 | M39: ='3E. Tel. Attrit. Renew. Reward'!AH100 | N39: ='3E. Tel. Attrit. Renew. Reward'!AI100 | O39: ='3E. Tel. Attrit. Renew. Reward'!AJ100 | P39: ='3E. Tel. Attrit. Renew. Reward'!AK100 | Q39: ='3E. Tel. Attrit. Renew. Reward'!AL100 | ... U39: ='3E. Tel. Attrit. Renew. Reward'!AP100 | V39: =((J39)+(K39)+(L39)+(M39)+(N39)+(O39)+(P39)+(Q39)+(R39)+(S39)+(T39)+(U39))
D40: Year 4 | F40: 37 - 48 | J40: ='3E. Tel. Attrit. Renew. Reward'!AQ100 | K40: ='3E. Tel. Attrit. Renew. Reward'!AR100 | L40: ='3E. Tel. Attrit. Renew. Reward'!AS100 | M40: ='3E. Tel. Attrit. Renew. Reward'!AT100 | N40: ='3E. Tel. Attrit. Renew. Reward'!AU100 | O40: ='3E. Tel. Attrit. Renew. Reward'!AV100 | P40: ='3E. Tel. Attrit. Renew. Reward'!AW100 | Q40: ='3E. Tel. Attrit. Renew. Reward'!AX100 | ... U40: ='3E. Tel. Attrit. Renew. Reward'!BB100 | V40: =((J40)+(K40)+(L40)+(M40)+(N40)+(O40)+(P40)+(Q40)+(R40)+(S40)+(T40)+(U40))
D41: Year 5 | F41: 49 - 60 | J41: ='3E. Tel. Attrit. Renew. Reward'!BC100 | K41: ='3E. Tel. Attrit. Renew. Reward'!BD100 | L41: ='3E. Tel. Attrit. Renew. Reward'!BE100 | M41: ='3E. Tel. Attrit. Renew. Reward'!BF100 | N41: ='3E. Tel. Attrit. Renew. Reward'!BG100 | O41: ='3E. Tel. Attrit. Renew. Reward'!BH100 | P41: ='3E. Tel. Attrit. Renew. Reward'!BI100 | Q41: ='3E. Tel. Attrit. Renew. Reward'!BJ100 | ... U41: ='3E. Tel. Attrit. Renew. Reward'!BN100 | V41: =((J41)+(K41)+(L41)+(M41)+(N41)+(O41)+(P41)+(Q41)+(R41)+(S41)+(T41)+(U41))
D42: Year 6 | F42: 61 - 72 | J42: ='3E. Tel. Attrit. Renew. Reward'!BO100 | K42: ='3E. Tel. Attrit. Renew. Reward'!BP100 | L42: ='3E. Tel. Attrit. Renew. Reward'!BQ100 | M42: ='3E. Tel. Attrit. Renew. Reward'!BR100 | N42: ='3E. Tel. Attrit. Renew. Reward'!BS100 | O42: ='3E. Tel. Attrit. Renew. Reward'!BT100 | P42: ='3E. Tel. Attrit. Renew. Reward'!BU100 | Q42: ='3E. Tel. Attrit. Renew. Reward'!BV100 | ... U42: ='3E. Tel. Attrit. Renew. Reward'!BZ100 | V42: =((J42)+(K42)+(L42)+(M42)+(N42)+(O42)+(P42)+(Q42)+(R42)+(S42)+(T42)+(U42))
B45: III. | D45: Renewals | J45: Fiscal Years 1 - 6
D48: Year | F48: Months | J48: Month 1 | K48: Month 2 | L48: Month 3 | M48: Month 4 | N48: Month 5 | O48: Month 6 | P48: Month 7 | Q48: Month 8 | R48: Month 9 | S48: Month 10 | T48: Month 11 | U48: Month 12 | V48: Ʃ, Full-Year
D51: Year 0 | F51: -12 - -1
D52: Year 1 | F52: 1 - 12 | J52: ='3E. Tel. Attrit. Renew. Reward'!G201 | K52: ='3E. Tel. Attrit. Renew. Reward'!H201 | L52: ='3E. Tel. Attrit. Renew. Reward'!I201 | M52: ='3E. Tel. Attrit. Renew. Reward'!J201 | N52: ='3E. Tel. Attrit. Renew. Reward'!K201 | O52: ='3E. Tel. Attrit. Renew. Reward'!L201 | P52: ='3E. Tel. Attrit. Renew. Reward'!M201 | Q52: ='3E. Tel. Attrit. Renew. Reward'!N201 | ... U52: ='3E. Tel. Attrit. Renew. Reward'!R201 | V52: =((J52)+(K52)+(L52)+(M52)+(N52)+(O52)+(P52)+(Q52)+(R52)+(S52)+(T52)+(U52))
